Workbook

Sheet Costing
A1: N/A | B1: N/A | C1: N/A | E1: On Hand | F1: U/M | G1: Avg Cost | H1: Asset Value | I1: % of Tot Asset | J1: Items in Sales Sheet & in Costing Sheet, But not in ENTRY Sheet. The Items Showing FALSE to be Added in Entry Sheet.
A2: =IF(B2=0,0,COUNTIF(B$1:B2,2)) -> 0 | B2: =IF(G2=0,0,IF(COUNTIFS(Sales!B$1:B$151,C2,Sales!C$1:C$151,D2)>0,0,IF(COUNTIFS(Sales!B$1:B$151,C2,Sales!C$1:C$151,D2)=0,IF(LEFT(D2,5)="Total",0,2),0))) -> 0 | C2: =IFERROR(IF(LEFT(D2,5)="Total",RIGHT(D2,LEN(D2)-6),C3),"TOTAL") -> GC-Hand Bags | D2: Inventory
A3: =IF(B3=0,0,COUNTIF(B$1:B3,2)) -> 0 | B3: =IF(G3=0,0,IF(COUNTIFS(Sales!B$1:B$151,C3,Sales!C$1:C$151,D3)>0,0,IF(COUNTIFS(Sales!B$1:B$151,C3,Sales!C$1:C$151,D3)=0,IF(LEFT(D3,5)="Total",0,2),0))) -> 0 | C3: =IFERROR(IF(LEFT(D3,5)="Total",RIGHT(D3,LEN(D3)-6),C4),"TOTAL") -> GC-Hand Bags | D3: Shoes
A4: =IF(B4=0,0,COUNTIF(B$1:B4,2)) -> 0 | B4: =IF(G4=0,0,IF(COUNTIFS(Sales!B$1:B$151,C4,Sales!C$1:C$151,D4)>0,0,IF(COUNTIFS(Sales!B$1:B$151,C4,Sales!C$1:C$151,D4)=0,IF(LEFT(D4,5)="Total",0,2),0))) -> 0 | C4: =IFERROR(IF(LEFT(D4,5)="Total",RIGHT(D4,LEN(D4)-6),C5),"TOTAL") -> GC-Hand Bags | D4: GC-Shoes & Hand Bags | J4: =IF(C4=0,TRUE,IF(COUNTIFS(ENTRY!B:B,C4,ENTRY!C:C,D4)=1,TRUE,FALSE)) -> TRUE
A5: =IF(B5=0,0,COUNTIF(B$1:B5,2)) -> 0 | B5: =IF(G5=0,0,IF(COUNTIFS(Sales!B$1:B$151,C5,Sales!C$1:C$151,D5)>0,0,IF(COUNTIFS(Sales!B$1:B$151,C5,Sales!C$1:C$151,D5)=0,IF(LEFT(D5,5)="Total",0,2),0))) -> 0 | C5: =IFERROR(IF(LEFT(D5,5)="Total",RIGHT(D5,LEN(D5)-6),C6),"TOTAL") -> GC-Hand Bags | D5: GC-Hand Bags | J5: =IF(C5=0,TRUE,IF(COUNTIFS(ENTRY!B:B,C5,ENTRY!C:C,D5)=1,TRUE,FALSE)) -> TRUE
A6: =IF(B6=0,0,COUNTIF(B$1:B6,2)) -> 0 | B6: =IF(G6=0,0,IF(COUNTIFS(Sales!B$1:B$151,C6,Sales!C$1:C$151,D6)>0,0,IF(COUNTIFS(Sales!B$1:B$151,C6,Sales!C$1:C$151,D6)=0,IF(LEFT(D6,5)="Total",0,2),0))) -> 0 | C6: =IFERROR(IF(LEFT(D6,5)="Total",RIGHT(D6,LEN(D6)-6),C7),"TOTAL") -> GC-Hand Bags | D6: BBC1 | J6: =IF(C6=0,TRUE,IF(COUNTIFS(ENTRY!B:B,C6,ENTRY!C:C,D6)=1,TRUE,FALSE)) -> TRUE | K6: =VLOOKUP(D6,ENTRY!C:D,2,0) -> FG-CAPS-1-BALE-45KG
A7: =IF(B7=0,0,COUNTIF(B$1:B7,2)) -> 0 | B7: =IF(G7=0,0,IF(COUNTIFS(Sales!B$1:B$151,C7,Sales!C$1:C$151,D7)>0,0,IF(COUNTIFS(Sales!B$1:B$151,C7,Sales!C$1:C$151,D7)=0,IF(LEFT(D7,5)="Total",0,2),0))) -> 0 | C7: =IFERROR(IF(LEFT(D7,5)="Total",RIGHT(D7,LEN(D7)-6),C8),"TOTAL") -> GC-Hand Bags | D7: BBC2 | E7: 15 | F7: Bales | G7: =H7/E7 -> 106.284 | H7: 1594.26 | J7: =IF(C7=0,TRUE,IF(COUNTIFS(ENTRY!B:B,C7,ENTRY!C:C,D7)=1,TRUE,FALSE)) -> TRUE | K7: =VLOOKUP(D7,ENTRY!C:D,2,0) -> FG-CAPS-2-BALE-45KG
A8: =IF(B8=0,0,COUNTIF(B$1:B8,2)) -> 0 | B8: =IF(G8=0,0,IF(COUNTIFS(Sales!B$1:B$151,C8,Sales!C$1:C$151,D8)>0,0,IF(COUNTIFS(Sales!B$1:B$151,C8,Sales!C$1:C$151,D8)=0,IF(LEFT(D8,5)="Total",0,2),0))) -> 0 | C8: =IFERROR(IF(LEFT(D8,5)="Total",RIGHT(D8,LEN(D8)-6),C9),"TOTAL") -> GC-Hand Bags | D8: HB2 NewGrade-Yellow | E8: 44 | F8: Bales | G8: =H8/E8 -> 73.398636 | H8: 3229.54 | J8: =IF(C8=0,TRUE,IF(COUNTIFS(ENTRY!B:B,C8,ENTRY!C:C,D8)=1,TRUE,FALSE)) -> TRUE | K8: =VLOOKUP(D8,ENTRY!C:D,2,0) -> FG-HANDBAGS-2-BALE-45KG
A9: =IF(B9=0,0,COUNTIF(B$1:B9,2)) -> 0 | B9: =IF(G9=0,0,IF(COUNTIFS(Sales!B$1:B$151,C9,Sales!C$1:C$151,D9)>0,0,IF(COUNTIFS(Sales!B$1:B$151,C9,Sales!C$1:C$151,D9)=0,IF(LEFT(D9,5)="Total",0,2),0))) -> 0 | C9: =IFERROR(IF(LEFT(D9,5)="Total",RIGHT(D9,LEN(D9)-6),C10),"TOTAL") -> GC-Hand Bags | D9: Laptop Bags#1 | F9: Bales | J9: =IF(C9=0,TRUE,IF(COUNTIFS(ENTRY!B:B,C9,ENTRY!C:C,D9)=1,TRUE,FALSE)) -> TRUE
A10: =IF(B10=0,0,COUNTIF(B$1:B10,2)) -> 0 | B10: =IF(G10=0,0,IF(COUNTIFS(Sales!B$1:B$151,C10,Sales!C$1:C$151,D10)>0,0,IF(COUNTIFS(Sales!B$1:B$151,C10,Sales!C$1:C$151,D10)=0,IF(LEFT(D10,5)="Total",0,2),0))) -> 0 | C10: =IFERROR(IF(LEFT(D10,5)="Total",RIGHT(D10,LEN(D10)-6),C11),"TOTAL") -> GC-Hand Bags | D10: Handbag A | E10: 1 | F10: Bales | G10: =H10/E10 -> 88.33 | H10: 88.33 | J10: =IF(C10=0,TRUE,IF(COUNTIFS(ENTRY!B:B,C10,ENTRY!C:C,D10)=1,TRUE,FALSE)) -> TRUE | K10: =VLOOKUP(D10,ENTRY!C:D,2,0) -> FG-HANDBAGS-A-BALE-45KG
A11: =IF(B11=0,0,COUNTIF(B$1:B11,2)) -> 0 | B11: =IF(G11=0,0,IF(COUNTIFS(Sales!B$1:B$151,C11,Sales!C$1:C$151,D11)>0,0,IF(COUNTIFS(Sales!B$1:B$151,C11,Sales!C$1:C$151,D11)=0,IF(LEFT(D11,5)="Total",0,2),0))) -> 0 | C11: =IFERROR(IF(LEFT(D11,5)="Total",RIGHT(D11,LEN(D11)-6),C12),"TOTAL") -> GC-Hand Bags | D11: HB3 | E11: 6 | F11: GC | G11: =H11/E11 -> 47.145 | H11: 282.87 | J11: =IF(C11=0,TRUE,IF(COUNTIFS(ENTRY!B:B,C11,ENTRY!C:C,D11)=1,TRUE,FALSE)) -> TRUE | K11: =VLOOKUP(D11,ENTRY!C:D,2,0) -> FG-HANDBAGS-3-BALE-50KG
A12: =IF(B12=0,0,COUNTIF(B$1:B12,2)) -> 0 | B12: =IF(G12=0,0,IF(COUNTIFS(Sales!B$1:B$151,C12,Sales!C$1:C$151,D12)>0,0,IF(COUNTIFS(Sales!B$1:B$151,C12,Sales!C$1:C$151,D12)=0,IF(LEFT(D12,5)="Total",0,2),0))) -> 0 | C12: =IFERROR(IF(LEFT(D12,5)="Total",RIGHT(D12,LEN(D12)-6),C13),"TOTAL") -> GC-Hand Bags | D12: Laptop Bags#2 | F12: Bag | J12: =IF(C12=0,TRUE,IF(COUNTIFS(ENTRY!B:B,C12,ENTRY!C:C,D12)=1,TRUE,FALSE)) -> TRUE
A13: =IF(B13=0,0,COUNTIF(B$1:B13,2)) -> 0 | B13: =IF(G13=0,0,IF(COUNTIFS(Sales!B$1:B$151,C13,Sales!C$1:C$151,D13)>0,0,IF(COUNTIFS(Sales!B$1:B$151,C13,Sales!C$1:C$151,D13)=0,IF(LEFT(D13,5)="Total",0,2),0))) -> 0 | C13: =IFERROR(IF(LEFT(D13,5)="Total",RIGHT(D13,LEN(D13)-6),C14),"TOTAL") -> GC-Hand Bags | D13: School Bag No.1 | F13: Bales | J13: =IF(C13=0,TRUE,IF(COUNTIFS(ENTRY!B:B,C13,ENTRY!C:C,D13)=1,TRUE,FALSE)) -> TRUE | K13: =VLOOKUP(D13,ENTRY!C:D,2,0) -> FG-SCHOOL BAGS-1-BALE-45KG
A14: =IF(B14=0,0,COUNTIF(B$1:B14,2)) -> 0 | B14: =IF(G14=0,0,IF(COUNTIFS(Sales!B$1:B$151,C14,Sales!C$1:C$151,D14)>0,0,IF(COUNTIFS(Sales!B$1:B$151,C14,Sales!C$1:C$151,D14)=0,IF(LEFT(D14,5)="Total",0,2),0))) -> 0 | C14: =IFERROR(IF(LEFT(D14,5)="Total",RIGHT(D14,LEN(D14)-6),C15),"TOTAL") -> GC-Hand Bags | D14: Travel Bag - Big Sack-90kg | E14: 2 | F14: Bag | G14: =H14/E14 -> 176.075 | H14: 352.15 | J14: =IF(C14=0,TRUE,IF(COUNTIFS(ENTRY!B:B,C14,ENTRY!C:C,D14)=1,TRUE,FALSE)) -> TRUE | K14: =VLOOKUP(D14,ENTRY!C:D,2,0) -> FG-BAGS-TRAVEL BAGS-BAG-90KG
A15: =IF(B15=0,0,COUNTIF(B$1:B15,2)) -> 0 | B15: =IF(G15=0,0,IF(COUNTIFS(Sales!B$1:B$151,C15,Sales!C$1:C$151,D15)>0,0,IF(COUNTIFS(Sales!B$1:B$151,C15,Sales!C$1:C$151,D15)=0,IF(LEFT(D15,5)="Total",0,2),0))) -> 0 | C15: =IFERROR(IF(LEFT(D15,5)="Total",RIGHT(D15,LEN(D15)-6),C16),"TOTAL") -> GC-Hand Bags | D15: TRAVELBAG No.1 | F15: Bales | J15: =IF(C15=0,TRUE,IF(COUNTIFS(ENTRY!B:B,C15,ENTRY!C:C,D15)=1,TRUE,FALSE)) -> TRUE | K15: =VLOOKUP(D15,ENTRY!C:D,2,0) -> FG-TRAVEL BAGS-1-BALE-45KG
A16: =IF(B16=0,0,COUNTIF(B$1:B16,2)) -> 0 | B16: =IF(G16=0,0,IF(COUNTIFS(Sales!B$1:B$151,C16,Sales!C$1:C$151,D16)>0,0,IF(COUNTIFS(Sales!B$1:B$151,C16,Sales!C$1:C$151,D16)=0,IF(LEFT(D16,5)="Total",0,2),0))) -> 0 | C16: =IFERROR(IF(LEFT(D16,5)="Total",RIGHT(D16,LEN(D16)-6),C17),"TOTAL") -> GC-Hand Bags | D16: Used Wool Caps | F16: Bales | J16: =IF(C16=0,TRUE,IF(COUNTIFS(ENTRY!B:B,C16,ENTRY!C:C,D16)=1,TRUE,FALSE)) -> TRUE
A17: =IF(B17=0,0,COUNTIF(B$1:B17,2)) -> 0 | B17: =IF(G17=0,0,IF(COUNTIFS(Sales!B$1:B$151,C17,Sales!C$1:C$151,D17)>0,0,IF(COUNTIFS(Sales!B$1:B$151,C17,Sales!C$1:C$151,D17)=0,IF(LEFT(D17,5)="Total",0,2),0))) -> 0 | C17: =IFERROR(IF(LEFT(D17,5)="Total",RIGHT(D17,LEN(D17)-6),C19),"TOTAL") -> GC-Hand Bags | D17: BELT#3 | F17: Bag | J17: =IF(C17=0,TRUE,IF(COUNTIFS(ENTRY!B:B,C17,ENTRY!C:C,D17)=1,TRUE,FALSE)) -> TRUE
A18: =IF(B18=0,0,COUNTIF(B$1:B18,2)) -> 0 | B18: =IF(G18=0,0,IF(COUNTIFS(Sales!B$1:B$151,C18,Sales!C$1:C$151,D18)>0,0,IF(COUNTIFS(Sales!B$1:B$151,C18,Sales!C$1:C$151,D18)=0,IF(LEFT(D18,5)="Total",0,2),0))) -> 0 | C18: GC-Hand Bags | D18: BELT-NEW GRADE-45 KG | F18: Bag | J18: =IF(C18=0,TRUE,IF(COUNTIFS(ENTRY!B:B,C18,ENTRY!C:C,D18)=1,TRUE,FALSE)) -> TRUE
A19: =IF(B19=0,0,COUNTIF(B$1:B19,2)) -> 0 | B19: =IF(G19=0,0,IF(COUNTIFS(Sales!B$1:B$151,C19,Sales!C$1:C$151,D19)>0,0,IF(COUNTIFS(Sales!B$1:B$151,C19,Sales!C$1:C$151,D19)=0,IF(LEFT(D19,5)="Total",0,2),0))) -> 0 | C19: =IFERROR(IF(LEFT(D19,5)="Total",RIGHT(D19,LEN(D19)-6),C20),"TOTAL") -> GC-Hand Bags | D19: Total GC-Hand Bags | F19: -MIXED- | J19: =IF(C19=0,TRUE,IF(COUNTIFS(ENTRY!B:B,C19,ENTRY!C:C,D19)=1,TRUE,FALSE)) -> TRUE
A20: =IF(B20=0,0,COUNTIF(B$1:B20,2)) -> 0 | B20: =IF(G20=0,0,IF(COUNTIFS(Sales!B$1:B$151,C20,Sales!C$1:C$151,D20)>0,0,IF(COUNTIFS(Sales!B$1:B$151,C20,Sales!C$1:C$151,D20)=0,IF(LEFT(D20,5)="Total",0,2),0))) -> 0 | C20: =IFERROR(IF(LEFT(D20,5)="Total",RIGHT(D20,LEN(D20)-6),C21),"TOTAL") -> GC-Shoes | D20: GC-Shoes | J20: =IF(C20=0,TRUE,IF(COUNTIFS(ENTRY!B:B,C20,ENTRY!C:C,D20)=1,TRUE,FALSE)) -> TRUE
A21: =IF(B21=0,0,COUNTIF(B$1:B21,2)) -> 0 | B21: =IF(G21=0,0,IF(COUNTIFS(Sales!B$1:B$151,C21,Sales!C$1:C$151,D21)>0,0,IF(COUNTIFS(Sales!B$1:B$151,C21,Sales!C$1:C$151,D21)=0,IF(LEFT(D21,5)="Total",0,2),0))) -> 0 | C21: =IFERROR(IF(LEFT(D21,5)="Total",RIGHT(D21,LEN(D21)-6),C22),"TOTAL") -> GC-Shoes | D21: Golf Men Shoes | E21: 1 | F21: Bag | G21: =H21/E21 -> 77.65 | H21: 77.65 | J21: =IF(C21=0,TRUE,IF(COUNTIFS(ENTRY!B:B,C21,ENTRY!C:C,D21)=1,TRUE,FALSE)) -> TRUE | K21: =VLOOKUP(D21,ENTRY!C:D,2,0) -> FG-MEN-GOLF-1+2-BAG-25KG
A22: =IF(B22=0,0,COUNTIF(B$1:B22,2)) -> 0 | B22: =IF(G22=0,0,IF(COUNTIFS(Sales!B$1:B$151,C22,Sales!C$1:C$151,D22)>0,0,IF(COUNTIFS(Sales!B$1:B$151,C22,Sales!C$1:C$151,D22)=0,IF(LEFT(D22,5)="Total",0,2),0))) -> 0 | C22: =IFERROR(IF(LEFT(D22,5)="Total",RIGHT(D22,LEN(D22)-6),C23),"TOTAL") -> GC-Shoes | D22: Big Size Men 1 | F22: Bag | J22: =IF(C22=0,TRUE,IF(COUNTIFS(ENTRY!B:B,C22,ENTRY!C:C,D22)=1,TRUE,FALSE)) -> TRUE
A23: =IF(B23=0,0,COUNTIF(B$1:B23,2)) -> 0 | B23: =IF(G23=0,0,IF(COUNTIFS(Sales!B$1:B$151,C23,Sales!C$1:C$151,D23)>0,0,IF(COUNTIFS(Sales!B$1:B$151,C23,Sales!C$1:C$151,D23)=0,IF(LEFT(D23,5)="Total",0,2),0))) -> 0 | C23: =IFERROR(IF(LEFT(D23,5)="Total",RIGHT(D23,LEN(D23)-6),C24),"TOTAL") -> GC-Shoes | D23: Big Size Sports 1+2 | F23: Bag | J23: =IF(C23=0,TRUE,IF(COUNTIFS(ENTRY!B:B,C23,ENTRY!C:C,D23)=1,TRUE,FALSE)) -> TRUE
A24: =IF(B24=0,0,COUNTIF(B$1:B24,2)) -> 0 | B24: =IF(G24=0,0,IF(COUNTIFS(Sales!B$1:B$151,C24,Sales!C$1:C$151,D24)>0,0,IF(COUNTIFS(Sales!B$1:B$151,C24,Sales!C$1:C$151,D24)=0,IF(LEFT(D24,5)="Total",0,2),0))) -> 0 | C24: =IFERROR(IF(LEFT(D24,5)="Total",RIGHT(D24,LEN(D24)-6),C25),"TOTAL") -> GC-Shoes | D24: C2 | E24: 112 | F24: GC | G24: =H24/E24 -> 150.3158 | H24: 16835.37 | J24: =IF(C24=0,TRUE,IF(COUNTIFS(ENTRY!B:B,C24,ENTRY!C:C,D24)=1,TRUE,FALSE)) -> TRUE | K24: =VLOOKUP(D24,ENTRY!C:D,2,0) -> FG-CHILDREN-2-BAG-25KG
A25: =IF(B25=0,0,COUNTIF(B$1:B25,2)) -> 0 | B25: =IF(G25=0,0,IF(COUNTIFS(Sales!B$1:B$151,C25,Sales!C$1:C$151,D25)>0,0,IF(COUNTIFS(Sales!B$1:B$151,C25,Sales!C$1:C$151,D25)=0,IF(LEFT(D25,5)="Total",0,2),0))) -> 0 | C25: =IFERROR(IF(LEFT(D25,5)="Total",RIGHT(D25,LEN(D25)-6),C26),"TOTAL") -> GC-Shoes | D25: C3 | E25: 137 | F25: GC | G25: =H25/E25 -> 66.209489 | H25: 9070.7 | J25: =IF(C25=0,TRUE,IF(COUNTIFS(ENTRY!B:B,C25,ENTRY!C:C,D25)=1,TRUE,FALSE)) -> TRUE | K25: =VLOOKUP(D25,ENTRY!C:D,2,0) -> FG-CHILDREN-3-BAG-25KG
A26: =IF(B26=0,0,COUNTIF(B$1:B26,2)) -> 0 | B26: =IF(G26=0,0,IF(COUNTIFS(Sales!B$1:B$151,C26,Sales!C$1:C$151,D26)>0,0,IF(COUNTIFS(Sales!B$1:B$151,C26,Sales!C$1:C$151,D26)=0,IF(LEFT(D26,5)="Total",0,2),0))) -> 0 | C26: =IFERROR(IF(LEFT(D26,5)="Total",RIGHT(D26,LEN(D26)-6),C27),"TOTAL") -> GC-Shoes | D26: C4 | E26: 60 | F26: Bag | G26: =H26/E26 -> 30.781 | H26: 1846.86 | J26: =IF(C26=0,TRUE,IF(COUNTIFS(ENTRY!B:B,C26,ENTRY!C:C,D26)=1,TRUE,FALSE)) -> TRUE | K26: =VLOOKUP(D26,ENTRY!C:D,2,0) -> FG-CHILDREN-4-BAG-25KG
A27: =IF(B27=0,0,COUNTIF(B$1:B27,2)) -> 0 | B27: =IF(G27=0,0,IF(COUNTIFS(Sales!B$1:B$151,C27,Sales!C$1:C$151,D27)>0,0,IF(COUNTIFS(Sales!B$1:B$151,C27,Sales!C$1:C$151,D27)=0,IF(LEFT(D27,5)="Total",0,2),0))) -> 0 | C27: =IFERROR(IF(LEFT(D27,5)="Total",RIGHT(D27,LEN(D27)-6),C28),"TOTAL") -> GC-Shoes | D27: CB1 | E27: 373 | F27: Bag | G27: =H27/E27 -> 185.78327 | H27: 69297.16 | J27: =IF(C27=0,TRUE,IF(COUNTIFS(ENTRY!B:B,C27,ENTRY!C:C,D27)=1,TRUE,FALSE)) -> TRUE | K27: =VLOOKUP(D27,ENTRY!C:D,2,0) -> FG-BOOTS-CH-1-BAG-25KG
A28: =IF(B28=0,0,COUNTIF(B$1:B28,2)) -> 0 | B28: =IF(G28=0,0,IF(COUNTIFS(Sales!B$1:B$151,C28,Sales!C$1:C$151,D28)>0,0,IF(COUNTIFS(Sales!B$1:B$151,C28,Sales!C$1:C$151,D28)=0,IF(LEFT(D28,5)="Total",0,2),0))) -> 0 | C28: =IFERROR(IF(LEFT(D28,5)="Total",RIGHT(D28,LEN(D28)-6),C29),"TOTAL") -> GC-Shoes | D28: CB2 | E28: 326 | F28: Bag | G28: =H28/E28 -> 99.935982 | H28: 32579.13 | J28: =IF(C28=0,TRUE,IF(COUNTIFS(ENTRY!B:B,C28,ENTRY!C:C,D28)=1,TRUE,FALSE)) -> TRUE | K28: =VLOOKUP(D28,ENTRY!C:D,2,0) -> FG-BOOTS-CH-2-BAG-25KG
A29: =IF(B29=0,0,COUNTIF(B$1:B29,2)) -> 0 | B29: =IF(G29=0,0,IF(COUNTIFS(Sales!B$1:B$151,C29,Sales!C$1:C$151,D29)>0,0,IF(COUNTIFS(Sales!B$1:B$151,C29,Sales!C$1:C$151,D29)=0,IF(LEFT(D29,5)="Total",0,2),0))) -> 0 | C29: =IFERROR(IF(LEFT(D29,5)="Total",RIGHT(D29,LEN(D29)-6),C30),"TOTAL") -> GC-Shoes | D29: Gum Boots Adult | E29: 45 | F29: Bag | G29: =H29/E29 -> 43.889111 | H29: 1975.01 | J29: =IF(C29=0,TRUE,IF(COUNTIFS(ENTRY!B:B,C29,ENTRY!C:C,D29)=1,TRUE,FALSE)) -> TRUE | K29: =VLOOKUP(D29,ENTRY!C:D,2,0) -> FG-BOOTS-ADULT-GUM BOOT-BAG-28KG
A30: =IF(B30=0,0,COUNTIF(B$1:B30,2)) -> 0 | B30: =IF(G30=0,0,IF(COUNTIFS(Sales!B$1:B$151,C30,Sales!C$1:C$151,D30)>0,0,IF(COUNTIFS(Sales!B$1:B$151,C30,Sales!C$1:C$151,D30)=0,IF(LEFT(D30,5)="Total",0,2),0))) -> 0 | C30: =IFERROR(IF(LEFT(D30,5)="Total",RIGHT(D30,LEN(D30)-6),C31),"TOTAL") -> GC-Shoes | D30: CB3 | E30: 494 | F30: Bag | G30: =H30/E30 -> 59.467874 | H30: 29377.13 | J30: =IF(C30=0,TRUE,IF(COUNTIFS(ENTRY!B:B,C30,ENTRY!C:C,D30)=1,TRUE,FALSE)) -> TRUE | K30: =VLOOKUP(D30,ENTRY!C:D,2,0) -> FG-BOOTS-CH-3-BAG-25KG
A31: =IF(B31=0,0,COUNTIF(B$1:B31,2)) -> 0 | B31: =IF(G31=0,0,IF(COUNTIFS(Sales!B$1:B$151,C31,Sales!C$1:C$151,D31)>0,0,IF(COUNTIFS(Sales!B$1:B$151,C31,Sales!C$1:C$151,D31)=0,IF(LEFT(D31,5)="Total",0,2),0))) -> 0 | C31: =IFERROR(IF(LEFT(D31,5)="Total",RIGHT(D31,LEN(D31)-6),C32),"TOTAL") -> GC-Shoes | D31: Cream Ladies Shoes | E31: 10 | F31: Bag | G31: =H31/E31 -> 244.239 | H31: 2442.39 | J31: =IF(C31=0,TRUE,IF(COUNTIFS(ENTRY!B:B,C31,ENTRY!C:C,D31)=1,TRUE,FALSE)) -> TRUE | K31: =VLOOKUP(D31,ENTRY!C:D,2,0) -> FG-LADIES-CREAM-BOX-25KG
A32: =IF(B32=0,0,COUNTIF(B$1:B32,2)) -> 0 | B32: =IF(G32=0,0,IF(COUNTIFS(Sales!B$1:B$151,C32,Sales!C$1:C$151,D32)>0,0,IF(COUNTIFS(Sales!B$1:B$151,C32,Sales!C$1:C$151,D32)=0,IF(LEFT(D32,5)="Total",0,2),0))) -> 0 | C32: =IFERROR(IF(LEFT(D32,5)="Total",RIGHT(D32,LEN(D32)-6),C33),"TOTAL") -> GC-Shoes | D32: Crocs No.1 | F32: Bag | J32: =IF(C32=0,TRUE,IF(COUNTIFS(ENTRY!B:B,C32,ENTRY!C:C,D32)=1,TRUE,FALSE)) -> TRUE | K32: =VLOOKUP(D32,ENTRY!C:D,2,0) -> FG-CANVAS-UN-CROCS-1-BAG-10KG
A33: =IF(B33=0,0,COUNTIF(B$1:B33,2)) -> 0 | B33: =IF(G33=0,0,IF(COUNTIFS(Sales!B$1:B$151,C33,Sales!C$1:C$151,D33)>0,0,IF(COUNTIFS(Sales!B$1:B$151,C33,Sales!C$1:C$151,D33)=0,IF(LEFT(D33,5)="Total",0,2),0))) -> 0 | C33: =IFERROR(IF(LEFT(D33,5)="Total",RIGHT(D33,LEN(D33)-6),C34),"TOTAL") -> GC-Shoes | D33: Crocs No.2 | E33: 13 | F33: Bag | G33: =H33/E33 -> 51.336923 | H33: 667.38 | J33: =IF(C33=0,TRUE,IF(COUNTIFS(ENTRY!B:B,C33,ENTRY!C:C,D33)=1,TRUE,FALSE)) -> TRUE | K33: =VLOOKUP(D33,ENTRY!C:D,2,0) -> FG-CANVAS-UN-CROCS-2-BAG-10KG
A34: =IF(B34=0,0,COUNTIF(B$1:B34,2)) -> 0 | B34: =IF(G34=0,0,IF(COUNTIFS(Sales!B$1:B$151,C34,Sales!C$1:C$151,D34)>0,0,IF(COUNTIFS(Sales!B$1:B$151,C34,Sales!C$1:C$151,D34)=0,IF(LEFT(D34,5)="Total",0,2),0))) -> 0 | C34: =IFERROR(IF(LEFT(D34,5)="Total",RIGHT(D34,LEN(D34)-6),C35),"TOTAL") -> GC-Shoes | D34: Ladies2-Close | E34: 90 | F34: Bag | G34: =H34/E34 -> 76.659222 | H34: 6899.33 | J34: =IF(C34=0,TRUE,IF(COUNTIFS(ENTRY!B:B,C34,ENTRY!C:C,D34)=1,TRUE,FALSE)) -> TRUE | K34: =VLOOKUP(D34,ENTRY!C:D,2,0) -> FG-LADIES-L-CLOSE-2-BAG-25KG
A35: =IF(B35=0,0,COUNTIF(B$1:B35,2)) -> 0 | B35: =IF(G35=0,0,IF(COUNTIFS(Sales!B$1:B$151,C35,Sales!C$1:C$151,D35)>0,0,IF(COUNTIFS(Sales!B$1:B$151,C35,Sales!C$1:C$151,D35)=0,IF(LEFT(D35,5)="Total",0,2),0))) -> 0 | C35: =IFERROR(IF(LEFT(D35,5)="Total",RIGHT(D35,LEN(D35)-6),C36),"TOTAL") -> GC-Shoes | D35: Ladies2-Mix | E35: 251 | F35: Bag | G35: =H35/E35 -> 50.82992 | H35: 12758.31 | J35: =IF(C35=0,TRUE,IF(COUNTIFS(ENTRY!B:B,C35,ENTRY!C:C,D35)=1,TRUE,FALSE)) -> TRUE | K35: =VLOOKUP(D35,ENTRY!C:D,2,0) -> FG-LADIES-L-MIX-2-BAG-25KG
A36: =IF(B36=0,0,COUNTIF(B$1:B36,2)) -> 0 | B36: =IF(G36=0,0,IF(COUNTIFS(Sales!B$1:B$151,C36,Sales!C$1:C$151,D36)>0,0,IF(COUNTIFS(Sales!B$1:B$151,C36,Sales!C$1:C$151,D36)=0,IF(LEFT(D36,5)="Total",0,2),0))) -> 0 | C36: =IFERROR(IF(LEFT(D36,5)="Total",RIGHT(D36,LEN(D36)-6),C37),"TOTAL") -> GC-Shoes | D36: Ladies2-Open | F36: Bag | J36: =IF(C36=0,TRUE,IF(COUNTIFS(ENTRY!B:B,C36,ENTRY!C:C,D36)=1,TRUE,FALSE)) -> TRUE | K36: =VLOOKUP(D36,ENTRY!C:D,2,0) -> FG-LADIES-OPEN FLAT-2-BAG-25KG
A37: =IF(B37=0,0,COUNTIF(B$1:B37,2)) -> 0 | B37: =IF(G37=0,0,IF(COUNTIFS(Sales!B$1:B$151,C37,Sales!C$1:C$151,D37)>0,0,IF(COUNTIFS(Sales!B$1:B$151,C37,Sales!C$1:C$151,D37)=0,IF(LEFT(D37,5)="Total",0,2),0))) -> 0 | C37: =IFERROR(IF(LEFT(D37,5)="Total",RIGHT(D37,LEN(D37)-6),C38),"TOTAL") -> GC-Shoes | D37: LHH Bulky Shoes A | F37: Bag | J37: =IF(C37=0,TRUE,IF(COUNTIFS(ENTRY!B:B,C37,ENTRY!C:C,D37)=1,TRUE,FALSE)) -> TRUE | K37: =VLOOKUP(D37,ENTRY!C:D,2,0) -> FG-LADIES-HH BULKY-1-BAG-25KG
A38: =IF(B38=0,0,COUNTIF(B$1:B38,2)) -> 0 | B38: =IF(G38=0,0,IF(COUNTIFS(Sales!B$1:B$151,C38,Sales!C$1:C$151,D38)>0,0,IF(COUNTIFS(Sales!B$1:B$151,C38,Sales!C$1:C$151,D38)=0,IF(LEFT(D38,5)="Total",0,2),0))) -> 0 | C38: =IFERROR(IF(LEFT(D38,5)="Total",RIGHT(D38,LEN(D38)-6),C39),"TOTAL") -> GC-Shoes | D38: LHH Bulky Shoes B | E38: 9 | F38: Bag | G38: =H38/E38 -> 41.58 | H38: 374.22 | J38: =IF(C38=0,TRUE,IF(COUNTIFS(ENTRY!B:B,C38,ENTRY!C:C,D38)=1,TRUE,FALSE)) -> TRUE | K38: =VLOOKUP(D38,ENTRY!C:D,2,0) -> FG-LADIES-HH BULKY-2-BAG-25KG
A39: =IF(B39=0,0,COUNTIF(B$1:B39,2)) -> 0 | B39: =IF(G39=0,0,IF(COUNTIFS(Sales!B$1:B$151,C39,Sales!C$1:C$151,D39)>0,0,IF(COUNTIFS(Sales!B$1:B$151,C39,Sales!C$1:C$151,D39)=0,IF(LEFT(D39,5)="Total",0,2),0))) -> 0 | C39: =IFERROR(IF(LEFT(D39,5)="Total",RIGHT(D39,LEN(D39)-6),C40),"TOTAL") -> GC-Shoes | D39: LHH Shoes B | F39: Bag | J39: =IF(C39=0,TRUE,IF(COUNTIFS(ENTRY!B:B,C39,ENTRY!C:C,D39)=1,TRUE,FALSE)) -> TRUE
A40: =IF(B40=0,0,COUNTIF(B$1:B40,2)) -> 0 | B40: =IF(G40=0,0,IF(COUNTIFS(Sales!B$1:B$151,C40,Sales!C$1:C$151,D40)>0,0,IF(COUNTIFS(Sales!B$1:B$151,C40,Sales!C$1:C$151,D40)=0,IF(LEFT(D40,5)="Total",0,2),0))) -> 0 | C40: =IFERROR(IF(LEFT(D40,5)="Total",RIGHT(D40,LEN(D40)-6),C41),"TOTAL") -> GC-Shoes | D40: M1 | E40: 28 | F40: GC | G40: =H40/E40 -> 267.88929 | H40: 7500.9 | J40: =IF(C40=0,TRUE,IF(COUNTIFS(ENTRY!B:B,C40,ENTRY!C:C,D40)=1,TRUE,FALSE)) -> TRUE | K40: =VLOOKUP(D40,ENTRY!C:D,2,0) -> FG-MEN-1-BAG-25KG
A41: =IF(B41=0,0,COUNTIF(B$1:B41,2)) -> 0 | B41: =IF(G41=0,0,IF(COUNTIFS(Sales!B$1:B$151,C41,Sales!C$1:C$151,D41)>0,0,IF(COUNTIFS(Sales!B$1:B$151,C41,Sales!C$1:C$151,D41)=0,IF(LEFT(D41,5)="Total",0,2),0))) -> 0 | C41: =IFERROR(IF(LEFT(D41,5)="Total",RIGHT(D41,LEN(D41)-6),C42),"TOTAL") -> GC-Shoes | D41: M2 | E41: 181 | F41: Bag | G41: =H41/E41 -> 166.02337 | H41: 30050.23 | J41: =IF(C41=0,TRUE,IF(COUNTIFS(ENTRY!B:B,C41,ENTRY!C:C,D41)=1,TRUE,FALSE)) -> TRUE | K41: =VLOOKUP(D41,ENTRY!C:D,2,0) -> FG-MEN-2-BAG-25KG
A42: =IF(B42=0,0,COUNTIF(B$1:B42,2)) -> 0 | B42: =IF(G42=0,0,IF(COUNTIFS(Sales!B$1:B$151,C42,Sales!C$1:C$151,D42)>0,0,IF(COUNTIFS(Sales!B$1:B$151,C42,Sales!C$1:C$151,D42)=0,IF(LEFT(D42,5)="Total",0,2),0))) -> 0 | C42: =IFERROR(IF(LEFT(D42,5)="Total",RIGHT(D42,LEN(D42)-6),C43),"TOTAL") -> GC-Shoes | D42: M3 | E42: 705 | F42: Bag | G42: =H42/E42 -> 100.18092 | H42: 70627.55 | J42: =IF(C42=0,TRUE,IF(COUNTIFS(ENTRY!B:B,C42,ENTRY!C:C,D42)=1,TRUE,FALSE)) -> TRUE | K42: =VLOOKUP(D42,ENTRY!C:D,2,0) -> FG-MEN-3-BAG-25KG
A43: =IF(B43=0,0,COUNTIF(B$1:B43,2)) -> 0 | B43: =IF(G43=0,0,IF(COUNTIFS(Sales!B$1:B$151,C43,Sales!C$1:C$151,D43)>0,0,IF(COUNTIFS(Sales!B$1:B$151,C43,Sales!C$1:C$151,D43)=0,IF(LEFT(D43,5)="Total",0,2),0))) -> 0 | C43: =IFERROR(IF(LEFT(D43,5)="Total",RIGHT(D43,LEN(D43)-6),C44),"TOTAL") -> GC-Shoes | D43: M4 | E43: 93 | F43: GC | G43: =H43/E43 -> 53.800215 | H43: 5003.42 | J43: =IF(C43=0,TRUE,IF(COUNTIFS(ENTRY!B:B,C43,ENTRY!C:C,D43)=1,TRUE,FALSE)) -> TRUE | K43: =VLOOKUP(D43,ENTRY!C:D,2,0) -> FG-MEN-4-BAG-25KG
A44: =IF(B44=0,0,COUNTIF(B$1:B44,2)) -> 0 | B44: =IF(G44=0,0,IF(COUNTIFS(Sales!B$1:B$151,C44,Sales!C$1:C$151,D44)>0,0,IF(COUNTIFS(Sales!B$1:B$151,C44,Sales!C$1:C$151,D44)=0,IF(LEFT(D44,5)="Total",0,2),0))) -> 0 | C44: =IFERROR(IF(LEFT(D44,5)="Total",RIGHT(D44,LEN(D44)-6),C45),"TOTAL") -> GC-Shoes | D44: MB1 | E44: 6 | F44: Bag | G44: =H44/E44 -> 220.37 | H44: 1322.22 | J44: =IF(C44=0,TRUE,IF(COUNTIFS(ENTRY!B:B,C44,ENTRY!C:C,D44)=1,TRUE,FALSE)) -> TRUE | K44: =VLOOKUP(D44,ENTRY!C:D,2,0) -> FG-BOOTS-M-1-BAG-25KG
A45: =IF(B45=0,0,COUNTIF(B$1:B45,2)) -> 0 | B45: =IF(G45=0,0,IF(COUNTIFS(Sales!B$1:B$151,C45,Sales!C$1:C$151,D45)>0,0,IF(COUNTIFS(Sales!B$1:B$151,C45,Sales!C$1:C$151,D45)=0,IF(LEFT(D45,5)="Total",0,2),0))) -> 0 | C45: =IFERROR(IF(LEFT(D45,5)="Total",RIGHT(D45,LEN(D45)-6),C46),"TOTAL") -> GC-Shoes | D45: MB2 | E45: 92 | F45: Bag | G45: =H45/E45 -> 118.19174 | H45: 10873.64 | J45: =IF(C45=0,TRUE,IF(COUNTIFS(ENTRY!B:B,C45,ENTRY!C:C,D45)=1,TRUE,FALSE)) -> TRUE | K45: =VLOOKUP(D45,ENTRY!C:D,2,0) -> FG-BOOTS-M-2-BAG-25KG
A46: =IF(B46=0,0,COUNTIF(B$1:B46,2)) -> 0 | B46: =IF(G46=0,0,IF(COUNTIFS(Sales!B$1:B$151,C46,Sales!C$1:C$151,D46)>0,0,IF(COUNTIFS(Sales!B$1:B$151,C46,Sales!C$1:C$151,D46)=0,IF(LEFT(D46,5)="Total",0,2),0))) -> 0 | C46: =IFERROR(IF(LEFT(D46,5)="Total",RIGHT(D46,LEN(D46)-6),C47),"TOTAL") -> GC-Shoes | D46: MB3 | E46: 385 | F46: Bag | G46: =H46/E46 -> 60.268208 | H46: 23203.26 | J46: =IF(C46=0,TRUE,IF(COUNTIFS(ENTRY!B:B,C46,ENTRY!C:C,D46)=1,TRUE,FALSE)) -> TRUE | K46: =VLOOKUP(D46,ENTRY!C:D,2,0) -> FG-BOOTS-M-3-BAG-25KG
A47: =IF(B47=0,0,COUNTIF(B$1:B47,2)) -> 0 | B47: =IF(G47=0,0,IF(COUNTIFS(Sales!B$1:B$151,C47,Sales!C$1:C$151,D47)>0,0,IF(COUNTIFS(Sales!B$1:B$151,C47,Sales!C$1:C$151,D47)=0,IF(LEFT(D47,5)="Total",0,2),0))) -> 0 | C47: =IFERROR(IF(LEFT(D47,5)="Total",RIGHT(D47,LEN(D47)-6),C48),"TOTAL") -> GC-Shoes | D47: N1131-L2+G3+G4 Mix Bags | F47: Bag | J47: =IF(C47=0,TRUE,IF(COUNTIFS(ENTRY!B:B,C47,ENTRY!C:C,D47)=1,TRUE,FALSE)) -> TRUE | K47: =VLOOKUP(D47,ENTRY!C:D,2,0) -> FG-COMBINATION-N1131-BAG-25KG
A48: =IF(B48=0,0,COUNTIF(B$1:B48,2)) -> 0 | B48: =IF(G48=0,0,IF(COUNTIFS(Sales!B$1:B$151,C48,Sales!C$1:C$151,D48)>0,0,IF(COUNTIFS(Sales!B$1:B$151,C48,Sales!C$1:C$151,D48)=0,IF(LEFT(D48,5)="Total",0,2),0))) -> 0 | C48: =IFERROR(IF(LEFT(D48,5)="Total",RIGHT(D48,LEN(D48)-6),C49),"TOTAL") -> GC-Shoes | D48: RollerShoes | E48: 32 | F48: Bag | G48: =H48/E48 -> 75.25875 | H48: 2408.28 | J48: =IF(C48=0,TRUE,IF(COUNTIFS(ENTRY!B:B,C48,ENTRY!C:C,D48)=1,TRUE,FALSE)) -> TRUE | K48: =VLOOKUP(D48,ENTRY!C:D,2,0) -> FG-ROLL SHOES-BAG-25KG
A49: =IF(B49=0,0,COUNTIF(B$1:B49,2)) -> 0 | B49: =IF(G49=0,0,IF(COUNTIFS(Sales!B$1:B$151,C49,Sales!C$1:C$151,D49)>0,0,IF(COUNTIFS(Sales!B$1:B$151,C49,Sales!C$1:C$151,D49)=0,IF(LEFT(D49,5)="Total",0,2),0))) -> 0 | C49: =IFERROR(IF(LEFT(D49,5)="Total",RIGHT(D49,LEN(D49)-6),C50),"TOTAL") -> GC-Shoes | D49: S3 | E49: 9 | F49: Bag | G49: =H49/E49 -> 122.85889 | H49: 1105.73 | J49: =IF(C49=0,TRUE,IF(COUNTIFS(ENTRY!B:B,C49,ENTRY!C:C,D49)=1,TRUE,FALSE)) -> TRUE | K49: =VLOOKUP(D49,ENTRY!C:D,2,0) -> FG-SPORTS-3-BAG-25KG
A50: =IF(B50=0,0,COUNTIF(B$1:B50,2)) -> 0 | B50: =IF(G50=0,0,IF(COUNTIFS(Sales!B$1:B$151,C50,Sales!C$1:C$151,D50)>0,0,IF(COUNTIFS(Sales!B$1:B$151,C50,Sales!C$1:C$151,D50)=0,IF(LEFT(D50,5)="Total",0,2),0))) -> 0 | C50: =IFERROR(IF(LEFT(D50,5)="Total",RIGHT(D50,LEN(D50)-6),C51),"TOTAL") -> GC-Shoes | D50: S4 | E50: 386 | F50: Bag | G50: =H50/E50 -> 52.35956 | H50: 20210.79 | J50: =IF(C50=0,TRUE,IF(COUNTIFS(ENTRY!B:B,C50,ENTRY!C:C,D50)=1,TRUE,FALSE)) -> TRUE | K50: =VLOOKUP(D50,ENTRY!C:D,2,0) -> FG-SPORTS-4-BAG-25KG
A51: =IF(B51=0,0,COUNTIF(B$1:B51,2)) -> 0 | B51: =IF(G51=0,0,IF(COUNTIFS(Sales!B$1:B$151,C51,Sales!C$1:C$151,D51)>0,0,IF(COUNTIFS(Sales!B$1:B$151,C51,Sales!C$1:C$151,D51)=0,IF(LEFT(D51,5)="Total",0,2),0))) -> 0 | C51: =IFERROR(IF(LEFT(D51,5)="Total",RIGHT(D51,LEN(D51)-6),C52),"TOTAL") -> GC-Shoes | D51: Safety Boot 1 | J51: =IF(C51=0,TRUE,IF(COUNTIFS(ENTRY!B:B,C51,ENTRY!C:C,D51)=1,TRUE,FALSE)) -> TRUE | K51: =VLOOKUP(D51,ENTRY!C:D,2,0) -> FG-BOOTS-SAFETY-1-BAG-25KG
A52: =IF(B52=0,0,COUNTIF(B$1:B52,2)) -> 0 | B52: =IF(G52=0,0,IF(COUNTIFS(Sales!B$1:B$151,C52,Sales!C$1:C$151,D52)>0,0,IF(COUNTIFS(Sales!B$1:B$151,C52,Sales!C$1:C$151,D52)=0,IF(LEFT(D52,5)="Total",0,2),0))) -> 0 | C52: =IFERROR(IF(LEFT(D52,5)="Total",RIGHT(D52,LEN(D52)-6),C53),"TOTAL") -> GC-Shoes | D52: Safety Boot 2 | F52: Bag | J52: =IF(C52=0,TRUE,IF(COUNTIFS(ENTRY!B:B,C52,ENTRY!C:C,D52)=1,TRUE,FALSE)) -> TRUE | K52: =VLOOKUP(D52,ENTRY!C:D,2,0) -> FG-BOOTS-SAFETY-2-BAG-25KG
A53: =IF(B53=0,0,COUNTIF(B$1:B53,2)) -> 0 | B53: =IF(G53=0,0,IF(COUNTIFS(Sales!B$1:B$151,C53,Sales!C$1:C$151,D53)>0,0,IF(COUNTIFS(Sales!B$1:B$151,C53,Sales!C$1:C$151,D53)=0,IF(LEFT(D53,5)="Total",0,2),0))) -> 0 | C53: =IFERROR(IF(LEFT(D53,5)="Total",RIGHT(D53,LEN(D53)-6),C54),"TOTAL") -> GC-Shoes | D53: Safety Boot 3 | E53: 1 | F53: Bag | G53: =H53/E53 -> 62.9 | H53: 62.9 | J53: =IF(C53=0,TRUE,IF(COUNTIFS(ENTRY!B:B,C53,ENTRY!C:C,D53)=1,TRUE,FALSE)) -> TRUE | K53: =VLOOKUP(D53,ENTRY!C:D,2,0) -> FG-BOOTS-SAFETY-3-BAG-25KG
A54: =IF(B54=0,0,COUNTIF(B$1:B54,2)) -> 0 | B54: =IF(G54=0,0,IF(COUNTIFS(Sales!B$1:B$151,C54,Sales!C$1:C$151,D54)>0,0,IF(COUNTIFS(Sales!B$1:B$151,C54,Sales!C$1:C$151,D54)=0,IF(LEFT(D54,5)="Total",0,2),0))) -> 0 | C54: =IFERROR(IF(LEFT(D54,5)="Total",RIGHT(D54,LEN(D54)-6),C56),"TOTAL") -> GC-Shoes | D54: Sandal 1 | F54: Bag | J54: =IF(C54=0,TRUE,IF(COUNTIFS(ENTRY!B:B,C54,ENTRY!C:C,D54)=1,TRUE,FALSE)) -> TRUE | K54: =VLOOKUP(D54,ENTRY!C:D,2,0) -> FG-CANVAS-M-SANDAL-1-BAG-25KG
A55: =IF(B55=0,0,COUNTIF(B$1:B55,2)) -> 0 | B55: =IF(G55=0,0,IF(COUNTIFS(Sales!B$1:B$151,C55,Sales!C$1:C$151,D55)>0,0,IF(COUNTIFS(Sales!B$1:B$151,C55,Sales!C$1:C$151,D55)=0,IF(LEFT(D55,5)="Total",0,2),0))) -> 0 | C55: =IFERROR(IF(LEFT(D55,5)="Total",RIGHT(D55,LEN(D55)-6),C57),"TOTAL") -> GC-Shoes | D55: Sandal2 Men | F55: Bag | J55: =IF(C55=0,TRUE,IF(COUNTIFS(ENTRY!B:B,C55,ENTRY!C:C,D55)=1,TRUE,FALSE)) -> TRUE | K55: =VLOOKUP(D55,ENTRY!C:D,2,0) -> FG-CANVAS-M-SANDAL-2-BAG-25KG
A56: =IF(B56=0,0,COUNTIF(B$1:B56,2)) -> 0 | B56: =IF(G56=0,0,IF(COUNTIFS(Sales!B$1:B$151,C56,Sales!C$1:C$151,D56)>0,0,IF(COUNTIFS(Sales!B$1:B$151,C56,Sales!C$1:C$151,D56)=0,IF(LEFT(D56,5)="Total",0,2),0))) -> 0 | C56: =IFERROR(IF(LEFT(D56,5)="Total",RIGHT(D56,LEN(D56)-6),C57),"TOTAL") -> GC-Shoes | D56: Sandal 3 | F56: Bag | J56: =IF(C56=0,TRUE,IF(COUNTIFS(ENTRY!B:B,C56,ENTRY!C:C,D56)=1,TRUE,FALSE)) -> TRUE | K56: =VLOOKUP(D56,ENTRY!C:D,2,0) -> FG-CANVAS-M-SANDAL-3-BAG-25KG
A57: =IF(B57=0,0,COUNTIF(B$1:B57,2)) -> 0 | B57: =IF(G57=0,0,IF(COUNTIFS(Sales!B$1:B$151,C57,Sales!C$1:C$151,D57)>0,0,IF(COUNTIFS(Sales!B$1:B$151,C57,Sales!C$1:C$151,D57)=0,IF(LEFT(D57,5)="Total",0,2),0))) -> 0 | C57: =IFERROR(IF(LEFT(D57,5)="Total",RIGHT(D57,LEN(D57)-6),C58),"TOTAL") -> GC-Shoes | D57: SB1 | F57: Bag | J57: =IF(C57=0,TRUE,IF(COUNTIFS(ENTRY!B:B,C57,ENTRY!C:C,D57)=1,TRUE,FALSE)) -> TRUE | K57: =VLOOKUP(D57,ENTRY!C:D,2,0) -> FG-BOOTS-M-SPORT-1-BAG-25KG
A58: =IF(B58=0,0,COUNTIF(B$1:B58,2)) -> 0 | B58: =IF(G58=0,0,IF(COUNTIFS(Sales!B$1:B$151,C58,Sales!C$1:C$151,D58)>0,0,IF(COUNTIFS(Sales!B$1:B$151,C58,Sales!C$1:C$151,D58)=0,IF(LEFT(D58,5)="Total",0,2),0))) -> 0 | C58: =IFERROR(IF(LEFT(D58,5)="Total",RIGHT(D58,LEN(D58)-6),C59),"TOTAL") -> GC-Shoes | D58: SB2 | F58: Bag | J58: =IF(C58=0,TRUE,IF(COUNTIFS(ENTRY!B:B,C58,ENTRY!C:C,D58)=1,TRUE,FALSE)) -> TRUE | K58: =VLOOKUP(D58,ENTRY!C:D,2,0) -> FG-BOOTS-M-SPORT-2-BAG-25KG
A59: =IF(B59=0,0,COUNTIF(B$1:B59,2)) -> 0 | B59: =IF(G59=0,0,IF(COUNTIFS(Sales!B$1:B$151,C59,Sales!C$1:C$151,D59)>0,0,IF(COUNTIFS(Sales!B$1:B$151,C59,Sales!C$1:C$151,D59)=0,IF(LEFT(D59,5)="Total",0,2),0))) -> 0 | C59: =IFERROR(IF(LEFT(D59,5)="Total",RIGHT(D59,LEN(D59)-6),C60),"TOTAL") -> GC-Shoes | D59: SS Mix (Slipper Sandal) | E59: 50 | F59: Bag | G59: =H59/E59 -> 77.6926 | H59: 3884.63 | J59: =IF(C59=0,TRUE,IF(COUNTIFS(ENTRY!B:B,C59,ENTRY!C:C,D59)=1,TRUE,FALSE)) -> TRUE | K59: =VLOOKUP(D59,ENTRY!C:D,2,0) -> FG-CANVAS-SS-1+2-BAG-25KG
A60: =IF(B60=0,0,COUNTIF(B$1:B60,2)) -> 0 | B60: =IF(G60=0,0,IF(COUNTIFS(Sales!B$1:B$151,C60,Sales!C$1:C$151,D60)>0,0,IF(COUNTIFS(Sales!B$1:B$151,C60,Sales!C$1:C$151,D60)=0,IF(LEFT(D60,5)="Total",0,2),0))) -> 0 | C60: =IFERROR(IF(LEFT(D60,5)="Total",RIGHT(D60,LEN(D60)-6),C61),"TOTAL") -> GC-Shoes | D60: Winter CB1 | F60: Bag | J60: =IF(C60=0,TRUE,IF(COUNTIFS(ENTRY!B:B,C60,ENTRY!C:C,D60)=1,TRUE,FALSE)) -> TRUE
A61: =IF(B61=0,0,COUNTIF(B$1:B61,2)) -> 0 | B61: =IF(G61=0,0,IF(COUNTIFS(Sales!B$1:B$151,C61,Sales!C$1:C$151,D61)>0,0,IF(COUNTIFS(Sales!B$1:B$151,C61,Sales!C$1:C$151,D61)=0,IF(LEFT(D61,5)="Total",0,2),0))) -> 0 | C61: =IFERROR(IF(LEFT(D61,5)="Total",RIGHT(D61,LEN(D61)-6),C62),"TOTAL") -> GC-Shoes | D61: Winter CB2 | E61: 388 | F61: Bag | G61: =H61/E61 -> 68.789253 | H61: 26690.23 | J61: =IF(C61=0,TRUE,IF(COUNTIFS(ENTRY!B:B,C61,ENTRY!C:C,D61)=1,TRUE,FALSE)) -> TRUE | K61: =VLOOKUP(D61,ENTRY!C:D,2,0) -> FG-BOOTS-WINTER-CH-2-BAG-25KG
A62: =IF(B62=0,0,COUNTIF(B$1:B62,2)) -> 0 | B62: =IF(G62=0,0,IF(COUNTIFS(Sales!B$1:B$151,C62,Sales!C$1:C$151,D62)>0,0,IF(COUNTIFS(Sales!B$1:B$151,C62,Sales!C$1:C$151,D62)=0,IF(LEFT(D62,5)="Total",0,2),0))) -> 0 | C62: =IFERROR(IF(LEFT(D62,5)="Total",RIGHT(D62,LEN(D62)-6),C63),"TOTAL") -> GC-Shoes | D62: Winter CB3 | E62: 1100 | F62: Bag | G62: =H62/E62 -> 35.249518 | H62: 38774.47 | J62: =IF(C62=0,TRUE,IF(COUNTIFS(ENTRY!B:B,C62,ENTRY!C:C,D62)=1,TRUE,FALSE)) -> TRUE | K62: =VLOOKUP(D62,ENTRY!C:D,2,0) -> FG-BOOTS-WINTER-CH-3-BAG-25KG
A63: =IF(B63=0,0,COUNTIF(B$1:B63,2)) -> 0 | B63: =IF(G63=0,0,IF(COUNTIFS(Sales!B$1:B$151,C63,Sales!C$1:C$151,D63)>0,0,IF(COUNTIFS(Sales!B$1:B$151,C63,Sales!C$1:C$151,D63)=0,IF(LEFT(D63,5)="Total",0,2),0))) -> 0 | C63: =IFERROR(IF(LEFT(D63,5)="Total",RIGHT(D63,LEN(D63)-6),C64),"TOTAL") -> GC-Shoes | D63: Winter MB2 | F63: Bag | J63: =IF(C63=0,TRUE,IF(COUNTIFS(ENTRY!B:B,C63,ENTRY!C:C,D63)=1,TRUE,FALSE)) -> TRUE | K63: =VLOOKUP(D63,ENTRY!C:D,2,0) -> FG-BOOTS-WINTER-M-2-BAG-25KG
A64: =IF(B64=0,0,COUNTIF(B$1:B64,2)) -> 0 | B64: =IF(G64=0,0,IF(COUNTIFS(Sales!B$1:B$151,C64,Sales!C$1:C$151,D64)>0,0,IF(COUNTIFS(Sales!B$1:B$151,C64,Sales!C$1:C$151,D64)=0,IF(LEFT(D64,5)="Total",0,2),0))) -> 0 | C64: =IFERROR(IF(LEFT(D64,5)="Total",RIGHT(D64,LEN(D64)-6),C65),"TOTAL") -> GC-Shoes | D64: Winter MB3 | E64: 527 | F64: Bag | G64: =H64/E64 -> 41.832808 | H64: 22045.89 | J64: =IF(C64=0,TRUE,IF(COUNTIFS(ENTRY!B:B,C64,ENTRY!C:C,D64)=1,TRUE,FALSE)) -> TRUE | K64: =VLOOKUP(D64,ENTRY!C:D,2,0) -> FG-BOOTS-WINTER-M-3-BAG-25KG
A65: =IF(B65=0,0,COUNTIF(B$1:B65,2)) -> 0 | B65: =IF(G65=0,0,IF(COUNTIFS(Sales!B$1:B$151,C65,Sales!C$1:C$151,D65)>0,0,IF(COUNTIFS(Sales!B$1:B$151,C65,Sales!C$1:C$151,D65)=0,IF(LEFT(D65,5)="Total",0,2),0))) -> 0 | C65: =IFERROR(IF(LEFT(D65,5)="Total",RIGHT(D65,LEN(D65)-6),C66),"TOTAL") -> GC-Shoes | D65: Total GC-Shoes | E65: =SUM(E6:E64) -> 5972 | F65: -MIXED- | H65: =SUM(H6:H64) -> 453511.93 | J65: =IF(C65=0,TRUE,IF(COUNTIFS(ENTRY!B:B,C65,ENTRY!C:C,D65)=1,TRUE,FALSE)) -> TRUE
A66: =IF(B66=0,0,COUNTIF(B$1:B66,2)) -> 0 | B66: =IF(G66=0,0,IF(COUNTIFS(Sales!B$1:B$151,C66,Sales!C$1:C$151,D66)>0,0,IF(COUNTIFS(Sales!B$1:B$151,C66,Sales!C$1:C$151,D66)=0,IF(LEFT(D66,5)="Total",0,2),0))) -> 0 | C66: =IFERROR(IF(LEFT(D66,5)="Total",RIGHT(D66,LEN(D66)-6),C67),"TOTAL") -> GC-Shoes & Hand Bags | D66: Total GC-Shoes & Hand Bags | E66: =E65 -> 5972 | F66: -MIXED- | H66: =H65 -> 453511.93 | J66: =IF(C66=0,TRUE,IF(COUNTIFS(ENTRY!B:B,C66,ENTRY!C:C,D66)=1,TRUE,FALSE)) -> TRUE
A67: =IF(B67=0,0,COUNTIF(B$1:B67,2)) -> 0 | B67: =IF(G67=0,0,IF(COUNTIFS(Sales!B$1:B$151,C67,Sales!C$1:C$151,D67)>0,0,IF(COUNTIFS(Sales!B$1:B$151,C67,Sales!C$1:C$151,D67)=0,IF(LEFT(D67,5)="Total",0,2),0))) -> 0 | C67: =IFERROR(IF(LEFT(D67,5)="Total",RIGHT(D67,LEN(D67)-6),C68),"TOTAL") -> Shoes | D67: Total Shoes | E67: =E66 -> 5972 | F67: -MIXED- | H67: =H66 -> 453511.93 | J67: =IF(C67=0,TRUE,IF(COUNTIFS(ENTRY!B:B,C67,ENTRY!C:C,D67)=1,TRUE,FALSE)) -> TRUE
A68: =IF(B68=0,0,COUNTIF(B$1:B68,2)) -> 0 | B68: =IF(G68=0,0,IF(COUNTIFS(Sales!B$1:B$151,C68,Sales!C$1:C$151,D68)>0,0,IF(COUNTIFS(Sales!B$1:B$151,C68,Sales!C$1:C$151,D68)=0,IF(LEFT(D68,5)="Total",0,2),0))) -> 0 | C68: =IFERROR(IF(LEFT(D68,5)="Total",RIGHT(D68,LEN(D68)-6),C69),"TOTAL") -> Inventory | D68: Total Inventory | E68: =E67 -> 5972 | F68: -MIXED- | H68: =H67 -> 453511.93 | J68: =IF(C68=0,TRUE,IF(COUNTIFS(ENTRY!B:B,C68,ENTRY!C:C,D68)=1,TRUE,FALSE)) -> TRUE
A69: =IF(B69=0,0,COUNTIF(B$1:B69,2)) -> 0 | B69: =IF(G69=0,0,IF(COUNTIFS(Sales!B$1:B$151,C69,Sales!C$1:C$151,D69)>0,0,IF(COUNTIFS(Sales!B$1:B$151,C69,Sales!C$1:C$151,D69)=0,IF(LEFT(D69,5)="Total",0,2),0))) -> 0 | C69: =IFERROR(IF(LEFT(D69,5)="Total",RIGHT(D69,LEN(D69)-6),C70),"TOTAL") -> TOTAL | D69: TOTAL | E69: =E68 -> 5972 | F69: -MIXED- | H69: =H68 -> 453511.93 | J69: =IF(C69=0,TRUE,IF(COUNTIFS(ENTRY!B:B,C69,ENTRY!C:C,D69)=1,TRUE,FALSE)) -> TRUE

Sheet Sales
E1: 1st Cell Manual, 2nd Cell onwards Drag to Right----> | F1: 45292 | G1: =F1+1 -> 45293 | H1: =G1+1 -> 45294 | I1: =H1+1 -> 45295 | J1: =I1+1 -> 45296 | K1: =J1+1 -> 45297 | L1: =K1+1 -> 45298 | M1: 45299 | N1: 45300 | O1: 45301 | P1: 45302 | Q1: 45303 | R1: 45304 | S1: =R1+1 -> 45305 | T1: =S1+1 -> 45306 | U1: =T1+1 -> 45307 | V1: =U1+1 -> 45308 | W1: =V1+1 -> 45309 | X1: =W1+1 -> 45310 | Y1: =X1+1 -> 45311 | Z1: =Y1+1 -> 45312 | ... AI1: =AH1+1 -> 45321 | AJ1: 45322 | AK1: =AJ1+1 -> 45323 | AL1: =AK1+1 -> 45324 | AM1: =AL1+1 -> 45325 | AN1: =AM1+1 -> 45326 | AO1: =AN1+1 -> 45327 | AP1: =AO1+1 -> 45328 | AQ1: =AP1+1 -> 45329 | AR1: =AQ1+1 -> 45330 | ... BE1: =BD1+1 -> 45343 | BF1: 45344 | BG1: 45345 | BH1: 45346 | BI1: 45347 | BJ1: 45348 | BK1: 45349 | BL1: 45350 | BM1: 45351 | BN1: 45352 | BO1: 45353 | BP1: 45354 | BQ1: 45355 | BR1: 45356 | BS1: 45357 | BT1: 45358 | BU1: 45359 | BV1: 45360 | BW1: 45361 | BX1: 45362 | BY1: 45363 | BZ1: 45364 | CA1: 45365 | CB1: 45366 | CC1: 45367 | CD1: 45368 | CE1: 45369 | CF1: 45370 | CG1: 45371 | CH1: 45372 | CI1: 45373 | CJ1: 45374 | CK1: 45375 | CL1: 45376 | CM1: 45377 | CN1: 45378 | CO1: 45379 | CP1: 45380 | CQ1: 45381 | CR1: 45382 | CS1: 45383 | CT1: 45384 | CU1: 45385 | CV1: 45386 | CW1: 45387 | CX1: 45388 | CY1: 45389 | CZ1: 45390 | DA1: 45391 | DB1: 45392 | DC1: 45393 | DD1: 45394 | DE1: 45395 | DF1: 45396 | DG1: 45397 | DH1: 45398 | DI1: 45399 | DJ1: 45400 | DK1: 45401 | DL1: 45402 | DM1: 45403 | DN1: 45404 | DO1: 45405 | DP1: 45406 | DQ1: 45407 | DR1: 45408 | DS1: 45409 | DT1: 45410 | DU1: 45411 | DV1: 45412 | DW1: 45413 | DX1: 45414 | DY1: 45415 | DZ1: 45416 | EA1: 45417 | EB1: 45418 | EC1: 45419 | ED1: 45420 | EE1: 45421 | EF1: 45422 | EG1: 45423 | EH1: 45424 | EI1: 45425 | EJ1: 45426 | EK1: 45427 | EL1: 45428 | EM1: 45429 | EN1: 45430 | EO1: 45431 | EP1: 45432 | EQ1: 45433 | ER1: 45434 | ES1: 45435 | ET1: 45436 | EU1: 45437 | EV1: 45438 | EW1: 45439 | EX1: 45440 | EY1: 45441 | EZ1: 45442 | FA1: 45443 | FB1: 45444 | FC1: 45445 | FD1: 45446 | FE1: 45447 | FF1: 45448 | FG1: 45449 | FH1: 45450 | FI1: 45451 | FJ1: 45452 | FK1: 45453 | FL1: 45454 | FM1: 45455 | FN1: 45456 | FO1: 45457 | FP1: 45458 | FQ1: 45459 | FR1: 45460 | FS1: 45461 | FT1: 45462 | FU1: 45463 | FV1: 45464 | FW1: 45465 | FX1: 45466 | FY1: 45467 | FZ1: 45468 | GA1: 45469 | GB1: 45470 | GC1: 45471 | GD1: =GC1+1 -> 45472 | GE1: =GD1+1 -> 45473 | GF1: =GE1+1 -> 45474 | GG1: =GF1+1 -> 45475 | GH1: =GG1+1 -> 45476 | GI1: =GH1+1 -> 45477 | GJ1: =GI1+1 -> 45478 | GK1: =GJ1+1 -> 45479 | ... KH1: =KG1+1 -> 45580 | KI1: 45581 | KJ1: 45582 | KK1: 45583 | KL1: 45584 | KM1: 45585 | KN1: 45586 | KO1: 45587 | KP1: 45588 | KQ1: 45589 | KR1: 45590 | KS1: 45591 | KT1: 45592 | KU1: 45593 | KV1: 45594 | KW1: 45595 | KX1: 45596 | KY1: 45597 | KZ1: 45598 | LA1: 45599 | LB1: 45600 | LC1: 45601 | LD1: 45602 | LE1: 45603 | LF1: 45604 | LG1: 45605 | LH1: 45606 | LI1: 45607 | LJ1: 45608 | LK1: 45609 | LL1: 45610 | LM1: 45611 | LN1: 45612 | LO1: 45613 | LP1: 45614 | LQ1: 45615 | LR1: 45616 | LS1: 45617 | LT1: 45618 | LU1: 45619 | LV1: 45620 | LW1: 45621 | LX1: 45622 | LY1: 45623 | LZ1: 45624 | MA1: 45625 | MB1: 45626 | MC1: 45627 | MD1: 45628 | ME1: 45629 | MF1: 45630 | MG1: 45631 | MH1: 45632 | MI1: 45633 | MJ1: 45634 | MK1: 45635 | ML1: 45636 | MM1: 45637 | MN1: 45638 | MO1: 45639 | MP1: 45640 | MQ1: 45641 | MR1: 45642 | MS1: 45643 | MT1: 45644 | MU1: 45645 | MV1: 45646 | MW1: 45647 | MX1: 45648 | MY1: 45649 | MZ1: 45650 | NA1: 45651 | NB1: 45652 | NC1: 45653 | ND1: 45654 | NE1: 45655 | NF1: 45656 | NG1: 45657 | NH1: 45658 | NI1: 45659 | NJ1: 45660 | NK1: 45661 | NL1: 45662 | NM1: 45663 | NN1: 45664 | NO1: 45665 | NP1: 45666 | NQ1: 45667 | NR1: 45668 | NS1: 45669 | NT1: 45670 | NU1: 45671 | NV1: 45672 | NW1: 45673 | NX1: 45674 | NY1: 45675 | NZ1: 45676 | OA1: 45677 | OB1: 45678 | OC1: 45679 | OD1: 45680 | OE1: 45681 | OF1: 45682 | OG1: 45683 | OH1: 45684 | OI1: 45685 | OJ1: 45686 | OK1: 45687 | OL1: 45688 | OM1: 45689 | ON1: 45690 | OO1: 45691 | OP1: 45692 | OQ1: 45693 | OR1: 45694 | OS1: 45695 | OT1: 45696 | OU1: 45697 | OV1: 45698 | OW1: 45699 | OX1: 45700 | OY1: 45701 | OZ1: 45702 | PA1: 45703 | PB1: 45704 | PC1: 45705 | PD1: 45706 | PE1: 45707 | PF1: 45708 | PG1: 45709 | PH1: 45710 | PI1: 45711 | PJ1: 45712 | PK1: 45713 | PL1: 45714 | PM1: 45715 | PN1: 45716 | PO1: 45717 | PP1: 45718 | PQ1: 45719 | PR1: 45720 | PS1: 45721 | PT1: 45722 | PU1: 45723 | PV1: 45724 | PW1: 45725 | PX1: 45726 | PY1: 45727 | PZ1: 45728 | QA1: 45729 | QB1: 45730 | QC1: 45731 | QD1: 45732 | QE1: 45733 | QF1: 45734 | QG1: 45735 | QH1: 45736 | QI1: 45737 | QJ1: 45738 | QK1: 45739 | QL1: 45740 | QM1: 45741 | QN1: 45742 | QO1: 45743 | QP1: 45744 | QQ1: 45745 | QR1: 45746 | QS1: 45747 | QT1: 45748 | QU1: 45749 | QV1: 45750 | QW1: 45751 | QX1: 45752 | QY1: 45753 | QZ1: 45754 | RA1: 45755 | RB1: 45756 | RC1: 45757 | RD1: 45758 | RE1: 45759 | RF1: 45760 | RG1: 45761 | RH1: 45762 | RI1: 45763 | RJ1: 45764 | RK1: 45765 | RL1: 45766 | RM1: 45767 | RN1: 45768 | RO1: 45769 | RP1: 45770 | RQ1: 45771 | RR1: 45772 | RS1: 45773 | RT1: 45774 | RU1: 45775 | RV1: 45776 | RW1: 45777 | RX1: 45778 | RY1: 45779 | RZ1: 45780 | SA1: 45781 | SB1: 45782 | SC1: 45783 | SD1: 45784 | SE1: 45785 | SF1: 45786 | SG1: 45787 | SH1: 45788 | SI1: 45789 | SJ1: 45790 | SK1: 45791 | SL1: 45792 | SM1: 45793 | SN1: 45794 | SO1: 45795 | SP1: 45796 | SQ1: 45797 | SR1: 45798 | SS1: 45799 | ST1: 45800 | SU1: 45801 | SV1: 45802 | SW1: 45803 | SX1: 45804 | SY1: 45805 | SZ1: 45806 | TA1: 45807 | TB1: 45808 | TC1: 45809 | TD1: 45810 | TE1: 45811 | TF1: 45812 | TG1: 45813 | TH1: 45814 | TI1: 45815 | TJ1: 45816 | TK1: 45817 | TL1: 45818 | TM1: 45819 | TN1: 45820 | TO1: 45821 | TP1: 45822 | TQ1: 45823 | TR1: 45824 | TS1: 45825 | TT1: 45826 | TU1: 45827 | TV1: 45828 | TW1: 45829 | TX1: 45830 | TY1: 45831 | TZ1: 45832 | UA1: =TZ1+1 -> 45833 | UB1: =UA1+1 -> 45834 | UC1: =UB1+1 -> 45835 | UD1: =UC1+1 -> 45836 | UE1: =UD1+1 -> 45837 | UF1: =UE1+1 -> 45838 | UG1: =UF1+1 -> 45839 | UH1: =UG1+1 -> 45840 | ... UR1: =UQ1+1 -> 45850 | US1: 46045 | UT1: 46046 | UU1: 46047 | UV1: 46048 | UW1: 46049 | UX1: 46050 | UY1: 46051 | UZ1: 46052 | VA1: 46053 | VB1: 46054 | VC1: 46055 | VD1: 46056 | VE1: 46057 | VF1: 46058 | VG1: 46059 | VH1: 46060 | VI1: 46061 | VJ1: 46062 | VK1: 46063 | VL1: 46064 | VM1: 46065 | VN1: 46066 | VO1: 46067 | VP1: 46068 | VQ1: 46069 | VR1: 46070 | VS1: 46071 | VT1: 46072 | VU1: 46073 | VV1: 46074 | VW1: 46075 | VX1: 46076 | VY1: 46077 | VZ1: 46078 | WA1: 46079 | WB1: 46080 | WC1: 46081 | WD1: 46082 | WE1: 46083 | WF1: 46084 | WG1: 46085 | WH1: 46086 | WI1: 46087 | WJ1: 46088 | WK1: 46089 | WL1: 46090 | WM1: 46091 | WN1: 46092 | WO1: 46093 | WP1: 46094 | WQ1: 46095 | WR1: 46096 | WS1: 46097 | WT1: 46098 | WU1: 46099 | WV1: 46100 | WW1: 46101 | WX1: 46102 | WY1: 46103 | WZ1: 46104 | XA1: 46105 | XB1: 46106 | XC1: 46107 | XD1: 46108 | XE1: 46109 | XF1: 46110 | XG1: 46111 | XH1: 46112 | XI1: 46113 | XJ1: 46114 | XK1: 46115 | XL1: 46116 | XM1: 46117 | XN1: 46118 | XO1: 46119 | XP1: 46120 | XQ1: 46121 | XR1: 46122 | XS1: 46123 | XT1: 46124 | XU1: 46125 | XV1: 46126 | XW1: 46127 | XX1: 46128 | XY1: 46129 | XZ1: 46130 | YA1: 46131 | YB1: 46132 | YC1: 46133 | YD1: 46134 | YE1: 46135 | YF1: 46136 | YG1: 46137 | YH1: 46138 | YI1: 46139 | YJ1: 46140 | YK1: 46141 | YL1: 46142 | YM1: 46143 | YN1: 46144 | YO1: 46145 | YP1: 46146 | YQ1: 46147 | YR1: 46148 | YS1: 46149 | YT1: 46150 | YU1: 46151 | YV1: 46152 | YW1: 46153 | YX1: 46154 | YY1: 46155 | YZ1: 46156 | ZA1: 46157 | ZB1: 46158 | ZC1: 46159 | ZD1: 46160 | ZE1: 46161 | ZF1: 46162 | ZG1: 46163 | ZH1: 46164 | ZI1: 46165 | ZJ1: 46166 | ZK1: 46167 | ZL1: 46168 | ZM1: 46169 | ZN1: 46170 | ZO1: 46171 | ZP1: 46172 | ZQ1: 46173 | ZR1: 46174 | ZS1: 46175 | ZT1: 46176 | ZU1: 46177 | ZV1: 46178 | ZW1: 46179 | ZX1: 46180 | ZY1: 46181 | ZZ1: 46182 | AAA1: 46183 | AAB1: 46184 | AAC1: 46185 | AAD1: 46186 | AAE1: 46187 | AAF1: 46188 | AAG1: 46189 | AAH1: 46190 | AAI1: 46191 | AAJ1: 46192 | AAK1: 46193 | AAL1: 46194 | AAM1: 46195 | AAN1: 46196 | AAO1: 46197 | AAP1: 46198 | AAQ1: 46199 | AAR1: 46200 | AAS1: 46201 | AAT1: 46202 | AAU1: 46203 | AAV1: 46204 | AAW1: 46205 | AAX1: 46206 | AAY1: 46207 | AAZ1: 46208 | ABA1: 46209 | ABB1: 46210 | ABC1: 46211 | ABD1: 46212 | ABE1: 46213 | ABF1: 46214 | ABG1: 46215 | ABH1: 46216
B2: GC-Hand Bags | C2: Shoes | D2: =CELL("row",D2) -> 2 | E2: =COUNTIF(ENTRY!C$4:C$294,C2) -> 1 | F2: 0 | G2: 0 | H2: 0 | I2: 0 | J2: 0 | K2: 0 | L2: 0 | M2: 0 | N2: 0 | O2: 0 | P2: 0 | Q2: 0 | R2: 0 | S2: 0 | T2: 0 | U2: 0 | V2: 0 | W2: 0 | X2: 0 | Y2: 0 | Z2: 0 | AA2: 0 | AB2: 0 | AC2: 0 | AD2: 0 | AE2: 0 | AF2: 0 | AG2: 0 | AH2: 0 | AI2: 0 | AJ2: 0 | AK2: 0 | AL2: 0 | AM2: 0 | AN2: 0 | AO2: 0 | AP2: 0 | AQ2: 0 | AR2: 0 | AS2: 0 | AT2: 0 | AU2: 0 | AV2: 0 | AW2: 0 | AX2: 0 | AY2: 0 | AZ2: 0 | BA2: 0 | BB2: 0 | BC2: 0 | BD2: 0 | BE2: 0 | BF2: 0 | BG2: 0 | BH2: 0 | BI2: 0 | BJ2: 0 | BK2: 0 | BL2: 0 | BM2: 0 | BN2: 0 | BO2: 0 | BP2: 0 | BQ2: 0 | BR2: 0 | BS2: 0 | BT2: 0 | BU2: 0 | BV2: 0 | BW2: 0 | BX2: 0 | BY2: 0 | BZ2: 0 | CA2: 0 | CB2: 0 | CC2: 0 | CD2: 0 | CE2: 0 | CF2: 0 | CG2: 0 | CH2: 0 | CI2: 0 | CJ2: 0 | CK2: 0 | CL2: 0 | CM2: 0 | CN2: 0 | CO2: 0 | CP2: 0 | CQ2: 0 | CR2: 0 | CS2: 0 | CT2: 0 | CU2: 0 | CV2: 0 | CW2: 0 | CX2: 0 | CY2: 0 | CZ2: 0 | DA2: 0 | DB2: 0 | DC2: 0 | DD2: 0 | DE2: 0 | DF2: 0 | DG2: 0 | DH2: 0 | DI2: 0 | DJ2: 0 | DK2: 0 | DL2: 0 | DM2: 0 | DN2: 0 | DO2: 0 | DP2: 0 | DQ2: 0 | DR2: 0 | DS2: 0 | DT2: 0 | DU2: 0 | DV2: 0 | DW2: 0 | DX2: 0 | DY2: 0 | DZ2: 0 | EA2: 0 | EB2: 0 | EC2: 0 | ED2: 0 | EE2: 0 | EF2: 0 | EG2: 0 | EH2: 0 | EI2: 0 | EJ2: 0 | EK2: 0 | EL2: 0 | EM2: 0 | EN2: 0 | EO2: 0 | EP2: 0 | EQ2: 0 | ER2: 0 | ES2: 0 | ET2: 0 | EU2: 0 | EV2: 0 | EW2: 0 | EX2: 0 | EY2: 0 | EZ2: 0 | FA2: 0 | FB2: 0 | FC2: 0 | FD2: 0 | FE2: 0 | FF2: 0 | FG2: 0 | FH2: 0 | FI2: 0 | FJ2: 0 | FK2: 0 | FL2: 0 | FM2: 0 | FN2: 0 | FO2: 0 | FP2: 0 | FQ2: 0 | FR2: 0 | FS2: 0 | FT2: 0 | FU2: 0 | FV2: 0 | FW2: 0 | FX2: 0 | FY2: 0 | FZ2: 0 | GA2: 0 | GB2: 0 | GC2: 0 | GD2: 0 | GE2: 0 | GF2: 0 | GG2: 0 | GH2: 0 | GI2: 0 | GJ2: 0 | GK2: 0 | GL2: 0 | GM2: 0 | GN2: 0 | GO2: 0 | GP2: 0 | GQ2: 0 | GR2: 0 | GS2: 0 | GT2: 0 | GU2: 0 | GV2: 0 | GW2: 0 | GX2: 0 | GY2: 0 | GZ2: 0 | HA2: 0 | HB2: 0 | HC2: 0 | HD2: 0 | HE2: 0 | HF2: 0 | HG2: 0 | HH2: 0 | HI2: 0 | HJ2: 0 | HK2: 0 | HL2: 0 | HM2: 0 | HN2: 0 | HO2: 0 | HP2: 0 | HQ2: 0 | HR2: 0 | HS2: 0 | HT2: 0 | HU2: 0 | HV2: 0 | HW2: 0 | HX2: 0 | HY2: 0 | HZ2: 0 | IA2: 0 | IB2: 0 | IC2: 0 | ID2: 0 | IE2: 0 | IF2: 0 | IG2: 0 | IH2: 0 | II2: 0 | IJ2: 0 | IK2: 0 | IL2: 0 | IM2: 0 | IN2: 0 | IO2: 0 | IP2: 0 | IQ2: 0 | IR2: 0 | IS2: 0 | IT2: 0 | IU2: 0 | IV2: 0 | IW2: 0 | IX2: 0 | IY2: 0 | IZ2: 0 | JA2: 0 | JB2: 0 | JC2: 0 | JD2: 0 | JE2: 0 | JF2: 0 | JG2: 0 | JH2: 0 | JI2: 0 | JJ2: 0 | JK2: 0 | JL2: 0 | JM2: 0 | JN2: 0 | JO2: 0 | JP2: 0 | JQ2: 0 | JR2: 0 | JS2: 0 | JT2: 0 | JU2: 0 | JV2: 0 | JW2: 0 | JX2: 0 | JY2: 0 | JZ2: 0 | KA2: 0 | KB2: 0 | KC2: 0 | KD2: 0 | KE2: 0 | KF2: 0 | KG2: 0 | KH2: 0 | KI2: 0 | KJ2: 0 | KK2: 0 | KL2: 0 | KM2: 0 | KN2: 0 | KO2: 0 | KP2: 0 | KQ2: 0 | KR2: 0 | KS2: 0 | KT2: 0 | KU2: 0 | KV2: 0 | KW2: 0 | KX2: 0 | KY2: 0 | KZ2: 0 | LA2: 0 | LB2: 0 | LC2: 0 | LD2: 0 | LE2: 0 | LF2: 0 | LG2: 0 | LH2: 0 | LI2: 0 | LJ2: 0 | LK2: 0 | LL2: 0 | LM2: 0 | LN2: 0 | LO2: 0 | LP2: 0 | LQ2: 0 | LR2: 0 | LS2: 0 | LT2: 0 | LU2: 0 | LV2: 0 | LW2: 0 | LX2: 0 | LY2: 0 | LZ2: 0 | MA2: 0 | MB2: 0 | MC2: 0 | MD2: 0 | ME2: 0 | MF2: 0 | MG2: 0 | MH2: 0 | MI2: 0 | MJ2: 0 | MK2: 0 | ML2: 0 | MM2: 0 | MN2: 0 | MO2: 0 | MP2: 0 | MQ2: 0 | MR2: 0 | MS2: 0 | MT2: 0 | MU2: 0 | MV2: 0 | MW2: 0 | MX2: 0 | MY2: 0 | MZ2: 0 | NA2: 0 | NB2: 0 | NC2: 0 | ND2: 0 | NE2: 0 | NF2: 0 | NG2: 0 | NH2: 0 | NI2: 0 | NJ2: 0 | NK2: 0 | NL2: 0 | NM2: 0 | NN2: 0 | NO2: 0 | NP2: 0 | NQ2: 0 | NR2: 0 | NS2: 0 | NT2: 0 | NU2: 0 | NV2: 0 | NW2: 0 | NX2: 0 | NY2: 0 | NZ2: 0 | OA2: 0 | OB2: 0 | OC2: 0 | OD2: 0 | OE2: 0 | OF2: 0 | OG2: 0 | OH2: 0 | OI2: 0 | OJ2: 0 | OK2: 0 | OL2: 0 | OM2: 0 | ON2: 0 | OO2: 0 | OP2: 0 | OQ2: 0 | OR2: 0 | OS2: 0 | OT2: 0 | OU2: 0 | OV2: 0 | OW2: 0 | OX2: 0 | OY2: 0 | OZ2: 0 | PA2: 0 | PB2: 0 | PC2: 0 | PD2: 0 | PE2: 0 | PF2: 0 | PG2: 0 | PH2: 0 | PI2: 0 | PJ2: 0 | PK2: 0 | PL2: 0 | PM2: 0 | PN2: 0 | PO2: 0 | PP2: 0 | PQ2: 0 | PR2: 0 | PS2: 0 | PT2: 0 | PU2: 0 | PV2: 0 | PW2: 0 | PX2: 0 | PY2: 0 | PZ2: 0 | QA2: 0 | QB2: 0 | QC2: 0 | QD2: 0 | QE2: 0 | QF2: 0 | QG2: 0 | QH2: 0 | QI2: 0 | QJ2: 0 | QK2: 0 | QL2: 0 | QM2: 0 | QN2: 0 | QO2: 0 | QP2: 0 | QQ2: 0 | QR2: 0 | QS2: 0 | QT2: 0 | QU2: 0 | QV2: 0 | QW2: 0 | QX2: 0 | QY2: 0 | QZ2: 0 | RA2: 0 | RB2: 0 | RC2: 0 | RD2: 0 | RE2: 0 | RF2: 0 | RG2: 0 | RH2: 0 | RI2: 0 | RJ2: 0 | RK2: 0 | RL2: 0 | RM2: 0 | RN2: 0 | RO2: 0 | RP2: 0 | RQ2: 0 | RR2: 0 | RS2: 0 | RT2: 0 | RU2: 0 | RV2: 0 | RW2: 0 | RX2: 0 | RY2: 0 | RZ2: 0 | SA2: 0 | SB2: 0 | SC2: 0 | SD2: 0 | SE2: 0 | SF2: 0 | SG2: 0 | SH2: 0 | SI2: 0 | SJ2: 0 | SK2: 0 | SL2: 0 | SM2: 0 | SN2: 0 | SO2: 0 | SP2: 0 | SQ2: 0 | SR2: 0 | SS2: 0 | ST2: 0 | SU2: 0 | SV2: 0 | SW2: 0 | SX2: 0 | SY2: 0 | SZ2: 0 | TA2: 0 | TB2: 0 | TC2: 0 | TD2: 0 | TE2: 0 | TF2: 0 | TG2: 0 | TH2: 0 | TI2: 0 | TJ2: 0 | TK2: 0 | TL2: 0 | TM2: 0 | TN2: 0 | TO2: 0 | TP2: 0 | TQ2: 0 | TR2: 0 | TS2: 0 | TT2: 0 | TU2: 0 | TV2: 0 | TW2: 0 | TX2: 0 | TY2: 0 | TZ2: 0 | UA2: 0 | UB2: 0 | UC2: 0 | UD2: 0 | UE2: 0 | UF2: 0 | UG2: 0 | UH2: 0 | UI2: 0 | UJ2: 0 | UK2: 0 | UL2: 0 | UM2: 0 | UN2: 0 | UO2: 0 | UP2: 0 | UQ2: 0 | UR2: 0 | US2: 0 | UT2: 0 | UU2: 0 | UV2: 0 | UW2: 0 | UX2: 0 | UY2: 0 | UZ2: 0 | VA2: 0 | VB2: 0 | VC2: 0 | VD2: 0 | VE2: 0 | VF2: 0 | VG2: 0 | VH2: 0 | VI2: 0 | VJ2: 0 | VK2: 0 | VL2: 0 | VM2: 0 | VN2: 0 | VO2: 0 | VP2: 0 | VQ2: 0 | VR2: 0 | VS2: 0 | VT2: 0 | VU2: 0 | VV2: 0 | VW2: 0 | VX2: 0 | VY2: 0 | VZ2: 0 | WA2: 0 | WB2: 0 | WC2: 0 | WD2: 0 | WE2: 0 | WF2: 0 | WG2: 0 | WH2: 0 | WI2: 0 | WJ2: 0 | WK2: 0 | WL2: 0 | WM2: 0 | WN2: 0 | WO2: 0 | WP2: 0 | WQ2: 0 | WR2: 0 | WS2: 0 | WT2: 0 | WU2: 0 | WV2: 0 | WW2: 0 | WX2: 0 | WY2: 0 | WZ2: 0 | XA2: 0 | XB2: 0 | XC2: 0 | XD2: 0 | XE2: 0 | XF2: 0 | XG2: 0 | XH2: 0 | XI2: 0 | XJ2: 0 | XK2: 0 | XL2: 0 | XM2: 0 | XN2: 0 | XO2: 0 | XP2: 0 | XQ2: 0 | XR2: 0 | XS2: 0 | XT2: 0 | XU2: 0 | XV2: 0 | XW2: 0 | XX2: 0 | XY2: 0 | XZ2: 0 | YA2: 0 | YB2: 0 | YC2: 0 | YD2: 0 | YE2: 0 | YF2: 0 | YG2: 0 | YH2: 0 | YI2: 0 | YJ2: 0 | YK2: 0 | YL2: 0 | YM2: 0 | YN2: 0 | YO2: 0 | YP2: 0 | YQ2: 0 | YR2: 0 | YS2: 0 | YT2: 0 | YU2: 0 | YV2: 0 | YW2: 0 | YX2: 0 | YY2: 0 | YZ2: 0 | ZA2: 0 | ZB2: 0 | ZC2: 0 | ZD2: 0 | ZE2: 0 | ZF2: 0 | ZG2: 0 | ZH2: 0 | ZI2: 0 | ZJ2: 0 | ZK2: 0 | ZL2: 0 | ZM2: 0 | ZN2: 0 | ZO2: 0 | ZP2: 0 | ZQ2: 0 | ZR2: 0 | ZS2: 0 | ZT2: 0 | ZU2: 0 | ZV2: 0 | ZW2: 0 | ZX2: 0 | ZY2: 0 | ZZ2: 0 | AAA2: 0 | AAB2: 0 | AAC2: 0 | AAD2: 0 | AAE2: 0 | AAF2: 0 | AAG2: 0 | AAH2: 0 | AAI2: 0 | AAJ2: 0 | AAK2: 0 | AAL2: 0 | AAM2: 0 | AAN2: 0 | AAO2: 0 | AAP2: 0 | AAQ2: =IF(LEFT($C2,5)="Total",0,IF(COUNTIF(ENTRY!$G$3:$BM$3,AAQ$1)=0,"CopyPasteValue",IFERROR(HLOOKUP(AAQ$1,ENTRY!$G$3:$BI$133,SUMIFS(ENTRY!$A$2:$A$133,ENTRY!$B$2:$B$133,$B2,ENTRY!$C$2:$C$133,$C2)-2,FALSE),0))) -> 0 | AAR2: =IF(LEFT($C2,5)="Total",0,IF(COUNTIF(ENTRY!$G$3:$BM$3,AAR$1)=0,"CopyPasteValue",IFERROR(HLOOKUP(AAR$1,ENTRY!$G$3:$BI$133,SUMIFS(ENTRY!$A$2:$A$133,ENTRY!$B$2:$B$133,$B2,ENTRY!$C$2:$C$133,$C2)-2,FALSE),0))) -> 0 | AAS2: =IF(LEFT($C2,5)="Total",0,IF(COUNTIF(ENTRY!$G$3:$BM$3,AAS$1)=0,"CopyPasteValue",IFERROR(HLOOKUP(AAS$1,ENTRY!$G$3:$BI$133,SUMIFS(ENTRY!$A$2:$A$133,ENTRY!$B$2:$B$133,$B2,ENTRY!$C$2:$C$133,$C2)-2,FALSE),0))) -> 0 | AAT2: =IF(LEFT($C2,5)="Total",0,IF(COUNTIF(ENTRY!$G$3:$BM$3,AAT$1)=0,"CopyPasteValue",IFERROR(HLOOKUP(AAT$1,ENTRY!$G$3:$BI$133,SUMIFS(ENTRY!$A$2:$A$133,ENTRY!$B$2:$B$133,$B2,ENTRY!$C$2:$C$133,$C2)-2,FALSE),0))) -> 0 | AAU2: =IF(LEFT($C2,5)="Total",0,IF(COUNTIF(ENTRY!$G$3:$BM$3,AAU$1)=0,"CopyPasteValue",IFERROR(HLOOKUP(AAU$1,ENTRY!$G$3:$BI$133,SUMIFS(ENTRY!$A$2:$A$133,ENTRY!$B$2:$B$133,$B2,ENTRY!$C$2:$C$133,$C2)-2,FALSE),0))) -> 0 | AAV2: =IF(LEFT($C2,5)="Total",0,IF(COUNTIF(ENTRY!$G$3:$BM$3,AAV$1)=0,"CopyPasteValue",IFERROR(HLOOKUP(AAV$1,ENTRY!$G$3:$BI$133,SUMIFS(ENTRY!$A$2:$A$133,ENTRY!$B$2:$B$133,$B2,ENTRY!$C$2:$C$133,$C2)-2,FALSE),0))) -> 0 | AAW2: =IF(LEFT($C2,5)="Total",0,IF(COUNTIF(ENTRY!$G$3:$BM$3,AAW$1)=0,"CopyPasteValue",IFERROR(HLOOKUP(AAW$1,ENTRY!$G$3:$BI$133,SUMIFS(ENTRY!$A$2:$A$133,ENTRY!$B$2:$B$133,$B2,ENTRY!$C$2:$C$133,$C2)-2,FALSE),0))) -> 0 | AAX2: =IF(LEFT($C2,5)="Total",0,IF(COUNTIF(ENTRY!$G$3:$BM$3,AAX$1)=0,"CopyPasteValue",IFERROR(HLOOKUP(AAX$1,ENTRY!$G$3:$BI$133,SUMIFS(ENTRY!$A$2:$A$133,ENTRY!$B$2:$B$133,$B2,ENTRY!$C$2:$C$133,$C2)-2,FALSE),0))) -> 0 | ... ABH2: =IF(LEFT($C2,5)="Total",0,IF(COUNTIF(ENTRY!$G$3:$BM$3,ABH$1)=0,"CopyPasteValue",IFERROR(HLOOKUP(ABH$1,ENTRY!$G$3:$BI$133,SUMIFS(ENTRY!$A$2:$A$133,ENTRY!$B$2:$B$133,$B2,ENTRY!$C$2:$C$133,$C2)-2,FALSE),0))) -> 0
B3: GC-Hand Bags | C3: GC-Shoes & Hand Bags | D3: =CELL("row",D3) -> 3 | E3: =COUNTIF(ENTRY!C$4:C$294,C3) -> 1 | F3: 0 | G3: 0 | H3: 0 | I3: 0 | J3: 0 | K3: 0 | L3: 0 | M3: 0 | N3: 0 | O3: 0 | P3: 0 | Q3: 0 | R3: 0 | S3: 0 | T3: 0 | U3: 0 | V3: 0 | W3: 0 | X3: 0 | Y3: 0 | Z3: 0 | AA3: 0 | AB3: 0 | AC3: 0 | AD3: 0 | AE3: 0 | AF3: 0 | AG3: 0 | AH3: 0 | AI3: 0 | AJ3: 0 | AK3: 0 | AL3: 0 | AM3: 0 | AN3: 0 | AO3: 0 | AP3: 0 | AQ3: 0 | AR3: 0 | AS3: 0 | AT3: 0 | AU3: 0 | AV3: 0 | AW3: 0 | AX3: 0 | AY3: 0 | AZ3: 0 | BA3: 0 | BB3: 0 | BC3: 0 | BD3: 0 | BE3: 0 | BF3: 0 | BG3: 0 | BH3: 0 | BI3: 0 | BJ3: 0 | BK3: 0 | BL3: 0 | BM3: 0 | BN3: 0 | BO3: 0 | BP3: 0 | BQ3: 0 | BR3: 0 | BS3: 0 | BT3: 0 | BU3: 0 | BV3: 0 | BW3: 0 | BX3: 0 | BY3: 0 | BZ3: 0 | CA3: 0 | CB3: 0 | CC3: 0 | CD3: 0 | CE3: 0 | CF3: 0 | CG3: 0 | CH3: 0 | CI3: 0 | CJ3: 0 | CK3: 0 | CL3: 0 | CM3: 0 | CN3: 0 | CO3: 0 | CP3: 0 | CQ3: 0 | CR3: 0 | CS3: 0 | CT3: 0 | CU3: 0 | CV3: 0 | CW3: 0 | CX3: 0 | CY3: 0 | CZ3: 0 | DA3: 0 | DB3: 0 | DC3: 0 | DD3: 0 | DE3: 0 | DF3: 0 | DG3: 0 | DH3: 0 | DI3: 0 | DJ3: 0 | DK3: 0 | DL3: 0 | DM3: 0 | DN3: 0 | DO3: 0 | DP3: 0 | DQ3: 0 | DR3: 0 | DS3: 0 | DT3: 0 | DU3: 0 | DV3: 0 | DW3: 0 | DX3: 0 | DY3: 0 | DZ3: 0 | EA3: 0 | EB3: 0 | EC3: 0 | ED3: 0 | EE3: 0 | EF3: 0 | EG3: 0 | EH3: 0 | EI3: 0 | EJ3: 0 | EK3: 0 | EL3: 0 | EM3: 0 | EN3: 0 | EO3: 0 | EP3: 0 | EQ3: 0 | ER3: 0 | ES3: 0 | ET3: 0 | EU3: 0 | EV3: 0 | EW3: 0 | EX3: 0 | EY3: 0 | EZ3: 0 | FA3: 0 | FB3: 0 | FC3: 0 | FD3: 0 | FE3: 0 | FF3: 0 | FG3: 0 | FH3: 0 | FI3: 0 | FJ3: 0 | FK3: 0 | FL3: 0 | FM3: 0 | FN3: 0 | FO3: 0 | FP3: 0 | FQ3: 0 | FR3: 0 | FS3: 0 | FT3: 0 | FU3: 0 | FV3: 0 | FW3: 0 | FX3: 0 | FY3: 0 | FZ3: 0 | GA3: 0 | GB3: 0 | GC3: 0 | GD3: 0 | GE3: 0 | GF3: 0 | GG3: 0 | GH3: 0 | GI3: 0 | GJ3: 0 | GK3: 0 | GL3: 0 | GM3: 0 | GN3: 0 | GO3: 0 | GP3: 0 | GQ3: 0 | GR3: 0 | GS3: 0 | GT3: 0 | GU3: 0 | GV3: 0 | GW3: 0 | GX3: 0 | GY3: 0 | GZ3: 0 | HA3: 0 | HB3: 0 | HC3: 0 | HD3: 0 | HE3: 0 | HF3: 0 | HG3: 0 | HH3: 0 | HI3: 0 | HJ3: 0 | HK3: 0 | HL3: 0 | HM3: 0 | HN3: 0 | HO3: 0 | HP3: 0 | HQ3: 0 | HR3: 0 | HS3: 0 | HT3: 0 | HU3: 0 | HV3: 0 | HW3: 0 | HX3: 0 | HY3: 0 | HZ3: 0 | IA3: 0 | IB3: 0 | IC3: 0 | ID3: 0 | IE3: 0 | IF3: 0 | IG3: 0 | IH3: 0 | II3: 0 | IJ3: 0 | IK3: 0 | IL3: 0 | IM3: 0 | IN3: 0 | IO3: 0 | IP3: 0 | IQ3: 0 | IR3: 0 | IS3: 0 | IT3: 0 | IU3: 0 | IV3: 0 | IW3: 0 | IX3: 0 | IY3: 0 | IZ3: 0 | JA3: 0 | JB3: 0 | JC3: 0 | JD3: 0 | JE3: 0 | JF3: 0 | JG3: 0 | JH3: 0 | JI3: 0 | JJ3: 0 | JK3: 0 | JL3: 0 | JM3: 0 | JN3: 0 | JO3: 0 | JP3: 0 | JQ3: 0 | JR3: 0 | JS3: 0 | JT3: 0 | JU3: 0 | JV3: 0 | JW3: 0 | JX3: 0 | JY3: 0 | JZ3: 0 | KA3: 0 | KB3: 0 | KC3: 0 | KD3: 0 | KE3: 0 | KF3: 0 | KG3: 0 | KH3: 0 | KI3: 0 | KJ3: 0 | KK3: 0 | KL3: 0 | KM3: 0 | KN3: 0 | KO3: 0 | KP3: 0 | KQ3: 0 | KR3: 0 | KS3: 0 | KT3: 0 | KU3: 0 | KV3: 0 | KW3: 0 | KX3: 0 | KY3: 0 | KZ3: 0 | LA3: 0 | LB3: 0 | LC3: 0 | LD3: 0 | LE3: 0 | LF3: 0 | LG3: 0 | LH3: 0 | LI3: 0 | LJ3: 0 | LK3: 0 | LL3: 0 | LM3: 0 | LN3: 0 | LO3: 0 | LP3: 0 | LQ3: 0 | LR3: 0 | LS3: 0 | LT3: 0 | LU3: 0 | LV3: 0 | LW3: 0 | LX3: 0 | LY3: 0 | LZ3: 0 | MA3: 0 | MB3: 0 | MC3: 0 | MD3: 0 | ME3: 0 | MF3: 0 | MG3: 0 | MH3: 0 | MI3: 0 | MJ3: 0 | MK3: 0 | ML3: 0 | MM3: 0 | MN3: 0 | MO3: 0 | MP3: 0 | MQ3: 0 | MR3: 0 | MS3: 0 | MT3: 0 | MU3: 0 | MV3: 0 | MW3: 0 | MX3: 0 | MY3: 0 | MZ3: 0 | NA3: 0 | NB3: 0 | NC3: 0 | ND3: 0 | NE3: 0 | NF3: 0 | NG3: 0 | NH3: 0 | NI3: 0 | NJ3: 0 | NK3: 0 | NL3: 0 | NM3: 0 | NN3: 0 | NO3: 0 | NP3: 0 | NQ3: 0 | NR3: 0 | NS3: 0 | NT3: 0 | NU3: 0 | NV3: 0 | NW3: 0 | NX3: 0 | NY3: 0 | NZ3: 0 | OA3: 0 | OB3: 0 | OC3: 0 | OD3: 0 | OE3: 0 | OF3: 0 | OG3: 0 | OH3: 0 | OI3: 0 | OJ3: 0 | OK3: 0 | OL3: 0 | OM3: 0 | ON3: 0 | OO3: 0 | OP3: 0 | OQ3: 0 | OR3: 0 | OS3: 0 | OT3: 0 | OU3: 0 | OV3: 0 | OW3: 0 | OX3: 0 | OY3: 0 | OZ3: 0 | PA3: 0 | PB3: 0 | PC3: 0 | PD3: 0 | PE3: 0 | PF3: 0 | PG3: 0 | PH3: 0 | PI3: 0 | PJ3: 0 | PK3: 0 | PL3: 0 | PM3: 0 | PN3: 0 | PO3: 0 | PP3: 0 | PQ3: 0 | PR3: 0 | PS3: 0 | PT3: 0 | PU3: 0 | PV3: 0 | PW3: 0 | PX3: 0 | PY3: 0 | PZ3: 0 | QA3: 0 | QB3: 0 | QC3: 0 | QD3: 0 | QE3: 0 | QF3: 0 | QG3: 0 | QH3: 0 | QI3: 0 | QJ3: 0 | QK3: 0 | QL3: 0 | QM3: 0 | QN3: 0 | QO3: 0 | QP3: 0 | QQ3: 0 | QR3: 0 | QS3: 0 | QT3: 0 | QU3: 0 | QV3: 0 | QW3: 0 | QX3: 0 | QY3: 0 | QZ3: 0 | RA3: 0 | RB3: 0 | RC3: 0 | RD3: 0 | RE3: 0 | RF3: 0 | RG3: 0 | RH3: 0 | RI3: 0 | RJ3: 0 | RK3: 0 | RL3: 0 | RM3: 0 | RN3: 0 | RO3: 0 | RP3: 0 | RQ3: 0 | RR3: 0 | RS3: 0 | RT3: 0 | RU3: 0 | RV3: 0 | RW3: 0 | RX3: 0 | RY3: 0 | RZ3: 0 | SA3: 0 | SB3: 0 | SC3: 0 | SD3: 0 | SE3: 0 | SF3: 0 | SG3: 0 | SH3: 0 | SI3: 0 | SJ3: 0 | SK3: 0 | SL3: 0 | SM3: 0 | SN3: 0 | SO3: 0 | SP3: 0 | SQ3: 0 | SR3: 0 | SS3: 0 | ST3: 0 | SU3: 0 | SV3: 0 | SW3: 0 | SX3: 0 | SY3: 0 | SZ3: 0 | TA3: 0 | TB3: 0 | TC3: 0 | TD3: 0 | TE3: 0 | TF3: 0 | TG3: 0 | TH3: 0 | TI3: 0 | TJ3: 0 | TK3: 0 | TL3: 0 | TM3: 0 | TN3: 0 | TO3: 0 | TP3: 0 | TQ3: 0 | TR3: 0 | TS3: 0 | TT3: 0 | TU3: 0 | TV3: 0 | TW3: 0 | TX3: 0 | TY3: 0 | TZ3: 0 | UA3: 0 | UB3: 0 | UC3: 0 | UD3: 0 | UE3: 0 | UF3: 0 | UG3: 0 | UH3: 0 | UI3: 0 | UJ3: 0 | UK3: 0 | UL3: 0 | UM3: 0 | UN3: 0 | UO3: 0 | UP3: 0 | UQ3: 0 | UR3: 0 | US3: 0 | UT3: 0 | UU3: 0 | UV3: 0 | UW3: 0 | UX3: 0 | UY3: 0 | UZ3: 0 | VA3: 0 | VB3: 0 | VC3: 0 | VD3: 0 | VE3: 0 | VF3: 0 | VG3: 0 | VH3: 0 | VI3: 0 | VJ3: 0 | VK3: 0 | VL3: 0 | VM3: 0 | VN3: 0 | VO3: 0 | VP3: 0 | VQ3: 0 | VR3: 0 | VS3: 0 | VT3: 0 | VU3: 0 | VV3: 0 | VW3: 0 | VX3: 0 | VY3: 0 | VZ3: 0 | WA3: 0 | WB3: 0 | WC3: 0 | WD3: 0 | WE3: 0 | WF3: 0 | WG3: 0 | WH3: 0 | WI3: 0 | WJ3: 0 | WK3: 0 | WL3: 0 | WM3: 0 | WN3: 0 | WO3: 0 | WP3: 0 | WQ3: 0 | WR3: 0 | WS3: 0 | WT3: 0 | WU3: 0 | WV3: 0 | WW3: 0 | WX3: 0 | WY3: 0 | WZ3: 0 | XA3: 0 | XB3: 0 | XC3: 0 | XD3: 0 | XE3: 0 | XF3: 0 | XG3: 0 | XH3: 0 | XI3: 0 | XJ3: 0 | XK3: 0 | XL3: 0 | XM3: 0 | XN3: 0 | XO3: 0 | XP3: 0 | XQ3: 0 | XR3: 0 | XS3: 0 | XT3: 0 | XU3: 0 | XV3: 0 | XW3: 0 | XX3: 0 | XY3: 0 | XZ3: 0 | YA3: 0 | YB3: 0 | YC3: 0 | YD3: 0 | YE3: 0 | YF3: 0 | YG3: 0 | YH3: 0 | YI3: 0 | YJ3: 0 | YK3: 0 | YL3: 0 | YM3: 0 | YN3: 0 | YO3: 0 | YP3: 0 | YQ3: 0 | YR3: 0 | YS3: 0 | YT3: 0 | YU3: 0 | YV3: 0 | YW3: 0 | YX3: 0 | YY3: 0 | YZ3: 0 | ZA3: 0 | ZB3: 0 | ZC3: 0 | ZD3: 0 | ZE3: 0 | ZF3: 0 | ZG3: 0 | ZH3: 0 | ZI3: 0 | ZJ3: 0 | ZK3: 0 | ZL3: 0 | ZM3: 0 | ZN3: 0 | ZO3: 0 | ZP3: 0 | ZQ3: 0 | ZR3: 0 | ZS3: 0 | ZT3: 0 | ZU3: 0 | ZV3: 0 | ZW3: 0 | ZX3: 0 | ZY3: 0 | ZZ3: 0 | AAA3: 0 | AAB3: 0 | AAC3: 0 | AAD3: 0 | AAE3: 0 | AAF3: 0 | AAG3: 0 | AAH3: 0 | AAI3: 0 | AAJ3: 0 | AAK3: 0 | AAL3: 0 | AAM3: 0 | AAN3: 0 | AAO3: 0 | AAP3: 0 | AAQ3: =IF(LEFT($C3,5)="Total",0,IF(COUNTIF(ENTRY!$G$3:$BM$3,AAQ$1)=0,"CopyPasteValue",IFERROR(HLOOKUP(AAQ$1,ENTRY!$G$3:$BI$133,SUMIFS(ENTRY!$A$2:$A$133,ENTRY!$B$2:$B$133,$B3,ENTRY!$C$2:$C$133,$C3)-2,FALSE),0))) -> 0 | AAR3: =IF(LEFT($C3,5)="Total",0,IF(COUNTIF(ENTRY!$G$3:$BM$3,AAR$1)=0,"CopyPasteValue",IFERROR(HLOOKUP(AAR$1,ENTRY!$G$3:$BI$133,SUMIFS(ENTRY!$A$2:$A$133,ENTRY!$B$2:$B$133,$B3,ENTRY!$C$2:$C$133,$C3)-2,FALSE),0))) -> 0 | AAS3: =IF(LEFT($C3,5)="Total",0,IF(COUNTIF(ENTRY!$G$3:$BM$3,AAS$1)=0,"CopyPasteValue",IFERROR(HLOOKUP(AAS$1,ENTRY!$G$3:$BI$133,SUMIFS(ENTRY!$A$2:$A$133,ENTRY!$B$2:$B$133,$B3,ENTRY!$C$2:$C$133,$C3)-2,FALSE),0))) -> 0 | AAT3: =IF(LEFT($C3,5)="Total",0,IF(COUNTIF(ENTRY!$G$3:$BM$3,AAT$1)=0,"CopyPasteValue",IFERROR(HLOOKUP(AAT$1,ENTRY!$G$3:$BI$133,SUMIFS(ENTRY!$A$2:$A$133,ENTRY!$B$2:$B$133,$B3,ENTRY!$C$2:$C$133,$C3)-2,FALSE),0))) -> 0 | AAU3: =IF(LEFT($C3,5)="Total",0,IF(COUNTIF(ENTRY!$G$3:$BM$3,AAU$1)=0,"CopyPasteValue",IFERROR(HLOOKUP(AAU$1,ENTRY!$G$3:$BI$133,SUMIFS(ENTRY!$A$2:$A$133,ENTRY!$B$2:$B$133,$B3,ENTRY!$C$2:$C$133,$C3)-2,FALSE),0))) -> 0 | AAV3: =IF(LEFT($C3,5)="Total",0,IF(COUNTIF(ENTRY!$G$3:$BM$3,AAV$1)=0,"CopyPasteValue",IFERROR(HLOOKUP(AAV$1,ENTRY!$G$3:$BI$133,SUMIFS(ENTRY!$A$2:$A$133,ENTRY!$B$2:$B$133,$B3,ENTRY!$C$2:$C$133,$C3)-2,FALSE),0))) -> 0 | AAW3: =IF(LEFT($C3,5)="Total",0,IF(COUNTIF(ENTRY!$G$3:$BM$3,AAW$1)=0,"CopyPasteValue",IFERROR(HLOOKUP(AAW$1,ENTRY!$G$3:$BI$133,SUMIFS(ENTRY!$A$2:$A$133,ENTRY!$B$2:$B$133,$B3,ENTRY!$C$2:$C$133,$C3)-2,FALSE),0))) -> 0 | AAX3: =IF(LEFT($C3,5)="Total",0,IF(COUNTIF(ENTRY!$G$3:$BM$3,AAX$1)=0,"CopyPasteValue",IFERROR(HLOOKUP(AAX$1,ENTRY!$G$3:$BI$133,SUMIFS(ENTRY!$A$2:$A$133,ENTRY!$B$2:$B$133,$B3,ENTRY!$C$2:$C$133,$C3)-2,FALSE),0))) -> 0 | ... ABH3: =IF(LEFT($C3,5)="Total",0,IF(COUNTIF(ENTRY!$G$3:$BM$3,ABH$1)=0,"CopyPasteValue",IFERROR(HLOOKUP(ABH$1,ENTRY!$G$3:$BI$133,SUMIFS(ENTRY!$A$2:$A$133,ENTRY!$B$2:$B$133,$B3,ENTRY!$C$2:$C$133,$C3)-2,FALSE),0))) -> 0
B4: GC-Hand Bags | C4: GC-Hand Bags | D4: =CELL("row",D4) -> 4 | E4: =COUNTIF(ENTRY!C$4:C$294,C4) -> 2 | F4: 0 | G4: 0 | H4: 0 | I4: 0 | J4: 0 | K4: 0 | L4: 0 | M4: 0 | N4: 0 | O4: 0 | P4: 0 | Q4: 0 | R4: 0 | S4: 0 | T4: 0 | U4: 0 | V4: 0 | W4: 0 | X4: 0 | Y4: 0 | Z4: 0 | AA4: 0 | AB4: 0 | AC4: 0 | AD4: 0 | AE4: 0 | AF4: 0 | AG4: 0 | AH4: 0 | AI4: 0 | AJ4: 0 | AK4: 0 | AL4: 0 | AM4: 0 | AN4: 0 | AO4: 0 | AP4: 0 | AQ4: 0 | AR4: 0 | AS4: 0 | AT4: 0 | AU4: 0 | AV4: 0 | AW4: 0 | AX4: 0 | AY4: 0 | AZ4: 0 | BA4: 0 | BB4: 0 | BC4: 0 | BD4: 0 | BE4: 0 | BF4: 0 | BG4: 0 | BH4: 0 | BI4: 0 | BJ4: 0 | BK4: 0 | BL4: 0 | BM4: 0 | BN4: 0 | BO4: 0 | BP4: 0 | BQ4: 0 | BR4: 0 | BS4: 0 | BT4: 0 | BU4: 0 | BV4: 0 | BW4: 0 | BX4: 0 | BY4: 0 | BZ4: 0 | CA4: 0 | CB4: 0 | CC4: 0 | CD4: 0 | CE4: 0 | CF4: 0 | CG4: 0 | CH4: 0 | CI4: 0 | CJ4: 0 | CK4: 0 | CL4: 0 | CM4: 0 | CN4: 0 | CO4: 0 | CP4: 0 | CQ4: 0 | CR4: 0 | CS4: 0 | CT4: 0 | CU4: 0 | CV4: 0 | CW4: 0 | CX4: 0 | CY4: 0 | CZ4: 0 | DA4: 0 | DB4: 0 | DC4: 0 | DD4: 0 | DE4: 0 | DF4: 0 | DG4: 0 | DH4: 0 | DI4: 0 | DJ4: 0 | DK4: 0 | DL4: 0 | DM4: 0 | DN4: 0 | DO4: 0 | DP4: 0 | DQ4: 0 | DR4: 0 | DS4: 0 | DT4: 0 | DU4: 0 | DV4: 0 | DW4: 0 | DX4: 0 | DY4: 0 | DZ4: 0 | EA4: 0 | EB4: 0 | EC4: 0 | ED4: 0 | EE4: 0 | EF4: 0 | EG4: 0 | EH4: 0 | EI4: 0 | EJ4: 0 | EK4: 0 | EL4: 0 | EM4: 0 | EN4: 0 | EO4: 0 | EP4: 0 | EQ4: 0 | ER4: 0 | ES4: 0 | ET4: 0 | EU4: 0 | EV4: 0 | EW4: 0 | EX4: 0 | EY4: 0 | EZ4: 0 | FA4: 0 | FB4: 0 | FC4: 0 | FD4: 0 | FE4: 0 | FF4: 0 | FG4: 0 | FH4: 0 | FI4: 0 | FJ4: 0 | FK4: 0 | FL4: 0 | FM4: 0 | FN4: 0 | FO4: 0 | FP4: 0 | FQ4: 0 | FR4: 0 | FS4: 0 | FT4: 0 | FU4: 0 | FV4: 0 | FW4: 0 | FX4: 0 | FY4: 0 | FZ4: 0 | GA4: 0 | GB4: 0 | GC4: 0 | GD4: 0 | GE4: 0 | GF4: 0 | GG4: 0 | GH4: 0 | GI4: 0 | GJ4: 0 | GK4: 0 | GL4: 0 | GM4: 0 | GN4: 0 | GO4: 0 | GP4: 0 | GQ4: 0 | GR4: 0 | GS4: 0 | GT4: 0 | GU4: 0 | GV4: 0 | GW4: 0 | GX4: 0 | GY4: 0 | GZ4: 0 | HA4: 0 | HB4: 0 | HC4: 0 | HD4: 0 | HE4: 0 | HF4: 0 | HG4: 0 | HH4: 0 | HI4: 0 | HJ4: 0 | HK4: 0 | HL4: 0 | HM4: 0 | HN4: 0 | HO4: 0 | HP4: 0 | HQ4: 0 | HR4: 0 | HS4: 0 | HT4: 0 | HU4: 0 | HV4: 0 | HW4: 0 | HX4: 0 | HY4: 0 | HZ4: 0 | IA4: 0 | IB4: 0 | IC4: 0 | ID4: 0 | IE4: 0 | IF4: 0 | IG4: 0 | IH4: 0 | II4: 0 | IJ4: 0 | IK4: 0 | IL4: 0 | IM4: 0 | IN4: 0 | IO4: 0 | IP4: 0 | IQ4: 0 | IR4: 0 | IS4: 0 | IT4: 0 | IU4: 0 | IV4: 0 | IW4: 0 | IX4: 0 | IY4: 0 | IZ4: 0 | JA4: 0 | JB4: 0 | JC4: 0 | JD4: 0 | JE4: 0 | JF4: 0 | JG4: 0 | JH4: 0 | JI4: 0 | JJ4: 0 | JK4: 0 | JL4: 0 | JM4: 0 | JN4: 0 | JO4: 0 | JP4: 0 | JQ4: 0 | JR4: 0 | JS4: 0 | JT4: 0 | JU4: 0 | JV4: 0 | JW4: 0 | JX4: 0 | JY4: 0 | JZ4: 0 | KA4: 0 | KB4: 0 | KC4: 0 | KD4: 0 | KE4: 0 | KF4: 0 | KG4: 0 | KH4: 0 | KI4: 0 | KJ4: 0 | KK4: 0 | KL4: 0 | KM4: 0 | KN4: 0 | KO4: 0 | KP4: 0 | KQ4: 0 | KR4: 0 | KS4: 0 | KT4: 0 | KU4: 0 | KV4: 0 | KW4: 0 | KX4: 0 | KY4: 0 | KZ4: 0 | LA4: 0 | LB4: 0 | LC4: 0 | LD4: 0 | LE4: 0 | LF4: 0 | LG4: 0 | LH4: 0 | LI4: 0 | LJ4: 0 | LK4: 0 | LL4: 0 | LM4: 0 | LN4: 0 | LO4: 0 | LP4: 0 | LQ4: 0 | LR4: 0 | LS4: 0 | LT4: 0 | LU4: 0 | LV4: 0 | LW4: 0 | LX4: 0 | LY4: 0 | LZ4: 0 | MA4: 0 | MB4: 0 | MC4: 0 | MD4: 0 | ME4: 0 | MF4: 0 | MG4: 0 | MH4: 0 | MI4: 0 | MJ4: 0 | MK4: 0 | ML4: 0 | MM4: 0 | MN4: 0 | MO4: 0 | MP4: 0 | MQ4: 0 | MR4: 0 | MS4: 0 | MT4: 0 | MU4: 0 | MV4: 0 | MW4: 0 | MX4: 0 | MY4: 0 | MZ4: 0 | NA4: 0 | NB4: 0 | NC4: 0 | ND4: 0 | NE4: 0 | NF4: 0 | NG4: 0 | NH4: 0 | NI4: 0 | NJ4: 0 | NK4: 0 | NL4: 0 | NM4: 0 | NN4: 0 | NO4: 0 | NP4: 0 | NQ4: 0 | NR4: 0 | NS4: 0 | NT4: 0 | NU4: 0 | NV4: 0 | NW4: 0 | NX4: 0 | NY4: 0 | NZ4: 0 | OA4: 0 | OB4: 0 | OC4: 0 | OD4: 0 | OE4: 0 | OF4: 0 | OG4: 0 | OH4: 0 | OI4: 0 | OJ4: 0 | OK4: 0 | OL4: 0 | OM4: 0 | ON4: 0 | OO4: 0 | OP4: 0 | OQ4: 0 | OR4: 0 | OS4: 0 | OT4: 0 | OU4: 0 | OV4: 0 | OW4: 0 | OX4: 0 | OY4: 0 | OZ4: 0 | PA4: 0 | PB4: 0 | PC4: 0 | PD4: 0 | PE4: 0 | PF4: 0 | PG4: 0 | PH4: 0 | PI4: 0 | PJ4: 0 | PK4: 0 | PL4: 0 | PM4: 0 | PN4: 0 | PO4: 0 | PP4: 0 | PQ4: 0 | PR4: 0 | PS4: 0 | PT4: 0 | PU4: 0 | PV4: 0 | PW4: 0 | PX4: 0 | PY4: 0 | PZ4: 0 | QA4: 0 | QB4: 0 | QC4: 0 | QD4: 0 | QE4: 0 | QF4: 0 | QG4: 0 | QH4: 0 | QI4: 0 | QJ4: 0 | QK4: 0 | QL4: 0 | QM4: 0 | QN4: 0 | QO4: 0 | QP4: 0 | QQ4: 0 | QR4: 0 | QS4: 0 | QT4: 0 | QU4: 0 | QV4: 0 | QW4: 0 | QX4: 0 | QY4: 0 | QZ4: 0 | RA4: 0 | RB4: 0 | RC4: 0 | RD4: 0 | RE4: 0 | RF4: 0 | RG4: 0 | RH4: 0 | RI4: 0 | RJ4: 0 | RK4: 0 | RL4: 0 | RM4: 0 | RN4: 0 | RO4: 0 | RP4: 0 | RQ4: 0 | RR4: 0 | RS4: 0 | RT4: 0 | RU4: 0 | RV4: 0 | RW4: 0 | RX4: 0 | RY4: 0 | RZ4: 0 | SA4: 0 | SB4: 0 | SC4: 0 | SD4: 0 | SE4: 0 | SF4: 0 | SG4: 0 | SH4: 0 | SI4: 0 | SJ4: 0 | SK4: 0 | SL4: 0 | SM4: 0 | SN4: 0 | SO4: 0 | SP4: 0 | SQ4: 0 | SR4: 0 | SS4: 0 | ST4: 0 | SU4: 0 | SV4: 0 | SW4: 0 | SX4: 0 | SY4: 0 | SZ4: 0 | TA4: 0 | TB4: 0 | TC4: 0 | TD4: 0 | TE4: 0 | TF4: 0 | TG4: 0 | TH4: 0 | TI4: 0 | TJ4: 0 | TK4: 0 | TL4: 0 | TM4: 0 | TN4: 0 | TO4: 0 | TP4: 0 | TQ4: 0 | TR4: 0 | TS4: 0 | TT4: 0 | TU4: 0 | TV4: 0 | TW4: 0 | TX4: 0 | TY4: 0 | TZ4: 0 | UA4: 0 | UB4: 0 | UC4: 0 | UD4: 0 | UE4: 0 | UF4: 0 | UG4: 0 | UH4: 0 | UI4: 0 | UJ4: 0 | UK4: 0 | UL4: 0 | UM4: 0 | UN4: 0 | UO4: 0 | UP4: 0 | UQ4: 0 | UR4: 0 | US4: 0 | UT4: 0 | UU4: 0 | UV4: 0 | UW4: 0 | UX4: 0 | UY4: 0 | UZ4: 0 | VA4: 0 | VB4: 0 | VC4: 0 | VD4: 0 | VE4: 0 | VF4: 0 | VG4: 0 | VH4: 0 | VI4: 0 | VJ4: 0 | VK4: 0 | VL4: 0 | VM4: 0 | VN4: 0 | VO4: 0 | VP4: 0 | VQ4: 0 | VR4: 0 | VS4: 0 | VT4: 0 | VU4: 0 | VV4: 0 | VW4: 0 | VX4: 0 | VY4: 0 | VZ4: 0 | WA4: 0 | WB4: 0 | WC4: 0 | WD4: 0 | WE4: 0 | WF4: 0 | WG4: 0 | WH4: 0 | WI4: 0 | WJ4: 0 | WK4: 0 | WL4: 0 | WM4: 0 | WN4: 0 | WO4: 0 | WP4: 0 | WQ4: 0 | WR4: 0 | WS4: 0 | WT4: 0 | WU4: 0 | WV4: 0 | WW4: 0 | WX4: 0 | WY4: 0 | WZ4: 0 | XA4: 0 | XB4: 0 | XC4: 0 | XD4: 0 | XE4: 0 | XF4: 0 | XG4: 0 | XH4: 0 | XI4: 0 | XJ4: 0 | XK4: 0 | XL4: 0 | XM4: 0 | XN4: 0 | XO4: 0 | XP4: 0 | XQ4: 0 | XR4: 0 | XS4: 0 | XT4: 0 | XU4: 0 | XV4: 0 | XW4: 0 | XX4: 0 | XY4: 0 | XZ4: 0 | YA4: 0 | YB4: 0 | YC4: 0 | YD4: 0 | YE4: 0 | YF4: 0 | YG4: 0 | YH4: 0 | YI4: 0 | YJ4: 0 | YK4: 0 | YL4: 0 | YM4: 0 | YN4: 0 | YO4: 0 | YP4: 0 | YQ4: 0 | YR4: 0 | YS4: 0 | YT4: 0 | YU4: 0 | YV4: 0 | YW4: 0 | YX4: 0 | YY4: 0 | YZ4: 0 | ZA4: 0 | ZB4: 0 | ZC4: 0 | ZD4: 0 | ZE4: 0 | ZF4: 0 | ZG4: 0 | ZH4: 0 | ZI4: 0 | ZJ4: 0 | ZK4: 0 | ZL4: 0 | ZM4: 0 | ZN4: 0 | ZO4: 0 | ZP4: 0 | ZQ4: 0 | ZR4: 0 | ZS4: 0 | ZT4: 0 | ZU4: 0 | ZV4: 0 | ZW4: 0 | ZX4: 0 | ZY4: 0 | ZZ4: 0 | AAA4: 0 | AAB4: 0 | AAC4: 0 | AAD4: 0 | AAE4: 0 | AAF4: 0 | AAG4: 0 | AAH4: 0 | AAI4: 0 | AAJ4: 0 | AAK4: 0 | AAL4: 0 | AAM4: 0 | AAN4: 0 | AAO4: 0 | AAP4: 0 | AAQ4: =IF(LEFT($C4,5)="Total",0,IF(COUNTIF(ENTRY!$G$3:$BM$3,AAQ$1)=0,"CopyPasteValue",IFERROR(HLOOKUP(AAQ$1,ENTRY!$G$3:$BI$133,SUMIFS(ENTRY!$A$2:$A$133,ENTRY!$B$2:$B$133,$B4,ENTRY!$C$2:$C$133,$C4)-2,FALSE),0))) -> 0 | AAR4: =IF(LEFT($C4,5)="Total",0,IF(COUNTIF(ENTRY!$G$3:$BM$3,AAR$1)=0,"CopyPasteValue",IFERROR(HLOOKUP(AAR$1,ENTRY!$G$3:$BI$133,SUMIFS(ENTRY!$A$2:$A$133,ENTRY!$B$2:$B$133,$B4,ENTRY!$C$2:$C$133,$C4)-2,FALSE),0))) -> 0 | AAS4: =IF(LEFT($C4,5)="Total",0,IF(COUNTIF(ENTRY!$G$3:$BM$3,AAS$1)=0,"CopyPasteValue",IFERROR(HLOOKUP(AAS$1,ENTRY!$G$3:$BI$133,SUMIFS(ENTRY!$A$2:$A$133,ENTRY!$B$2:$B$133,$B4,ENTRY!$C$2:$C$133,$C4)-2,FALSE),0))) -> 0 | AAT4: =IF(LEFT($C4,5)="Total",0,IF(COUNTIF(ENTRY!$G$3:$BM$3,AAT$1)=0,"CopyPasteValue",IFERROR(HLOOKUP(AAT$1,ENTRY!$G$3:$BI$133,SUMIFS(ENTRY!$A$2:$A$133,ENTRY!$B$2:$B$133,$B4,ENTRY!$C$2:$C$133,$C4)-2,FALSE),0))) -> 0 | AAU4: =IF(LEFT($C4,5)="Total",0,IF(COUNTIF(ENTRY!$G$3:$BM$3,AAU$1)=0,"CopyPasteValue",IFERROR(HLOOKUP(AAU$1,ENTRY!$G$3:$BI$133,SUMIFS(ENTRY!$A$2:$A$133,ENTRY!$B$2:$B$133,$B4,ENTRY!$C$2:$C$133,$C4)-2,FALSE),0))) -> 0 | AAV4: =IF(LEFT($C4,5)="Total",0,IF(COUNTIF(ENTRY!$G$3:$BM$3,AAV$1)=0,"CopyPasteValue",IFERROR(HLOOKUP(AAV$1,ENTRY!$G$3:$BI$133,SUMIFS(ENTRY!$A$2:$A$133,ENTRY!$B$2:$B$133,$B4,ENTRY!$C$2:$C$133,$C4)-2,FALSE),0))) -> 0 | AAW4: =IF(LEFT($C4,5)="Total",0,IF(COUNTIF(ENTRY!$G$3:$BM$3,AAW$1)=0,"CopyPasteValue",IFERROR(HLOOKUP(AAW$1,ENTRY!$G$3:$BI$133,SUMIFS(ENTRY!$A$2:$A$133,ENTRY!$B$2:$B$133,$B4,ENTRY!$C$2:$C$133,$C4)-2,FALSE),0))) -> 0 | AAX4: =IF(LEFT($C4,5)="Total",0,IF(COUNTIF(ENTRY!$G$3:$BM$3,AAX$1)=0,"CopyPasteValue",IFERROR(HLOOKUP(AAX$1,ENTRY!$G$3:$BI$133,SUMIFS(ENTRY!$A$2:$A$133,ENTRY!$B$2:$B$133,$B4,ENTRY!$C$2:$C$133,$C4)-2,FALSE),0))) -> 0 | ... ABH4: =IF(LEFT($C4,5)="Total",0,IF(COUNTIF(ENTRY!$G$3:$BM$3,ABH$1)=0,"CopyPasteValue",IFERROR(HLOOKUP(ABH$1,ENTRY!$G$3:$BI$133,SUMIFS(ENTRY!$A$2:$A$133,ENTRY!$B$2:$B$133,$B4,ENTRY!$C$2:$C$133,$C4)-2,FALSE),0))) -> 0
B5: GC-Hand Bags | C5: HB2 NewGrade-Yellow | D5: =CELL("row",D5) -> 5 | E5: =COUNTIF(ENTRY!C$4:C$294,C5) -> 1 | F5: 0 | G5: 0 | H5: 0 | I5: 0 | J5: 3 | K5: 0 | L5: 0 | M5: 1 | N5: 1 | O5: 0 | P5: 0 | Q5: 3 | R5: 1 | S5: 0 | T5: 0 | U5: 0 | V5: 0 | W5: 1 | X5: 1 | Y5: 9 | Z5: 0 | AA5: 0 | AB5: 1 | AC5: 0 | AD5: 0 | AE5: 0 | AF5: 0 | AG5: 0 | AH5: 0 | AI5: 1 | AJ5: 1 | AK5: 1 | AL5: 1 | AM5: 1 | AN5: 0 | AO5: 1 | AP5: 1 | AQ5: 1 | AR5: 0 | AS5: 0 | AT5: 0 | AU5: 0 | AV5: 1 | AW5: 0 | AX5: 1 | AY5: 2 | AZ5: 0 | BA5: 0 | BB5: 0 | BC5: 0 | BD5: 0 | BE5: 1 | BF5: 2 | BG5: 0 | BH5: 0 | BI5: 0 | BJ5: 2 | BK5: 0 | BL5: 5 | BM5: 0 | BN5: 0 | BO5: 13 | BP5: 0 | BQ5: 2 | BR5: 0 | BS5: 0 | BT5: 2 | BU5: 0 | BV5: 0 | BW5: 0 | BX5: 0 | BY5: 2 | BZ5: 0 | CA5: 1 | CB5: 0 | CC5: 0 | CD5: 0 | CE5: 0 | CF5: 1 | CG5: 0 | CH5: 1 | CI5: 1 | CJ5: 0 | CK5: 0 | CL5: 0 | CM5: 4 | CN5: 0 | CO5: 0 | CP5: 0 | CQ5: 0 | CR5: 0 | CS5: 0 | CT5: 8 | CU5: 0 | CV5: 0 | CW5: 0 | CX5: 0 | CY5: 0 | CZ5: 0 | DA5: 0 | DB5: 1 | DC5: 2 | DD5: 2 | DE5: 0 | DF5: 0 | DG5: 1 | DH5: 4 | DI5: 2 | DJ5: 17 | DK5: 36 | DL5: 1 | DM5: 0 | DN5: 11 | DO5: 3 | DP5: 1 | DQ5: 1 | DR5: 0 | DS5: 0 | DT5: 0 | DU5: 4 | DV5: 1 | DW5: 0 | DX5: 1 | DY5: 0 | DZ5: 3 | EA5: 0 | EB5: 1 | EC5: 1 | ED5: 10 | EE5: 0 | EF5: 1 | EG5: 41 | EH5: 0 | EI5: 2 | EJ5: 1 | EK5: 2 | EL5: 3 | EM5: 0 | EN5: 12 | EO5: 0 | EP5: 2 | EQ5: 3 | ER5: 3 | ES5: 0 | ET5: 0 | EU5: 0 | EV5: 0 | EW5: 0 | EX5: 5 | EY5: 0 | EZ5: 0 | FA5: 0 | FB5: 0 | FC5: 0 | FD5: 0 | FE5: 0 | FF5: 0 | FG5: 0 | FH5: 0 | FI5: 0 | FJ5: 0 | FK5: 0 | FL5: 0 | FM5: 0 | FN5: 0 | FO5: 0 | FP5: 0 | FQ5: 0 | FR5: 0 | FS5: 0 | FT5: 0 | FU5: 0 | FV5: 0 | FW5: 0 | FX5: 0 | FY5: 0 | FZ5: 0 | GA5: 4 | GB5: 0 | GC5: 0 | GD5: 0 | GE5: 0 | GF5: 0 | GG5: 4 | GH5: 0 | GI5: 0 | GJ5: 0 | GK5: 0 | GL5: 0 | GM5: 0 | GN5: 0 | GO5: 0 | GP5: 0 | GQ5: 0 | GR5: 0 | GS5: 0 | GT5: 0 | GU5: 0 | GV5: 0 | GW5: 0 | GX5: 2 | GY5: 0 | GZ5: 0 | HA5: 0 | HB5: 0 | HC5: 0 | HD5: 0 | HE5: 0 | HF5: 0 | HG5: 0 | HH5: 0 | HI5: 0 | HJ5: 0 | HK5: 0 | HL5: 6 | HM5: 0 | HN5: 0 | HO5: 1 | HP5: 0 | HQ5: 0 | HR5: 0 | HS5: 0 | HT5: 0 | HU5: 0 | HV5: 0 | HW5: 7 | HX5: 0 | HY5: 0 | HZ5: 0 | IA5: 0 | IB5: 0 | IC5: 0 | ID5: 0 | IE5: 0 | IF5: 0 | IG5: 0 | IH5: 0 | II5: 0 | IJ5: 0 | IK5: 0 | IL5: 0 | IM5: 0 | IN5: 0 | IO5: 0 | IP5: 0 | IQ5: 0 | IR5: 0 | IS5: 0 | IT5: 0 | IU5: 0 | IV5: 0 | IW5: 0 | IX5: 0 | IY5: 0 | IZ5: 0 | JA5: 0 | JB5: 0 | JC5: 0 | JD5: 0 | JE5: 0 | JF5: 0 | JG5: 0 | JH5: 0 | JI5: 0 | JJ5: 0 | JK5: 0 | JL5: 0 | JM5: 0 | JN5: 0 | JO5: 0 | JP5: 0 | JQ5: 0 | JR5: 0 | JS5: 0 | JT5: 0 | JU5: 0 | JV5: 0 | JW5: 0 | JX5: 0 | JY5: 0 | JZ5: 0 | KA5: 0 | KB5: 0 | KC5: 0 | KD5: 0 | KE5: 0 | KF5: 0 | KG5: 0 | KH5: 0 | KI5: 0 | KJ5: 5 | KK5: 3 | KL5: 0 | KM5: 0 | KN5: 0 | KO5: 0 | KP5: 0 | KQ5: 0 | KR5: 0 | KS5: 0 | KT5: 0 | KU5: 0 | KV5: 0 | KW5: 0 | KX5: 0 | KY5: 0 | KZ5: 0 | LA5: 0 | LB5: 0 | LC5: 0 | LD5: 0 | LE5: 0 | LF5: 0 | LG5: 0 | LH5: 0 | LI5: 0 | LJ5: 0 | LK5: 0 | LL5: 16 | LM5: 0 | LN5: 0 | LO5: 0 | LP5: 0 | LQ5: 0 | LR5: 8 | LS5: 0 | LT5: 0 | LU5: 0 | LV5: 0 | LW5: 0 | LX5: 0 | LY5: 0 | LZ5: 0 | MA5: 0 | MB5: 0 | MC5: 0 | MD5: 0 | ME5: 0 | MF5: 0 | MG5: 0 | MH5: 0 | MI5: 0 | MJ5: 0 | MK5: 0 | ML5: 0 | MM5: 0 | MN5: 0 | MO5: 0 | MP5: 3 | MQ5: 0 | MR5: 0 | MS5: 0 | MT5: 0 | MU5: 0 | MV5: 0 | MW5: 0 | MX5: 0 | MY5: 0 | MZ5: 0 | NA5: 0 | NB5: 0 | NC5: 0 | ND5: 1 | NE5: 0 | NF5: 0 | NG5: 0 | NH5: 0 | NI5: 0 | NJ5: 0 | NK5: 0 | NL5: 0 | NM5: 0 | NN5: 0 | NO5: 0 | NP5: 0 | NQ5: 1 | NR5: 0 | NS5: 0 | NT5: 1 | NU5: 0 | NV5: 0 | NW5: 0 | NX5: 0 | NY5: 0 | NZ5: 0 | OA5: 1 | OB5: 0 | OC5: 0 | OD5: 0 | OE5: 0 | OF5: 0 | OG5: 0 | OH5: 0 | OI5: 31 | OJ5: 21 | OK5: 13 | OL5: 0 | OM5: 0 | ON5: 0 | OO5: 0 | OP5: 0 | OQ5: 0 | OR5: 0 | OS5: 0 | OT5: 0 | OU5: 0 | OV5: 0 | OW5: 0 | OX5: 0 | OY5: 38 | OZ5: 0 | PA5: 0 | PB5: 0 | PC5: 0 | PD5: 0 | PE5: 0 | PF5: 0 | PG5: 0 | PH5: 0 | PI5: 0 | PJ5: 0 | PK5: 0 | PL5: 0 | PM5: 0 | PN5: 0 | PO5: 1 | PP5: 0 | PQ5: 0 | PR5: 0 | PS5: 0 | PT5: 0 | PU5: 0 | PV5: 0 | PW5: 0 | PX5: 0 | PY5: 0 | PZ5: 1 | QA5: 0 | QB5: 0 | QC5: 0 | QD5: 0 | QE5: 0 | QF5: 0 | QG5: 1 | QH5: 0 | QI5: 0 | QJ5: 0 | QK5: 0 | QL5: 0 | QM5: 0 | QN5: 0 | QO5: 0 | QP5: 0 | QQ5: 0 | QR5: 0 | QS5: 0 | QT5: 1 | QU5: 0 | QV5: 0 | QW5: 1 | QX5: 0 | QY5: 0 | QZ5: 0 | RA5: 1 | RB5: 1 | RC5: 2 | RD5: 0 | RE5: 0 | RF5: 0 | RG5: 0 | RH5: 1 | RI5: 1 | RJ5: 0 | RK5: 1 | RL5: 0 | RM5: 0 | RN5: 0 | RO5: 0 | RP5: 3 | RQ5: 0 | RR5: 0 | RS5: 0 | RT5: 0 | RU5: 1 | RV5: 1 | RW5: 1 | RX5: 0 | RY5: 8 | RZ5: 0 | SA5: 0 | SB5: 0 | SC5: 1 | SD5: 0 | SE5: 1 | SF5: 0 | SG5: 0 | SH5: 0 | SI5: 0 | SJ5: 1 | SK5: 0 | SL5: 0 | SM5: 1 | SN5: 0 | SO5: 0 | SP5: 1 | SQ5: 2 | SR5: 1 | SS5: 0 | ST5: 0 | SU5: 0 | SV5: 0 | SW5: 0 | SX5: 0 | SY5: 1 | SZ5: 0 | TA5: 0 | TB5: 0 | TC5: 0 | TD5: 0 | TE5: 0 | TF5: 0 | TG5: 0 | TH5: 0 | TI5: 0 | TJ5: 0 | TK5: 0 | TL5: 0 | TM5: 0 | TN5: 0 | TO5: 0 | TP5: 0 | TQ5: 0 | TR5: 0 | TS5: 0 | TT5: 0 | TU5: 0 | TV5: 0 | TW5: 0 | TX5: 0 | TY5: 0 | TZ5: 5 | UA5: 0 | UB5: 0 | UC5: 0 | UD5: 0 | UE5: 0 | UF5: 0 | UG5: 0 | UH5: 0 | UI5: 0 | UJ5: 0 | UK5: 0 | UL5: 0 | UM5: 0 | UN5: 0 | UO5: 0 | UP5: 0 | UQ5: 0 | UR5: 0 | US5: 0 | UT5: 1 | UU5: 0 | UV5: 8 | UW5: 1 | UX5: 0 | UY5: 0 | UZ5: 0 | VA5: 0 | VB5: 0 | VC5: 0 | VD5: 0 | VE5: 0 | VF5: 0 | VG5: 0 | VH5: 0 | VI5: 0 | VJ5: 0 | VK5: 0 | VL5: 0 | VM5: 3 | VN5: 7 | VO5: 1 | VP5: 0 | VQ5: 4 | VR5: 2 | VS5: 0 | VT5: 0 | VU5: 3 | VV5: 5 | VW5: 0 | VX5: 10 | VY5: 0 | VZ5: 0 | WA5: 0 | WB5: 1 | WC5: 0 | WD5: 0 | WE5: 0 | WF5: 0 | WG5: 0 | WH5: 0 | WI5: 0 | WJ5: 0 | WK5: 0 | WL5: 0 | WM5: 0 | WN5: 0 | WO5: 0 | WP5: 0 | WQ5: 0 | WR5: 0 | WS5: 0 | WT5: 0 | WU5: 0 | WV5: 0 | WW5: 0 | WX5: 0 | WY5: 0 | WZ5: 0 | XA5: 0 | XB5: 0 | XC5: 0 | XD5: 0 | XE5: 0 | XF5: 0 | XG5: 0 | XH5: 0 | XI5: 0 | XJ5: 0 | XK5: 0 | XL5: 0 | XM5: 0 | XN5: 0 | XO5: 1 | XP5: 0 | XQ5: 0 | XR5: 0 | XS5: 0 | XT5: 0 | XU5: 0 | XV5: 0 | XW5: 0 | XX5: 0 | XY5: 1 | XZ5: 0 | YA5: 0 | YB5: 0 | YC5: 0 | YD5: 0 | YE5: 0 | YF5: 0 | YG5: 0 | YH5: 0 | YI5: 2 | YJ5: 0 | YK5: 0 | YL5: 0 | YM5: 0 | YN5: 0 | YO5: 0 | YP5: 0 | YQ5: 0 | YR5: 0 | YS5: 11 | YT5: 0 | YU5: 0 | YV5: 0 | YW5: 1 | YX5: 0 | YY5: 0 | YZ5: 0 | ZA5: 0 | ZB5: 1 | ZC5: 0 | ZD5: 0 | ZE5: 0 | ZF5: 0 | ZG5: 0 | ZH5: 0 | ZI5: 0 | ZJ5: 0 | ZK5: 0 | ZL5: 0 | ZM5: 0 | ZN5: 0 | ZO5: 0 | ZP5: 0 | ZQ5: 0 | ZR5: 0 | ZS5: 0 | ZT5: 0 | ZU5: 2 | ZV5: 0 | ZW5: 1 | ZX5: 0 | ZY5: 13 | ZZ5: 1 | AAA5: 0 | AAB5: 1 | AAC5: 0 | AAD5: 0 | AAE5: 0 | AAF5: 9 | AAG5: 0 | AAH5: 2 | AAI5: 3 | AAJ5: 0 | AAK5: 0 | AAL5: 0 | AAM5: 0 | AAN5: 3 | AAO5: 3 | AAP5: 2 | AAQ5: =IF(LEFT($C5,5)="Total",0,IF(COUNTIF(ENTRY!$G$3:$BM$3,AAQ$1)=0,"CopyPasteValue",IFERROR(HLOOKUP(AAQ$1,ENTRY!$G$3:$BI$133,SUMIFS(ENTRY!$A$2:$A$133,ENTRY!$B$2:$B$133,$B5,ENTRY!$C$2:$C$133,$C5)-2,FALSE),0))) -> 2 | AAR5: =IF(LEFT($C5,5)="Total",0,IF(COUNTIF(ENTRY!$G$3:$BM$3,AAR$1)=0,"CopyPasteValue",IFERROR(HLOOKUP(AAR$1,ENTRY!$G$3:$BI$133,SUMIFS(ENTRY!$A$2:$A$133,ENTRY!$B$2:$B$133,$B5,ENTRY!$C$2:$C$133,$C5)-2,FALSE),0))) -> 1 | AAS5: =IF(LEFT($C5,5)="Total",0,IF(COUNTIF(ENTRY!$G$3:$BM$3,AAS$1)=0,"CopyPasteValue",IFERROR(HLOOKUP(AAS$1,ENTRY!$G$3:$BI$133,SUMIFS(ENTRY!$A$2:$A$133,ENTRY!$B$2:$B$133,$B5,ENTRY!$C$2:$C$133,$C5)-2,FALSE),0))) -> 0 | AAT5: =IF(LEFT($C5,5)="Total",0,IF(COUNTIF(ENTRY!$G$3:$BM$3,AAT$1)=0,"CopyPasteValue",IFERROR(HLOOKUP(AAT$1,ENTRY!$G$3:$BI$133,SUMIFS(ENTRY!$A$2:$A$133,ENTRY!$B$2:$B$133,$B5,ENTRY!$C$2:$C$133,$C5)-2,FALSE),0))) -> 11 | AAU5: =IF(LEFT($C5,5)="Total",0,IF(COUNTIF(ENTRY!$G$3:$BM$3,AAU$1)=0,"CopyPasteValue",IFERROR(HLOOKUP(AAU$1,ENTRY!$G$3:$BI$133,SUMIFS(ENTRY!$A$2:$A$133,ENTRY!$B$2:$B$133,$B5,ENTRY!$C$2:$C$133,$C5)-2,FALSE),0))) -> 0 | AAV5: =IF(LEFT($C5,5)="Total",0,IF(COUNTIF(ENTRY!$G$3:$BM$3,AAV$1)=0,"CopyPasteValue",IFERROR(HLOOKUP(AAV$1,ENTRY!$G$3:$BI$133,SUMIFS(ENTRY!$A$2:$A$133,ENTRY!$B$2:$B$133,$B5,ENTRY!$C$2:$C$133,$C5)-2,FALSE),0))) -> 1 | AAW5: =IF(LEFT($C5,5)="Total",0,IF(COUNTIF(ENTRY!$G$3:$BM$3,AAW$1)=0,"CopyPasteValue",IFERROR(HLOOKUP(AAW$1,ENTRY!$G$3:$BI$133,SUMIFS(ENTRY!$A$2:$A$133,ENTRY!$B$2:$B$133,$B5,ENTRY!$C$2:$C$133,$C5)-2,FALSE),0))) -> 7 | AAX5: =IF(LEFT($C5,5)="Total",0,IF(COUNTIF(ENTRY!$G$3:$BM$3,AAX$1)=0,"CopyPasteValue",IFERROR(HLOOKUP(AAX$1,ENTRY!$G$3:$BI$133,SUMIFS(ENTRY!$A$2:$A$133,ENTRY!$B$2:$B$133,$B5,ENTRY!$C$2:$C$133,$C5)-2,FALSE),0))) -> 0 | ... ABH5: =IF(LEFT($C5,5)="Total",0,IF(COUNTIF(ENTRY!$G$3:$BM$3,ABH$1)=0,"CopyPasteValue",IFERROR(HLOOKUP(ABH$1,ENTRY!$G$3:$BI$133,SUMIFS(ENTRY!$A$2:$A$133,ENTRY!$B$2:$B$133,$B5,ENTRY!$C$2:$C$133,$C5)-2,FALSE),0))) -> 0
B6: GC-Hand Bags | C6: BBC1 | D6: =CELL("row",D6) -> 6 | E6: =COUNTIF(ENTRY!C$4:C$294,C6) -> 1 | F6: 0 | G6: 0 | H6: 0 | I6: 0 | J6: 0 | K6: 0 | L6: 0 | M6: 0 | N6: 0 | O6: 0 | P6: 0 | Q6: 0 | R6: 0 | S6: 0 | T6: 0 | U6: 0 | V6: 0 | W6: 0 | X6: 0 | Y6: 0 | Z6: 0 | AA6: 0 | AB6: 0 | AC6: 0 | AD6: 0 | AE6: 0 | AF6: 1 | AG6: 0 | AH6: 0 | AI6: 0 | AJ6: 0 | AK6: 0 | AL6: 0 | AM6: 0 | AN6: 0 | AO6: 0 | AP6: 0 | AQ6: 0 | AR6: 0 | AS6: 0 | AT6: 0 | AU6: 0 | AV6: 0 | AW6: 0 | AX6: 0 | AY6: 0 | AZ6: 0 | BA6: 0 | BB6: 0 | BC6: 0 | BD6: 0 | BE6: 0 | BF6: 0 | BG6: 0 | BH6: 0 | BI6: 0 | BJ6: 1 | BK6: 0 | BL6: 0 | BM6: 0 | BN6: 0 | BO6: 0 | BP6: 0 | BQ6: 0 | BR6: 0 | BS6: 1 | BT6: 0 | BU6: 1 | BV6: 0 | BW6: 0 | BX6: 1 | BY6: 0 | BZ6: 0 | CA6: 0 | CB6: 2 | CC6: 0 | CD6: 0 | CE6: 1 | CF6: 0 | CG6: 0 | CH6: 0 | CI6: 0 | CJ6: 0 | CK6: 0 | CL6: 0 | CM6: 0 | CN6: 0 | CO6: 1 | CP6: 1 | CQ6: 0 | CR6: 0 | CS6: 1 | CT6: 0 | CU6: 0 | CV6: 0 | CW6: 1 | CX6: 0 | CY6: 0 | CZ6: 1 | DA6: 2 | DB6: 1 | DC6: 0 | DD6: 0 | DE6: 0 | DF6: 0 | DG6: 2 | DH6: 0 | DI6: 0 | DJ6: 1 | DK6: 0 | DL6: 0 | DM6: 0 | DN6: 1 | DO6: 0 | DP6: 0 | DQ6: 0 | DR6: 0 | DS6: 0 | DT6: 0 | DU6: 0 | DV6: 0 | DW6: 0 | DX6: 0 | DY6: 0 | DZ6: 0 | EA6: 0 | EB6: 0 | EC6: 0 | ED6: 0 | EE6: 0 | EF6: 0 | EG6: 0 | EH6: 0 | EI6: 0 | EJ6: 0 | EK6: 0 | EL6: 0 | EM6: 0 | EN6: 0 | EO6: 0 | EP6: 0 | EQ6: 0 | ER6: 0 | ES6: 0 | ET6: 0 | EU6: 0 | EV6: 0 | EW6: 0 | EX6: 0 | EY6: 0 | EZ6: 0 | FA6: 0 | FB6: 0 | FC6: 0 | FD6: 0 | FE6: 0 | FF6: 0 | FG6: 0 | FH6: 0 | FI6: 0 | FJ6: 0 | FK6: 0 | FL6: 0 | FM6: 0 | FN6: 0 | FO6: 0 | FP6: 0 | FQ6: 0 | FR6: 0 | FS6: 0 | FT6: 0 | FU6: 0 | FV6: 0 | FW6: 0 | FX6: 0 | FY6: 0 | FZ6: 0 | GA6: 2 | GB6: 0 | GC6: 0 | GD6: 0 | GE6: 0 | GF6: 0 | GG6: 2 | GH6: 0 | GI6: 0 | GJ6: 0 | GK6: 0 | GL6: 0 | GM6: 0 | GN6: 0 | GO6: 0 | GP6: 0 | GQ6: 0 | GR6: 0 | GS6: 0 | GT6: 0 | GU6: 0 | GV6: 0 | GW6: 0 | GX6: 0 | GY6: 0 | GZ6: 0 | HA6: 0 | HB6: 1 | HC6: 0 | HD6: 0 | HE6: 0 | HF6: 0 | HG6: 0 | HH6: 1 | HI6: 0 | HJ6: 0 | HK6: 0 | HL6: 0 | HM6: 0 | HN6: 0 | HO6: 1 | HP6: 0 | HQ6: 0 | HR6: 0 | HS6: 0 | HT6: 0 | HU6: 0 | HV6: 0 | HW6: 0 | HX6: 0 | HY6: 0 | HZ6: 0 | IA6: 0 | IB6: 0 | IC6: 0 | ID6: 0 | IE6: 0 | IF6: 0 | IG6: 0 | IH6: 0 | II6: 0 | IJ6: 0 | IK6: 0 | IL6: 0 | IM6: 0 | IN6: 0 | IO6: 0 | IP6: 0 | IQ6: 0 | IR6: 0 | IS6: 0 | IT6: 0 | IU6: 0 | IV6: 0 | IW6: 0 | IX6: 0 | IY6: 0 | IZ6: 0 | JA6: 0 | JB6: 0 | JC6: 0 | JD6: 0 | JE6: 0 | JF6: 0 | JG6: 0 | JH6: 0 | JI6: 0 | JJ6: 0 | JK6: 0 | JL6: 0 | JM6: 0 | JN6: 0 | JO6: 0 | JP6: 0 | JQ6: 0 | JR6: 0 | JS6: 0 | JT6: 0 | JU6: 0 | JV6: 0 | JW6: 0 | JX6: 0 | JY6: 0 | JZ6: 0 | KA6: 0 | KB6: 0 | KC6: 0 | KD6: 0 | KE6: 0 | KF6: 0 | KG6: 0 | KH6: 0 | KI6: 0 | KJ6: 1 | KK6: 0 | KL6: 0 | KM6: 0 | KN6: 0 | KO6: 0 | KP6: 0 | KQ6: 0 | KR6: 0 | KS6: 0 | KT6: 0 | KU6: 0 | KV6: 0 | KW6: 0 | KX6: 0 | KY6: 0 | KZ6: 0 | LA6: 0 | LB6: 0 | LC6: 0 | LD6: 1 | LE6: 1 | LF6: 0 | LG6: 0 | LH6: 0 | LI6: 1 | LJ6: 0 | LK6: 0 | LL6: 0 | LM6: 0 | LN6: 0 | LO6: 0 | LP6: 0 | LQ6: 0 | LR6: 0 | LS6: 0 | LT6: 0 | LU6: 0 | LV6: 0 | LW6: 0 | LX6: 0 | LY6: 0 | LZ6: 0 | MA6: 0 | MB6: 0 | MC6: 0 | MD6: 0 | ME6: 0 | MF6: 0 | MG6: 0 | MH6: 0 | MI6: 0 | MJ6: 0 | MK6: 0 | ML6: 0 | MM6: 0 | MN6: 2 | MO6: 0 | MP6: 0 | MQ6: 0 | MR6: 0 | MS6: 0 | MT6: 0 | MU6: 0 | MV6: 0 | MW6: 0 | MX6: 0 | MY6: 1 | MZ6: 0 | NA6: 0 | NB6: 0 | NC6: 0 | ND6: 0 | NE6: 0 | NF6: 0 | NG6: 0 | NH6: 0 | NI6: 1 | NJ6: 0 | NK6: 0 | NL6: 0 | NM6: 0 | NN6: 0 | NO6: 0 | NP6: 0 | NQ6: 0 | NR6: 0 | NS6: 0 | NT6: 1 | NU6: 0 | NV6: 0 | NW6: 0 | NX6: 0 | NY6: 0 | NZ6: 0 | OA6: 0 | OB6: 0 | OC6: 0 | OD6: 0 | OE6: 0 | OF6: 0 | OG6: 0 | OH6: 0 | OI6: 0 | OJ6: 0 | OK6: 0 | OL6: 0 | OM6: 0 | ON6: 0 | OO6: 0 | OP6: 0 | OQ6: 2 | OR6: 0 | OS6: 0 | OT6: 0 | OU6: 0 | OV6: 0 | OW6: 0 | OX6: 2 | OY6: 0 | OZ6: 0 | PA6: 0 | PB6: 0 | PC6: 0 | PD6: 0 | PE6: 0 | PF6: 0 | PG6: 0 | PH6: 0 | PI6: 0 | PJ6: 0 | PK6: 0 | PL6: 0 | PM6: 0 | PN6: 0 | PO6: 0 | PP6: 0 | PQ6: 0 | PR6: 0 | PS6: 0 | PT6: 0 | PU6: 0 | PV6: 0 | PW6: 0 | PX6: 1 | PY6: 0 | PZ6: 0 | QA6: 0 | QB6: 0 | QC6: 0 | QD6: 0 | QE6: 0 | QF6: 0 | QG6: 0 | QH6: 0 | QI6: 0 | QJ6: 0 | QK6: 0 | QL6: 0 | QM6: 0 | QN6: 0 | QO6: 0 | QP6: 0 | QQ6: 0 | QR6: 0 | QS6: 0 | QT6: 0 | QU6: 1 | QV6: 0 | QW6: 0 | QX6: 0 | QY6: 0 | QZ6: 0 | RA6: 0 | RB6: 0 | RC6: 0 | RD6: 0 | RE6: 0 | RF6: 0 | RG6: 0 | RH6: 0 | RI6: 0 | RJ6: 0 | RK6: 0 | RL6: 0 | RM6: 0 | RN6: 0 | RO6: 0 | RP6: 0 | RQ6: 0 | RR6: 0 | RS6: 0 | RT6: 0 | RU6: 0 | RV6: 0 | RW6: 0 | RX6: 0 | RY6: 0 | RZ6: 0 | SA6: 0 | SB6: 2 | SC6: 0 | SD6: 0 | SE6: 0 | SF6: 0 | SG6: 0 | SH6: 0 | SI6: 0 | SJ6: 0 | SK6: 0 | SL6: 0 | SM6: 0 | SN6: 0 | SO6: 0 | SP6: 0 | SQ6: 0 | SR6: 0 | SS6: 0 | ST6: 0 | SU6: 0 | SV6: 0 | SW6: 0 | SX6: 0 | SY6: 0 | SZ6: 0 | TA6: 0 | TB6: 0 | TC6: 0 | TD6: 0 | TE6: 0 | TF6: 0 | TG6: 0 | TH6: 0 | TI6: 0 | TJ6: 0 | TK6: 0 | TL6: 0 | TM6: 0 | TN6: 0 | TO6: 0 | TP6: 0 | TQ6: 0 | TR6: 0 | TS6: 0 | TT6: 0 | TU6: 0 | TV6: 0 | TW6: 1 | TX6: 0 | TY6: 0 | TZ6: 0 | UA6: 0 | UB6: 0 | UC6: 0 | UD6: 0 | UE6: 0 | UF6: 0 | UG6: 0 | UH6: 0 | UI6: 0 | UJ6: 0 | UK6: 0 | UL6: 0 | UM6: 0 | UN6: 0 | UO6: 0 | UP6: 0 | UQ6: 0 | UR6: 0 | US6: 0 | UT6: 0 | UU6: 0 | UV6: 0 | UW6: 0 | UX6: 0 | UY6: 0 | UZ6: 0 | VA6: 0 | VB6: 0 | VC6: 0 | VD6: 0 | VE6: 0 | VF6: 0 | VG6: 0 | VH6: 0 | VI6: 0 | VJ6: 0 | VK6: 0 | VL6: 0 | VM6: 2 | VN6: 0 | VO6: 0 | VP6: 0 | VQ6: 0 | VR6: 2 | VS6: 0 | VT6: 0 | VU6: 0 | VV6: 0 | VW6: 0 | VX6: 0 | VY6: 1 | VZ6: 1 | WA6: 0 | WB6: 1 | WC6: 0 | WD6: 0 | WE6: 0 | WF6: 0 | WG6: 0 | WH6: 0 | WI6: 0 | WJ6: 0 | WK6: 0 | WL6: 0 | WM6: 0 | WN6: 0 | WO6: 0 | WP6: 0 | WQ6: 0 | WR6: 0 | WS6: 0 | WT6: 0 | WU6: 0 | WV6: 0 | WW6: 0 | WX6: 0 | WY6: 0 | WZ6: 0 | XA6: 0 | XB6: 0 | XC6: 0 | XD6: 0 | XE6: 0 | XF6: 0 | XG6: 0 | XH6: 0 | XI6: 0 | XJ6: 0 | XK6: 0 | XL6: 0 | XM6: 0 | XN6: 0 | XO6: 1 | XP6: 0 | XQ6: 0 | XR6: 0 | XS6: 0 | XT6: 0 | XU6: 0 | XV6: 0 | XW6: 0 | XX6: 1 | XY6: 0 | XZ6: 0 | YA6: 0 | YB6: 0 | YC6: 0 | YD6: 0 | YE6: 0 | YF6: 0 | YG6: 0 | YH6: 0 | YI6: 0 | YJ6: 0 | YK6: 1 | YL6: 2 | YM6: 0 | YN6: 1 | YO6: 0 | YP6: 0 | YQ6: 0 | YR6: 0 | YS6: 0 | YT6: 0 | YU6: 0 | YV6: 0 | YW6: 0 | YX6: 0 | YY6: 0 | YZ6: 0 | ZA6: 0 | ZB6: 0 | ZC6: 0 | ZD6: 0 | ZE6: 0 | ZF6: 0 | ZG6: 0 | ZH6: 0 | ZI6: 0 | ZJ6: 0 | ZK6: 0 | ZL6: 1 | ZM6: 0 | ZN6: 0 | ZO6: 1 | ZP6: 0 | ZQ6: 0 | ZR6: 0 | ZS6: 0 | ZT6: 0 | ZU6: 0 | ZV6: 0 | ZW6: 0 | ZX6: 0 | ZY6: 0 | ZZ6: 0 | AAA6: 0 | AAB6: 0 | AAC6: 0 | AAD6: 0 | AAE6: 0 | AAF6: 0 | AAG6: 0 | AAH6: 0 | AAI6: 0 | AAJ6: 0 | AAK6: 0 | AAL6: 0 | AAM6: 0 | AAN6: 0 | AAO6: 0 | AAP6: 0 | AAQ6: =IF(LEFT($C6,5)="Total",0,IF(COUNTIF(ENTRY!$G$3:$BM$3,AAQ$1)=0,"CopyPasteValue",IFERROR(HLOOKUP(AAQ$1,ENTRY!$G$3:$BI$133,SUMIFS(ENTRY!$A$2:$A$133,ENTRY!$B$2:$B$133,$B6,ENTRY!$C$2:$C$133,$C6)-2,FALSE),0))) -> 0 | AAR6: =IF(LEFT($C6,5)="Total",0,IF(COUNTIF(ENTRY!$G$3:$BM$3,AAR$1)=0,"CopyPasteValue",IFERROR(HLOOKUP(AAR$1,ENTRY!$G$3:$BI$133,SUMIFS(ENTRY!$A$2:$A$133,ENTRY!$B$2:$B$133,$B6,ENTRY!$C$2:$C$133,$C6)-2,FALSE),0))) -> 0 | AAS6: =IF(LEFT($C6,5)="Total",0,IF(COUNTIF(ENTRY!$G$3:$BM$3,AAS$1)=0,"CopyPasteValue",IFERROR(HLOOKUP(AAS$1,ENTRY!$G$3:$BI$133,SUMIFS(ENTRY!$A$2:$A$133,ENTRY!$B$2:$B$133,$B6,ENTRY!$C$2:$C$133,$C6)-2,FALSE),0))) -> 0 | AAT6: =IF(LEFT($C6,5)="Total",0,IF(COUNTIF(ENTRY!$G$3:$BM$3,AAT$1)=0,"CopyPasteValue",IFERROR(HLOOKUP(AAT$1,ENTRY!$G$3:$BI$133,SUMIFS(ENTRY!$A$2:$A$133,ENTRY!$B$2:$B$133,$B6,ENTRY!$C$2:$C$133,$C6)-2,FALSE),0))) -> 0 | AAU6: =IF(LEFT($C6,5)="Total",0,IF(COUNTIF(ENTRY!$G$3:$BM$3,AAU$1)=0,"CopyPasteValue",IFERROR(HLOOKUP(AAU$1,ENTRY!$G$3:$BI$133,SUMIFS(ENTRY!$A$2:$A$133,ENTRY!$B$2:$B$133,$B6,ENTRY!$C$2:$C$133,$C6)-2,FALSE),0))) -> 0 | AAV6: =IF(LEFT($C6,5)="Total",0,IF(COUNTIF(ENTRY!$G$3:$BM$3,AAV$1)=0,"CopyPasteValue",IFERROR(HLOOKUP(AAV$1,ENTRY!$G$3:$BI$133,SUMIFS(ENTRY!$A$2:$A$133,ENTRY!$B$2:$B$133,$B6,ENTRY!$C$2:$C$133,$C6)-2,FALSE),0))) -> 0 | AAW6: =IF(LEFT($C6,5)="Total",0,IF(COUNTIF(ENTRY!$G$3:$BM$3,AAW$1)=0,"CopyPasteValue",IFERROR(HLOOKUP(AAW$1,ENTRY!$G$3:$BI$133,SUMIFS(ENTRY!$A$2:$A$133,ENTRY!$B$2:$B$133,$B6,ENTRY!$C$2:$C$133,$C6)-2,FALSE),0))) -> 0 | AAX6: =IF(LEFT($C6,5)="Total",0,IF(COUNTIF(ENTRY!$G$3:$BM$3,AAX$1)=0,"CopyPasteValue",IFERROR(HLOOKUP(AAX$1,ENTRY!$G$3:$BI$133,SUMIFS(ENTRY!$A$2:$A$133,ENTRY!$B$2:$B$133,$B6,ENTRY!$C$2:$C$133,$C6)-2,FALSE),0))) -> 0 | ... ABH6: =IF(LEFT($C6,5)="Total",0,IF(COUNTIF(ENTRY!$G$3:$BM$3,ABH$1)=0,"CopyPasteValue",IFERROR(HLOOKUP(ABH$1,ENTRY!$G$3:$BI$133,SUMIFS(ENTRY!$A$2:$A$133,ENTRY!$B$2:$B$133,$B6,ENTRY!$C$2:$C$133,$C6)-2,FALSE),0))) -> 0
B7: GC-Hand Bags | C7: BBC2 | D7: =CELL("row",D7) -> 7 | E7: =COUNTIF(ENTRY!C$4:C$294,C7) -> 1 | F7: 0 | G7: 0 | H7: 0 | I7: 0 | J7: 0 | K7: 0 | L7: 0 | M7: 0 | N7: 1 | O7: 0 | P7: 0 | Q7: 0 | R7: 0 | S7: 0 | T7: 0 | U7: 0 | V7: 0 | W7: 3 | X7: 0 | Y7: 0 | Z7: 0 | AA7: 0 | AB7: 0 | AC7: 0 | AD7: 0 | AE7: 0 | AF7: 0 | AG7: 0 | AH7: 0 | AI7: 0 | AJ7: 0 | AK7: 0 | AL7: 0 | AM7: 0 | AN7: 0 | AO7: 0 | AP7: 0 | AQ7: 0 | AR7: 0 | AS7: 0 | AT7: 0 | AU7: 0 | AV7: 0 | AW7: 0 | AX7: 0 | AY7: 1 | AZ7: 0 | BA7: 0 | BB7: 0 | BC7: 0 | BD7: 1 | BE7: 0 | BF7: 0 | BG7: 0 | BH7: 0 | BI7: 0 | BJ7: 3 | BK7: 0 | BL7: 0 | BM7: 1 | BN7: 0 | BO7: 0 | BP7: 0 | BQ7: 2 | BR7: 0 | BS7: 0 | BT7: 0 | BU7: 0 | BV7: 0 | BW7: 0 | BX7: 0 | BY7: 0 | BZ7: 0 | CA7: 0 | CB7: 0 | CC7: 0 | CD7: 0 | CE7: 0 | CF7: 0 | CG7: 0 | CH7: 0 | CI7: 0 | CJ7: 1 | CK7: 0 | CL7: 0 | CM7: 0 | CN7: 0 | CO7: 0 | CP7: 1 | CQ7: 0 | CR7: 0 | CS7: 0 | CT7: 0 | CU7: 2 | CV7: 0 | CW7: 0 | CX7: 0 | CY7: 0 | CZ7: 0 | DA7: 0 | DB7: 0 | DC7: 0 | DD7: 0 | DE7: 0 | DF7: 0 | DG7: 0 | DH7: 0 | DI7: 0 | DJ7: 0 | DK7: 0 | DL7: 0 | DM7: 0 | DN7: 0 | DO7: 0 | DP7: 0 | DQ7: 0 | DR7: 0 | DS7: 0 | DT7: 0 | DU7: 0 | DV7: 0 | DW7: 0 | DX7: 0 | DY7: 0 | DZ7: 0 | EA7: 0 | EB7: 0 | EC7: 0 | ED7: 0 | EE7: 0 | EF7: 0 | EG7: 0 | EH7: 0 | EI7: 0 | EJ7: 0 | EK7: 0 | EL7: 0 | EM7: 0 | EN7: 0 | EO7: 0 | EP7: 0 | EQ7: 0 | ER7: 0 | ES7: 0 | ET7: 0 | EU7: 0 | EV7: 0 | EW7: 0 | EX7: 0 | EY7: 0 | EZ7: 0 | FA7: 0 | FB7: 0 | FC7: 0 | FD7: 0 | FE7: 0 | FF7: 0 | FG7: 0 | FH7: 0 | FI7: 0 | FJ7: 0 | FK7: 0 | FL7: 0 | FM7: 0 | FN7: 0 | FO7: 0 | FP7: 0 | FQ7: 0 | FR7: 0 | FS7: 0 | FT7: 0 | FU7: 0 | FV7: 0 | FW7: 0 | FX7: 0 | FY7: 1 | FZ7: 0 | GA7: 1 | GB7: 0 | GC7: 0 | GD7: 0 | GE7: 0 | GF7: 0 | GG7: 2 | GH7: 0 | GI7: 0 | GJ7: 0 | GK7: 0 | GL7: 0 | GM7: 0 | GN7: 0 | GO7: 0 | GP7: 0 | GQ7: 0 | GR7: 0 | GS7: 0 | GT7: 0 | GU7: 0 | GV7: 0 | GW7: 0 | GX7: 0 | GY7: 0 | GZ7: 0 | HA7: 0 | HB7: 1 | HC7: 0 | HD7: 0 | HE7: 0 | HF7: 0 | HG7: 0 | HH7: 1 | HI7: 0 | HJ7: 0 | HK7: 0 | HL7: 0 | HM7: 0 | HN7: 0 | HO7: 1 | HP7: 0 | HQ7: 0 | HR7: 0 | HS7: 0 | HT7: 0 | HU7: 0 | HV7: 0 | HW7: 0 | HX7: 0 | HY7: 0 | HZ7: 0 | IA7: 0 | IB7: 0 | IC7: 0 | ID7: 0 | IE7: 0 | IF7: 0 | IG7: 0 | IH7: 0 | II7: 0 | IJ7: 0 | IK7: 0 | IL7: 0 | IM7: 0 | IN7: 0 | IO7: 0 | IP7: 0 | IQ7: 0 | IR7: 0 | IS7: 0 | IT7: 0 | IU7: 0 | IV7: 0 | IW7: 0 | IX7: 0 | IY7: 0 | IZ7: 0 | JA7: 0 | JB7: 0 | JC7: 0 | JD7: 0 | JE7: 0 | JF7: 0 | JG7: 0 | JH7: 0 | JI7: 0 | JJ7: 0 | JK7: 0 | JL7: 0 | JM7: 0 | JN7: 0 | JO7: 0 | JP7: 0 | JQ7: 0 | JR7: 0 | JS7: 0 | JT7: 0 | JU7: 0 | JV7: 0 | JW7: 0 | JX7: 0 | JY7: 0 | JZ7: 0 | KA7: 0 | KB7: 0 | KC7: 0 | KD7: 0 | KE7: 0 | KF7: 0 | KG7: 0 | KH7: 0 | KI7: 0 | KJ7: 1 | KK7: 1 | KL7: 0 | KM7: 0 | KN7: 0 | KO7: 0 | KP7: 0 | KQ7: 0 | KR7: 0 | KS7: 0 | KT7: 0 | KU7: 0 | KV7: 0 | KW7: 0 | KX7: 0 | KY7: 0 | KZ7: 0 | LA7: 0 | LB7: 0 | LC7: 0 | LD7: 2 | LE7: 0 | LF7: 0 | LG7: 0 | LH7: 0 | LI7: 0 | LJ7: 0 | LK7: 0 | LL7: 0 | LM7: 0 | LN7: 0 | LO7: 0 | LP7: 0 | LQ7: 0 | LR7: 1 | LS7: 0 | LT7: 1 | LU7: 0 | LV7: 0 | LW7: 0 | LX7: 0 | LY7: 0 | LZ7: 0 | MA7: 0 | MB7: 0 | MC7: 0 | MD7: 0 | ME7: 0 | MF7: 0 | MG7: 0 | MH7: 0 | MI7: 0 | MJ7: 0 | MK7: 0 | ML7: 0 | MM7: 0 | MN7: 2 | MO7: 0 | MP7: 0 | MQ7: 0 | MR7: 0 | MS7: 0 | MT7: 0 | MU7: 0 | MV7: 0 | MW7: 0 | MX7: 0 | MY7: 0 | MZ7: 0 | NA7: 0 | NB7: 1 | NC7: 0 | ND7: 0 | NE7: 0 | NF7: 1 | NG7: 0 | NH7: 0 | NI7: 0 | NJ7: 0 | NK7: 1 | NL7: 0 | NM7: 0 | NN7: 0 | NO7: 0 | NP7: 0 | NQ7: 0 | NR7: 0 | NS7: 0 | NT7: 1 | NU7: 0 | NV7: 0 | NW7: 0 | NX7: 0 | NY7: 0 | NZ7: 0 | OA7: 0 | OB7: 0 | OC7: 0 | OD7: 0 | OE7: 0 | OF7: 0 | OG7: 0 | OH7: 0 | OI7: 0 | OJ7: 0 | OK7: 0 | OL7: 0 | OM7: 0 | ON7: 0 | OO7: 0 | OP7: 0 | OQ7: 0 | OR7: 0 | OS7: 0 | OT7: 0 | OU7: 0 | OV7: 0 | OW7: 0 | OX7: 5 | OY7: 0 | OZ7: 0 | PA7: 0 | PB7: 0 | PC7: 0 | PD7: 0 | PE7: 0 | PF7: 0 | PG7: 0 | PH7: 0 | PI7: 0 | PJ7: 0 | PK7: 0 | PL7: 0 | PM7: 0 | PN7: 0 | PO7: 0 | PP7: 0 | PQ7: 0 | PR7: 0 | PS7: 0 | PT7: 0 | PU7: 0 | PV7: 0 | PW7: 0 | PX7: 0 | PY7: 0 | PZ7: 0 | QA7: 0 | QB7: 0 | QC7: 0 | QD7: 0 | QE7: 1 | QF7: 0 | QG7: 0 | QH7: 0 | QI7: 0 | QJ7: 0 | QK7: 0 | QL7: 0 | QM7: 0 | QN7: 0 | QO7: 0 | QP7: 0 | QQ7: 0 | QR7: 0 | QS7: 0 | QT7: 0 | QU7: 1 | QV7: 0 | QW7: 0 | QX7: 0 | QY7: 0 | QZ7: 0 | RA7: 0 | RB7: 0 | RC7: 0 | RD7: 0 | RE7: 0 | RF7: 0 | RG7: 0 | RH7: 0 | RI7: 0 | RJ7: 0 | RK7: 0 | RL7: 0 | RM7: 0 | RN7: 0 | RO7: 0 | RP7: 0 | RQ7: 0 | RR7: 0 | RS7: 0 | RT7: 0 | RU7: 0 | RV7: 0 | RW7: 0 | RX7: 0 | RY7: 0 | RZ7: 0 | SA7: 0 | SB7: 0 | SC7: 0 | SD7: 0 | SE7: 0 | SF7: 0 | SG7: 0 | SH7: 0 | SI7: 0 | SJ7: 0 | SK7: 0 | SL7: 0 | SM7: 0 | SN7: 0 | SO7: 0 | SP7: 0 | SQ7: 0 | SR7: 0 | SS7: 0 | ST7: 0 | SU7: 0 | SV7: 0 | SW7: 0 | SX7: 0 | SY7: 0 | SZ7: 0 | TA7: 0 | TB7: 0 | TC7: 0 | TD7: 0 | TE7: 0 | TF7: 0 | TG7: 0 | TH7: 0 | TI7: 0 | TJ7: 0 | TK7: 0 | TL7: 0 | TM7: 0 | TN7: 0 | TO7: 0 | TP7: 0 | TQ7: 0 | TR7: 0 | TS7: 0 | TT7: 0 | TU7: 0 | TV7: 0 | TW7: 0 | TX7: 0 | TY7: 0 | TZ7: 1 | UA7: 0 | UB7: 0 | UC7: 0 | UD7: 0 | UE7: 0 | UF7: 0 | UG7: 0 | UH7: 0 | UI7: 0 | UJ7: 0 | UK7: 0 | UL7: 0 | UM7: 0 | UN7: 0 | UO7: 0 | UP7: 0 | UQ7: 0 | UR7: 0 | US7: 0 | UT7: 0 | UU7: 0 | UV7: 1 | UW7: 1 | UX7: 0 | UY7: 0 | UZ7: 0 | VA7: 0 | VB7: 0 | VC7: 0 | VD7: 0 | VE7: 0 | VF7: 2 | VG7: 0 | VH7: 0 | VI7: 0 | VJ7: 0 | VK7: 0 | VL7: 0 | VM7: 2 | VN7: 0 | VO7: 0 | VP7: 0 | VQ7: 0 | VR7: 0 | VS7: 0 | VT7: 0 | VU7: 0 | VV7: 0 | VW7: 0 | VX7: 0 | VY7: 0 | VZ7: 0 | WA7: 0 | WB7: 0 | WC7: 1 | WD7: 0 | WE7: 0 | WF7: 0 | WG7: 0 | WH7: 0 | WI7: 0 | WJ7: 0 | WK7: 0 | WL7: 0 | WM7: 0 | WN7: 0 | WO7: 0 | WP7: 0 | WQ7: 0 | WR7: 0 | WS7: 0 | WT7: 0 | WU7: 0 | WV7: 1 | WW7: 0 | WX7: 0 | WY7: 0 | WZ7: 0 | XA7: 0 | XB7: 0 | XC7: 0 | XD7: 0 | XE7: 0 | XF7: 0 | XG7: 0 | XH7: 0 | XI7: 0 | XJ7: 0 | XK7: 0 | XL7: 0 | XM7: 0 | XN7: 0 | XO7: 0 | XP7: 0 | XQ7: 0 | XR7: 0 | XS7: 0 | XT7: 0 | XU7: 0 | XV7: 0 | XW7: 0 | XX7: 0 | XY7: 0 | XZ7: 0 | YA7: 0 | YB7: 0 | YC7: 0 | YD7: 0 | YE7: 0 | YF7: 0 | YG7: 0 | YH7: 0 | YI7: 0 | YJ7: 0 | YK7: 0 | YL7: 0 | YM7: 0 | YN7: 0 | YO7: 0 | YP7: 0 | YQ7: 0 | YR7: 0 | YS7: 0 | YT7: 0 | YU7: 0 | YV7: 0 | YW7: 0 | YX7: 0 | YY7: 1 | YZ7: 0 | ZA7: 0 | ZB7: 0 | ZC7: 0 | ZD7: 0 | ZE7: 0 | ZF7: 0 | ZG7: 0 | ZH7: 0 | ZI7: 0 | ZJ7: 0 | ZK7: 0 | ZL7: 0 | ZM7: 0 | ZN7: 0 | ZO7: 0 | ZP7: 0 | ZQ7: 0 | ZR7: 0 | ZS7: 0 | ZT7: 0 | ZU7: 0 | ZV7: 0 | ZW7: 0 | ZX7: 0 | ZY7: 0 | ZZ7: 0 | AAA7: 0 | AAB7: 0 | AAC7: 0 | AAD7: 0 | AAE7: 0 | AAF7: 1 | AAG7: 0 | AAH7: 0 | AAI7: 0 | AAJ7: 1 | AAK7: 0 | AAL7: 0 | AAM7: 0 | AAN7: 0 | AAO7: 0 | AAP7: 0 | AAQ7: =IF(LEFT($C7,5)="Total",0,IF(COUNTIF(ENTRY!$G$3:$BM$3,AAQ$1)=0,"CopyPasteValue",IFERROR(HLOOKUP(AAQ$1,ENTRY!$G$3:$BI$133,SUMIFS(ENTRY!$A$2:$A$133,ENTRY!$B$2:$B$133,$B7,ENTRY!$C$2:$C$133,$C7)-2,FALSE),0))) -> 0 | AAR7: =IF(LEFT($C7,5)="Total",0,IF(COUNTIF(ENTRY!$G$3:$BM$3,AAR$1)=0,"CopyPasteValue",IFERROR(HLOOKUP(AAR$1,ENTRY!$G$3:$BI$133,SUMIFS(ENTRY!$A$2:$A$133,ENTRY!$B$2:$B$133,$B7,ENTRY!$C$2:$C$133,$C7)-2,FALSE),0))) -> 0 | AAS7: =IF(LEFT($C7,5)="Total",0,IF(COUNTIF(ENTRY!$G$3:$BM$3,AAS$1)=0,"CopyPasteValue",IFERROR(HLOOKUP(AAS$1,ENTRY!$G$3:$BI$133,SUMIFS(ENTRY!$A$2:$A$133,ENTRY!$B$2:$B$133,$B7,ENTRY!$C$2:$C$133,$C7)-2,FALSE),0))) -> 0 | AAT7: =IF(LEFT($C7,5)="Total",0,IF(COUNTIF(ENTRY!$G$3:$BM$3,AAT$1)=0,"CopyPasteValue",IFERROR(HLOOKUP(AAT$1,ENTRY!$G$3:$BI$133,SUMIFS(ENTRY!$A$2:$A$133,ENTRY!$B$2:$B$133,$B7,ENTRY!$C$2:$C$133,$C7)-2,FALSE),0))) -> 0 | AAU7: =IF(LEFT($C7,5)="Total",0,IF(COUNTIF(ENTRY!$G$3:$BM$3,AAU$1)=0,"CopyPasteValue",IFERROR(HLOOKUP(AAU$1,ENTRY!$G$3:$BI$133,SUMIFS(ENTRY!$A$2:$A$133,ENTRY!$B$2:$B$133,$B7,ENTRY!$C$2:$C$133,$C7)-2,FALSE),0))) -> 0 | AAV7: =IF(LEFT($C7,5)="Total",0,IF(COUNTIF(ENTRY!$G$3:$BM$3,AAV$1)=0,"CopyPasteValue",IFERROR(HLOOKUP(AAV$1,ENTRY!$G$3:$BI$133,SUMIFS(ENTRY!$A$2:$A$133,ENTRY!$B$2:$B$133,$B7,ENTRY!$C$2:$C$133,$C7)-2,FALSE),0))) -> 0 | AAW7: =IF(LEFT($C7,5)="Total",0,IF(COUNTIF(ENTRY!$G$3:$BM$3,AAW$1)=0,"CopyPasteValue",IFERROR(HLOOKUP(AAW$1,ENTRY!$G$3:$BI$133,SUMIFS(ENTRY!$A$2:$A$133,ENTRY!$B$2:$B$133,$B7,ENTRY!$C$2:$C$133,$C7)-2,FALSE),0))) -> 0 | AAX7: =IF(LEFT($C7,5)="Total",0,IF(COUNTIF(ENTRY!$G$3:$BM$3,AAX$1)=0,"CopyPasteValue",IFERROR(HLOOKUP(AAX$1,ENTRY!$G$3:$BI$133,SUMIFS(ENTRY!$A$2:$A$133,ENTRY!$B$2:$B$133,$B7,ENTRY!$C$2:$C$133,$C7)-2,FALSE),0))) -> 0 | ... ABH7: =IF(LEFT($C7,5)="Total",0,IF(COUNTIF(ENTRY!$G$3:$BM$3,ABH$1)=0,"CopyPasteValue",IFERROR(HLOOKUP(ABH$1,ENTRY!$G$3:$BI$133,SUMIFS(ENTRY!$A$2:$A$133,ENTRY!$B$2:$B$133,$B7,ENTRY!$C$2:$C$133,$C7)-2,FALSE),0))) -> 0
B8: GC-Hand Bags | C8: BELT#3 | D8: =CELL("row",D8) -> 8 | E8: =COUNTIF(ENTRY!C$4:C$294,C8) -> 1 | F8: 0 | G8: 0 | H8: 0 | I8: 0 | J8: 0 | K8: 1 | L8: 0 | M8: 0 | N8: 0 | O8: 1 | P8: 0 | Q8: 0 | R8: 0 | S8: 0 | T8: 0 | U8: 0 | V8: 0 | W8: 0 | X8: 2 | Y8: 0 | Z8: 0 | AA8: 0 | AB8: 0 | AC8: 0 | AD8: 0 | AE8: 0 | AF8: 0 | AG8: 0 | AH8: 0 | AI8: 0 | AJ8: 0 | AK8: 0 | AL8: 0 | AM8: 0 | AN8: 0 | AO8: 2 | AP8: 0 | AQ8: 1 | AR8: 0 | AS8: 0 | AT8: 0 | AU8: 0 | AV8: 0 | AW8: 0 | AX8: 0 | AY8: 0 | AZ8: 0 | BA8: 0 | BB8: 0 | BC8: 0 | BD8: 0 | BE8: 0 | BF8: 0 | BG8: 0 | BH8: 0 | BI8: 0 | BJ8: 0 | BK8: 1 | BL8: 0 | BM8: 0 | BN8: 0 | BO8: 0 | BP8: 0 | BQ8: 1 | BR8: 0 | BS8: 0 | BT8: 0 | BU8: 0 | BV8: 0 | BW8: 0 | BX8: 1 | BY8: 0 | BZ8: 1 | CA8: 0 | CB8: 0 | CC8: 0 | CD8: 0 | CE8: 0 | CF8: 0 | CG8: 0 | CH8: 0 | CI8: 1 | CJ8: 0 | CK8: 0 | CL8: 0 | CM8: 0 | CN8: 0 | CO8: 0 | CP8: 0 | CQ8: 0 | CR8: 0 | CS8: 2 | CT8: 0 | CU8: 0 | CV8: 0 | CW8: 0 | CX8: 0 | CY8: 0 | CZ8: 0 | DA8: 0 | DB8: 0 | DC8: 0 | DD8: 0 | DE8: 0 | DF8: 0 | DG8: 0 | DH8: 0 | DI8: 0 | DJ8: 0 | DK8: 0 | DL8: 0 | DM8: 0 | DN8: 0 | DO8: 0 | DP8: 0 | DQ8: 0 | DR8: 0 | DS8: 0 | DT8: 0 | DU8: 0 | DV8: 0 | DW8: 0 | DX8: 0 | DY8: 0 | DZ8: 0 | EA8: 0 | EB8: 0 | EC8: 0 | ED8: 0 | EE8: 0 | EF8: 0 | EG8: 0 | EH8: 0 | EI8: 0 | EJ8: 0 | EK8: 0 | EL8: 0 | EM8: 0 | EN8: 0 | EO8: 0 | EP8: 0 | EQ8: 0 | ER8: 0 | ES8: 0 | ET8: 0 | EU8: 0 | EV8: 0 | EW8: 0 | EX8: 0 | EY8: 0 | EZ8: 0 | FA8: 0 | FB8: 0 | FC8: 0 | FD8: 0 | FE8: 0 | FF8: 0 | FG8: 0 | FH8: 0 | FI8: 0 | FJ8: 0 | FK8: 0 | FL8: 0 | FM8: 0 | FN8: 0 | FO8: 0 | FP8: 0 | FQ8: 0 | FR8: 0 | FS8: 0 | FT8: 0 | FU8: 0 | FV8: 0 | FW8: 0 | FX8: 0 | FY8: 2 | FZ8: 2 | GA8: 0 | GB8: 0 | GC8: 0 | GD8: 0 | GE8: 0 | GF8: 2 | GG8: 0 | GH8: 1 | GI8: 1 | GJ8: 0 | GK8: 0 | GL8: 0 | GM8: 0 | GN8: 0 | GO8: 0 | GP8: 0 | GQ8: 0 | GR8: 0 | GS8: 0 | GT8: 0 | GU8: 0 | GV8: 0 | GW8: 0 | GX8: 0 | GY8: 0 | GZ8: 0 | HA8: 0 | HB8: 2 | HC8: 0 | HD8: 0 | HE8: 0 | HF8: 0 | HG8: 0 | HH8: 1 | HI8: 0 | HJ8: 1 | HK8: 0 | HL8: 2 | HM8: 0 | HN8: 0 | HO8: 4 | HP8: 0 | HQ8: 1 | HR8: 0 | HS8: 0 | HT8: 0 | HU8: 0 | HV8: 1 | HW8: 0 | HX8: 1 | HY8: 0 | HZ8: 2 | IA8: 0 | IB8: 0 | IC8: 0 | ID8: 0 | IE8: 0 | IF8: 0 | IG8: 0 | IH8: 0 | II8: 0 | IJ8: 1 | IK8: 0 | IL8: 0 | IM8: 0 | IN8: 0 | IO8: 0 | IP8: 0 | IQ8: 0 | IR8: 0 | IS8: 0 | IT8: 0 | IU8: 0 | IV8: 0 | IW8: 0 | IX8: 0 | IY8: 0 | IZ8: 0 | JA8: 0 | JB8: 0 | JC8: 0 | JD8: 0 | JE8: 0 | JF8: 0 | JG8: 0 | JH8: 0 | JI8: 0 | JJ8: 0 | JK8: 0 | JL8: 0 | JM8: 0 | JN8: 0 | JO8: 0 | JP8: 0 | JQ8: 0 | JR8: 0 | JS8: 0 | JT8: 0 | JU8: 0 | JV8: 0 | JW8: 0 | JX8: 0 | JY8: 0 | JZ8: 0 | KA8: 0 | KB8: 0 | KC8: 0 | KD8: 0 | KE8: 0 | KF8: 0 | KG8: 0 | KH8: 0 | KI8: 0 | KJ8: 0 | KK8: 0 | KL8: 0 | KM8: 0 | KN8: 2 | KO8: 0 | KP8: 0 | KQ8: 0 | KR8: 0 | KS8: 0 | KT8: 0 | KU8: 0 | KV8: 0 | KW8: 0 | KX8: 0 | KY8: 0 | KZ8: 0 | LA8: 0 | LB8: 0 | LC8: 0 | LD8: 0 | LE8: 0 | LF8: 0 | LG8: 0 | LH8: 0 | LI8: 0 | LJ8: 1 | LK8: 0 | LL8: 0 | LM8: 0 | LN8: 0 | LO8: 0 | LP8: 1 | LQ8: 0 | LR8: 0 | LS8: 0 | LT8: 0 | LU8: 0 | LV8: 0 | LW8: 0 | LX8: 1 | LY8: 0 | LZ8: 0 | MA8: 0 | MB8: 0 | MC8: 0 | MD8: 0 | ME8: 0 | MF8: 0 | MG8: 0 | MH8: 0 | MI8: 0 | MJ8: 0 | MK8: 0 | ML8: 0 | MM8: 1 | MN8: 0 | MO8: 0 | MP8: 0 | MQ8: 0 | MR8: 1 | MS8: 0 | MT8: 0 | MU8: 0 | MV8: 0 | MW8: 0 | MX8: 0 | MY8: 3 | MZ8: 0 | NA8: 0 | NB8: 1 | NC8: 0 | ND8: 0 | NE8: 0 | NF8: 0 | NG8: 0 | NH8: 0 | NI8: 0 | NJ8: 0 | NK8: 0 | NL8: 0 | NM8: 1 | NN8: 0 | NO8: 1 | NP8: 0 | NQ8: 0 | NR8: 1 | NS8: 0 | NT8: 1 | NU8: 0 | NV8: 0 | NW8: 0 | NX8: 0 | NY8: 0 | NZ8: 0 | OA8: 2 | OB8: 0 | OC8: 0 | OD8: 0 | OE8: 1 | OF8: 0 | OG8: 0 | OH8: 0 | OI8: 0 | OJ8: 0 | OK8: 0 | OL8: 0 | OM8: 0 | ON8: 0 | OO8: 1 | OP8: 0 | OQ8: 1 | OR8: 0 | OS8: 0 | OT8: 0 | OU8: 0 | OV8: 1 | OW8: 0 | OX8: 0 | OY8: 0 | OZ8: 0 | PA8: 0 | PB8: 0 | PC8: 0 | PD8: 0 | PE8: 0 | PF8: 0 | PG8: 0 | PH8: 0 | PI8: 0 | PJ8: 0 | PK8: 0 | PL8: 0 | PM8: 0 | PN8: 0 | PO8: 0 | PP8: 0 | PQ8: 0 | PR8: 0 | PS8: 0 | PT8: 0 | PU8: 0 | PV8: 1 | PW8: 0 | PX8: 0 | PY8: 0 | PZ8: 0 | QA8: 0 | QB8: 0 | QC8: 0 | QD8: 0 | QE8: 0 | QF8: 0 | QG8: 0 | QH8: 0 | QI8: 0 | QJ8: 0 | QK8: 0 | QL8: 0 | QM8: 0 | QN8: 0 | QO8: 0 | QP8: 0 | QQ8: 0 | QR8: 0 | QS8: 0 | QT8: 0 | QU8: 0 | QV8: 0 | QW8: 0 | QX8: 0 | QY8: 0 | QZ8: 0 | RA8: 1 | RB8: 0 | RC8: 0 | RD8: 0 | RE8: 0 | RF8: 0 | RG8: 1 | RH8: 0 | RI8: 0 | RJ8: 0 | RK8: 0 | RL8: 0 | RM8: 0 | RN8: 0 | RO8: 0 | RP8: 0 | RQ8: 0 | RR8: 0 | RS8: 0 | RT8: 0 | RU8: 0 | RV8: 0 | RW8: 0 | RX8: 0 | RY8: 0 | RZ8: 0 | SA8: 0 | SB8: 0 | SC8: 1 | SD8: 3 | SE8: 0 | SF8: 0 | SG8: 1 | SH8: 0 | SI8: 0 | SJ8: 0 | SK8: 0 | SL8: 0 | SM8: 0 | SN8: 0 | SO8: 0 | SP8: 1 | SQ8: 0 | SR8: 0 | SS8: 0 | ST8: 0 | SU8: 0 | SV8: 0 | SW8: 0 | SX8: 0 | SY8: 0 | SZ8: 0 | TA8: 0 | TB8: 0 | TC8: 0 | TD8: 0 | TE8: 0 | TF8: 0 | TG8: 0 | TH8: 0 | TI8: 0 | TJ8: 0 | TK8: 0 | TL8: 0 | TM8: 0 | TN8: 0 | TO8: 0 | TP8: 0 | TQ8: 0 | TR8: 0 | TS8: 0 | TT8: 0 | TU8: 0 | TV8: 0 | TW8: 1 | TX8: 0 | TY8: 0 | TZ8: 1 | UA8: 0 | UB8: 0 | UC8: 0 | UD8: 0 | UE8: 0 | UF8: 0 | UG8: 0 | UH8: 0 | UI8: 0 | UJ8: 0 | UK8: 0 | UL8: 0 | UM8: 0 | UN8: 0 | UO8: 0 | UP8: 0 | UQ8: 0 | UR8: 0 | US8: 0 | UT8: 0 | UU8: 0 | UV8: 0 | UW8: 0 | UX8: 0 | UY8: 0 | UZ8: 0 | VA8: 0 | VB8: 0 | VC8: 0 | VD8: 0 | VE8: 0 | VF8: 0 | VG8: 0 | VH8: 0 | VI8: 0 | VJ8: 0 | VK8: 0 | VL8: 0 | VM8: 2 | VN8: 0 | VO8: 0 | VP8: 0 | VQ8: 0 | VR8: 0 | VS8: 0 | VT8: 0 | VU8: 2 | VV8: 0 | VW8: 0 | VX8: 0 | VY8: 0 | VZ8: 0 | WA8: 0 | WB8: 0 | WC8: 0 | WD8: 0 | WE8: 0 | WF8: 0 | WG8: 0 | WH8: 0 | WI8: 0 | WJ8: 0 | WK8: 0 | WL8: 0 | WM8: 0 | WN8: 0 | WO8: 0 | WP8: 0 | WQ8: 0 | WR8: 0 | WS8: 0 | WT8: 0 | WU8: 0 | WV8: 0 | WW8: 0 | WX8: 0 | WY8: 0 | WZ8: 0 | XA8: 0 | XB8: 0 | XC8: 1 | XD8: 0 | XE8: 0 | XF8: 0 | XG8: 4 | XH8: 0 | XI8: 0 | XJ8: 0 | XK8: 0 | XL8: 0 | XM8: 0 | XN8: 0 | XO8: 0 | XP8: 0 | XQ8: 0 | XR8: 0 | XS8: 0 | XT8: 0 | XU8: 1 | XV8: 0 | XW8: 1 | XX8: 0 | XY8: 0 | XZ8: 0 | YA8: 0 | YB8: 0 | YC8: 0 | YD8: 0 | YE8: 0 | YF8: 0 | YG8: 0 | YH8: 0 | YI8: 0 | YJ8: 0 | YK8: 0 | YL8: 0 | YM8: 0 | YN8: 0 | YO8: 0 | YP8: 0 | YQ8: 0 | YR8: 0 | YS8: 0 | YT8: 0 | YU8: 0 | YV8: 0 | YW8: 0 | YX8: 0 | YY8: 0 | YZ8: 0 | ZA8: 0 | ZB8: 0 | ZC8: 0 | ZD8: 0 | ZE8: 0 | ZF8: 0 | ZG8: 0 | ZH8: 0 | ZI8: 0 | ZJ8: 0 | ZK8: 0 | ZL8: 0 | ZM8: 0 | ZN8: 0 | ZO8: 0 | ZP8: 0 | ZQ8: 0 | ZR8: 0 | ZS8: 0 | ZT8: 0 | ZU8: 0 | ZV8: 0 | ZW8: 0 | ZX8: 0 | ZY8: 0 | ZZ8: 0 | AAA8: 0 | AAB8: 0 | AAC8: 0 | AAD8: 0 | AAE8: 0 | AAF8: 0 | AAG8: 0 | AAH8: 0 | AAI8: 0 | AAJ8: 0 | AAK8: 0 | AAL8: 0 | AAM8: 0 | AAN8: 0 | AAO8: 0 | AAP8: 0 | AAQ8: =IF(LEFT($C8,5)="Total",0,IF(COUNTIF(ENTRY!$G$3:$BM$3,AAQ$1)=0,"CopyPasteValue",IFERROR(HLOOKUP(AAQ$1,ENTRY!$G$3:$BI$133,SUMIFS(ENTRY!$A$2:$A$133,ENTRY!$B$2:$B$133,$B8,ENTRY!$C$2:$C$133,$C8)-2,FALSE),0))) -> 0 | AAR8: =IF(LEFT($C8,5)="Total",0,IF(COUNTIF(ENTRY!$G$3:$BM$3,AAR$1)=0,"CopyPasteValue",IFERROR(HLOOKUP(AAR$1,ENTRY!$G$3:$BI$133,SUMIFS(ENTRY!$A$2:$A$133,ENTRY!$B$2:$B$133,$B8,ENTRY!$C$2:$C$133,$C8)-2,FALSE),0))) -> 0 | AAS8: =IF(LEFT($C8,5)="Total",0,IF(COUNTIF(ENTRY!$G$3:$BM$3,AAS$1)=0,"CopyPasteValue",IFERROR(HLOOKUP(AAS$1,ENTRY!$G$3:$BI$133,SUMIFS(ENTRY!$A$2:$A$133,ENTRY!$B$2:$B$133,$B8,ENTRY!$C$2:$C$133,$C8)-2,FALSE),0))) -> 0 | AAT8: =IF(LEFT($C8,5)="Total",0,IF(COUNTIF(ENTRY!$G$3:$BM$3,AAT$1)=0,"CopyPasteValue",IFERROR(HLOOKUP(AAT$1,ENTRY!$G$3:$BI$133,SUMIFS(ENTRY!$A$2:$A$133,ENTRY!$B$2:$B$133,$B8,ENTRY!$C$2:$C$133,$C8)-2,FALSE),0))) -> 0 | AAU8: =IF(LEFT($C8,5)="Total",0,IF(COUNTIF(ENTRY!$G$3:$BM$3,AAU$1)=0,"CopyPasteValue",IFERROR(HLOOKUP(AAU$1,ENTRY!$G$3:$BI$133,SUMIFS(ENTRY!$A$2:$A$133,ENTRY!$B$2:$B$133,$B8,ENTRY!$C$2:$C$133,$C8)-2,FALSE),0))) -> 0 | AAV8: =IF(LEFT($C8,5)="Total",0,IF(COUNTIF(ENTRY!$G$3:$BM$3,AAV$1)=0,"CopyPasteValue",IFERROR(HLOOKUP(AAV$1,ENTRY!$G$3:$BI$133,SUMIFS(ENTRY!$A$2:$A$133,ENTRY!$B$2:$B$133,$B8,ENTRY!$C$2:$C$133,$C8)-2,FALSE),0))) -> 0 | AAW8: =IF(LEFT($C8,5)="Total",0,IF(COUNTIF(ENTRY!$G$3:$BM$3,AAW$1)=0,"CopyPasteValue",IFERROR(HLOOKUP(AAW$1,ENTRY!$G$3:$BI$133,SUMIFS(ENTRY!$A$2:$A$133,ENTRY!$B$2:$B$133,$B8,ENTRY!$C$2:$C$133,$C8)-2,FALSE),0))) -> 0 | AAX8: =IF(LEFT($C8,5)="Total",0,IF(COUNTIF(ENTRY!$G$3:$BM$3,AAX$1)=0,"CopyPasteValue",IFERROR(HLOOKUP(AAX$1,ENTRY!$G$3:$BI$133,SUMIFS(ENTRY!$A$2:$A$133,ENTRY!$B$2:$B$133,$B8,ENTRY!$C$2:$C$133,$C8)-2,FALSE),0))) -> 0 | ... ABH8: =IF(LEFT($C8,5)="Total",0,IF(COUNTIF(ENTRY!$G$3:$BM$3,ABH$1)=0,"CopyPasteValue",IFERROR(HLOOKUP(ABH$1,ENTRY!$G$3:$BI$133,SUMIFS(ENTRY!$A$2:$A$133,ENTRY!$B$2:$B$133,$B8,ENTRY!$C$2:$C$133,$C8)-2,FALSE),0))) -> 0
B9: GC-Hand Bags | C9: BELT-New Grade | D9: =CELL("row",D9) -> 9 | E9: =COUNTIF(ENTRY!C$4:C$294,C9) -> 1 | F9: 0 | G9: 1 | H9: 1 | I9: 0 | J9: 0 | K9: 1 | L9: 0 | M9: 4 | N9: 1 | O9: 0 | P9: 2 | Q9: 0 | R9: 0 | S9: 0 | T9: 3 | U9: 0 | V9: 0 | W9: 1 | X9: 0 | Y9: 1 | Z9: 0 | AA9: 0 | AB9: 0 | AC9: 0 | AD9: 0 | AE9: 0 | AF9: 0 | AG9: 0 | AH9: 0 | AI9: 0 | AJ9: 5 | AK9: 0 | AL9: 0 | AM9: 0 | AN9: 0 | AO9: 0 | AP9: 0 | AQ9: 0 | AR9: 0 | AS9: 0 | AT9: 0 | AU9: 0 | AV9: 0 | AW9: 0 | AX9: 0 | AY9: 0 | AZ9: 0 | BA9: 0 | BB9: 0 | BC9: 0 | BD9: 0 | BE9: 0 | BF9: 3 | BG9: 2 | BH9: 0 | BI9: 0 | BJ9: 0 | BK9: 0 | BL9: 0 | BM9: 0 | BN9: 0 | BO9: 0 | BP9: 0 | BQ9: 0 | BR9: 0 | BS9: 0 | BT9: 0 | BU9: 0 | BV9: 0 | BW9: 0 | BX9: 0 | BY9: 0 | BZ9: 0 | CA9: 0 | CB9: 0 | CC9: 0 | CD9: 0 | CE9: 0 | CF9: 0 | CG9: 0 | CH9: 0 | CI9: 4 | CJ9: 0 | CK9: 0 | CL9: 1 | CM9: 0 | CN9: 0 | CO9: 0 | CP9: 0 | CQ9: 0 | CR9: 0 | CS9: 5 | CT9: 0 | CU9: 0 | CV9: 0 | CW9: 0 | CX9: 0 | CY9: 0 | CZ9: 0 | DA9: 0 | DB9: 0 | DC9: 0 | DD9: 0 | DE9: 0 | DF9: 0 | DG9: 0 | DH9: 0 | DI9: 0 | DJ9: 0 | DK9: 0 | DL9: 0 | DM9: 0 | DN9: 0 | DO9: 0 | DP9: 0 | DQ9: 0 | DR9: 0 | DS9: 0 | DT9: 0 | DU9: 0 | DV9: 0 | DW9: 0 | DX9: 0 | DY9: 0 | DZ9: 0 | EA9: 0 | EB9: 0 | EC9: 0 | ED9: 0 | EE9: 0 | EF9: 0 | EG9: 0 | EH9: 0 | EI9: 0 | EJ9: 0 | EK9: 0 | EL9: 0 | EM9: 0 | EN9: 0 | EO9: 0 | EP9: 0 | EQ9: 0 | ER9: 0 | ES9: 0 | ET9: 0 | EU9: 0 | EV9: 0 | EW9: 0 | EX9: 0 | EY9: 0 | EZ9: 0 | FA9: 0 | FB9: 0 | FC9: 0 | FD9: 0 | FE9: 0 | FF9: 0 | FG9: 0 | FH9: 0 | FI9: 0 | FJ9: 0 | FK9: 0 | FL9: 0 | FM9: 0 | FN9: 0 | FO9: 0 | FP9: 0 | FQ9: 0 | FR9: 0 | FS9: 0 | FT9: 0 | FU9: 0 | FV9: 0 | FW9: 0 | FX9: 0 | FY9: 3 | FZ9: 0 | GA9: 0 | GB9: 1 | GC9: 0 | GD9: 0 | GE9: 0 | GF9: 3 | GG9: 0 | GH9: 0 | GI9: 1 | GJ9: 0 | GK9: 0 | GL9: 0 | GM9: 0 | GN9: 0 | GO9: 0 | GP9: 0 | GQ9: 0 | GR9: 0 | GS9: 0 | GT9: 0 | GU9: 0 | GV9: 0 | GW9: 0 | GX9: 0 | GY9: 0 | GZ9: 0 | HA9: 0 | HB9: 2 | HC9: 0 | HD9: 0 | HE9: 0 | HF9: 0 | HG9: 0 | HH9: 1 | HI9: 2 | HJ9: 0 | HK9: 0 | HL9: 0 | HM9: 0 | HN9: 0 | HO9: 2 | HP9: 0 | HQ9: 0 | HR9: 0 | HS9: 0 | HT9: 0 | HU9: 0 | HV9: 0 | HW9: 0 | HX9: 0 | HY9: 0 | HZ9: 0 | IA9: 0 | IB9: 0 | IC9: 0 | ID9: 0 | IE9: 0 | IF9: 0 | IG9: 0 | IH9: 0 | II9: 0 | IJ9: 0 | IK9: 0 | IL9: 0 | IM9: 0 | IN9: 0 | IO9: 0 | IP9: 0 | IQ9: 0 | IR9: 0 | IS9: 0 | IT9: 0 | IU9: 0 | IV9: 0 | IW9: 0 | IX9: 0 | IY9: 0 | IZ9: 0 | JA9: 0 | JB9: 0 | JC9: 0 | JD9: 0 | JE9: 0 | JF9: 0 | JG9: 0 | JH9: 0 | JI9: 0 | JJ9: 0 | JK9: 0 | JL9: 0 | JM9: 0 | JN9: 0 | JO9: 0 | JP9: 0 | JQ9: 0 | JR9: 0 | JS9: 0 | JT9: 0 | JU9: 0 | JV9: 0 | JW9: 0 | JX9: 0 | JY9: 0 | JZ9: 0 | KA9: 0 | KB9: 0 | KC9: 0 | KD9: 0 | KE9: 0 | KF9: 0 | KG9: 0 | KH9: 0 | KI9: 0 | KJ9: 5 | KK9: 0 | KL9: 0 | KM9: 0 | KN9: 0 | KO9: 1 | KP9: 0 | KQ9: 0 | KR9: 0 | KS9: 0 | KT9: 0 | KU9: 0 | KV9: 0 | KW9: 0 | KX9: 0 | KY9: 0 | KZ9: 0 | LA9: 0 | LB9: 0 | LC9: 0 | LD9: 0 | LE9: 0 | LF9: 1 | LG9: 0 | LH9: 0 | LI9: 1 | LJ9: 5 | LK9: 0 | LL9: 1 | LM9: 0 | LN9: 1 | LO9: 0 | LP9: 0 | LQ9: 0 | LR9: 1 | LS9: 0 | LT9: 4 | LU9: 0 | LV9: 0 | LW9: 0 | LX9: 0 | LY9: 0 | LZ9: 0 | MA9: 0 | MB9: 0 | MC9: 0 | MD9: 0 | ME9: 0 | MF9: 0 | MG9: 0 | MH9: 0 | MI9: 0 | MJ9: 0 | MK9: 0 | ML9: 0 | MM9: 0 | MN9: 6 | MO9: 0 | MP9: 0 | MQ9: 0 | MR9: 0 | MS9: 0 | MT9: 0 | MU9: 0 | MV9: 0 | MW9: 0 | MX9: 0 | MY9: 1 | MZ9: 0 | NA9: 0 | NB9: 2 | NC9: 0 | ND9: 1 | NE9: 0 | NF9: 0 | NG9: 0 | NH9: 0 | NI9: 0 | NJ9: 0 | NK9: 10 | NL9: 0 | NM9: 0 | NN9: 0 | NO9: 0 | NP9: 0 | NQ9: 0 | NR9: 0 | NS9: 0 | NT9: 5 | NU9: 0 | NV9: 0 | NW9: 0 | NX9: 0 | NY9: 6 | NZ9: 0 | OA9: 0 | OB9: 0 | OC9: 0 | OD9: 0 | OE9: 0 | OF9: 0 | OG9: 0 | OH9: 3 | OI9: 0 | OJ9: 0 | OK9: 0 | OL9: 0 | OM9: 0 | ON9: 0 | OO9: 0 | OP9: 0 | OQ9: 0 | OR9: 0 | OS9: 0 | OT9: 0 | OU9: 0 | OV9: 0 | OW9: 0 | OX9: 0 | OY9: 0 | OZ9: 0 | PA9: 0 | PB9: 0 | PC9: 0 | PD9: 0 | PE9: 0 | PF9: 0 | PG9: 0 | PH9: 0 | PI9: 0 | PJ9: 0 | PK9: 0 | PL9: 0 | PM9: 0 | PN9: 0 | PO9: 0 | PP9: 0 | PQ9: 0 | PR9: 0 | PS9: 0 | PT9: 0 | PU9: 0 | PV9: 0 | PW9: 0 | PX9: 1 | PY9: 1 | PZ9: 4 | QA9: 0 | QB9: 0 | QC9: 0 | QD9: 0 | QE9: 0 | QF9: 0 | QG9: 0 | QH9: 0 | QI9: 0 | QJ9: 0 | QK9: 0 | QL9: 0 | QM9: 0 | QN9: 0 | QO9: 0 | QP9: 0 | QQ9: 0 | QR9: 0 | QS9: 0 | QT9: 0 | QU9: 1 | QV9: 1 | QW9: 1 | QX9: 0 | QY9: 0 | QZ9: 0 | RA9: 0 | RB9: 0 | RC9: 0 | RD9: 1 | RE9: 0 | RF9: 0 | RG9: 1 | RH9: 0 | RI9: 0 | RJ9: 0 | RK9: 0 | RL9: 0 | RM9: 0 | RN9: 0 | RO9: 0 | RP9: 1 | RQ9: 1 | RR9: 0 | RS9: 0 | RT9: 0 | RU9: 0 | RV9: 0 | RW9: 1 | RX9: 0 | RY9: 1 | RZ9: 0 | SA9: 0 | SB9: 0 | SC9: 0 | SD9: 0 | SE9: 0 | SF9: 0 | SG9: 0 | SH9: 0 | SI9: 0 | SJ9: 0 | SK9: 0 | SL9: 0 | SM9: 0 | SN9: 0 | SO9: 0 | SP9: 0 | SQ9: 0 | SR9: 0 | SS9: 0 | ST9: 0 | SU9: 0 | SV9: 0 | SW9: 0 | SX9: 0 | SY9: 0 | SZ9: 0 | TA9: 0 | TB9: 0 | TC9: 0 | TD9: 0 | TE9: 0 | TF9: 0 | TG9: 0 | TH9: 0 | TI9: 0 | TJ9: 0 | TK9: 0 | TL9: 0 | TM9: 0 | TN9: 0 | TO9: 0 | TP9: 0 | TQ9: 0 | TR9: 0 | TS9: 0 | TT9: 0 | TU9: 0 | TV9: 0 | TW9: 1 | TX9: 0 | TY9: 0 | TZ9: 0 | UA9: 0 | UB9: 0 | UC9: 0 | UD9: 0 | UE9: 0 | UF9: 0 | UG9: 0 | UH9: 0 | UI9: 0 | UJ9: 0 | UK9: 0 | UL9: 0 | UM9: 0 | UN9: 0 | UO9: 0 | UP9: 0 | UQ9: 0 | UR9: 0 | US9: 0 | UT9: 0 | UU9: 0 | UV9: 0 | UW9: 0 | UX9: 0 | UY9: 0 | UZ9: 0 | VA9: 0 | VB9: 0 | VC9: 0 | VD9: 0 | VE9: 0 | VF9: 0 | VG9: 0 | VH9: 0 | VI9: 0 | VJ9: 0 | VK9: 0 | VL9: 0 | VM9: 0 | VN9: 0 | VO9: 0 | VP9: 0 | VQ9: 0 | VR9: 0 | VS9: 0 | VT9: 0 | VU9: 0 | VV9: 0 | VW9: 0 | VX9: 0 | VY9: 0 | VZ9: 0 | WA9: 0 | WB9: 0 | WC9: 0 | WD9: 0 | WE9: 0 | WF9: 0 | WG9: 0 | WH9: 0 | WI9: 0 | WJ9: 0 | WK9: 0 | WL9: 0 | WM9: 0 | WN9: 0 | WO9: 0 | WP9: 0 | WQ9: 0 | WR9: 0 | WS9: 0 | WT9: 0 | WU9: 0 | WV9: 0 | WW9: 0 | WX9: 0 | WY9: 0 | WZ9: 0 | XA9: 0 | XB9: 0 | XC9: 0 | XD9: 0 | XE9: 0 | XF9: 0 | XG9: 0 | XH9: 0 | XI9: 0 | XJ9: 0 | XK9: 0 | XL9: 0 | XM9: 0 | XN9: 0 | XO9: 0 | XP9: 0 | XQ9: 0 | XR9: 0 | XS9: 0 | XT9: 0 | XU9: 0 | XV9: 0 | XW9: 0 | XX9: 0 | XY9: 0 | XZ9: 0 | YA9: 0 | YB9: 0 | YC9: 0 | YD9: 0 | YE9: 0 | YF9: 0 | YG9: 0 | YH9: 0 | YI9: 0 | YJ9: 0 | YK9: 0 | YL9: 0 | YM9: 0 | YN9: 0 | YO9: 0 | YP9: 0 | YQ9: 0 | YR9: 0 | YS9: 0 | YT9: 0 | YU9: 0 | YV9: 0 | YW9: 0 | YX9: 0 | YY9: 0 | YZ9: 0 | ZA9: 0 | ZB9: 0 | ZC9: 0 | ZD9: 0 | ZE9: 0 | ZF9: 0 | ZG9: 0 | ZH9: 0 | ZI9: 0 | ZJ9: 0 | ZK9: 0 | ZL9: 0 | ZM9: 0 | ZN9: 0 | ZO9: 0 | ZP9: 0 | ZQ9: 0 | ZR9: 0 | ZS9: 0 | ZT9: 0 | ZU9: 0 | ZV9: 0 | ZW9: 0 | ZX9: 0 | ZY9: 0 | ZZ9: 0 | AAA9: 0 | AAB9: 0 | AAC9: 0 | AAD9: 0 | AAE9: 0 | AAF9: 0 | AAG9: 0 | AAH9: 0 | AAI9: 0 | AAJ9: 0 | AAK9: 0 | AAL9: 0 | AAM9: 0 | AAN9: 0 | AAO9: 0 | AAP9: 0 | AAQ9: =IF(LEFT($C9,5)="Total",0,IF(COUNTIF(ENTRY!$G$3:$BM$3,AAQ$1)=0,"CopyPasteValue",IFERROR(HLOOKUP(AAQ$1,ENTRY!$G$3:$BI$133,SUMIFS(ENTRY!$A$2:$A$133,ENTRY!$B$2:$B$133,$B9,ENTRY!$C$2:$C$133,$C9)-2,FALSE),0))) -> 0 | AAR9: =IF(LEFT($C9,5)="Total",0,IF(COUNTIF(ENTRY!$G$3:$BM$3,AAR$1)=0,"CopyPasteValue",IFERROR(HLOOKUP(AAR$1,ENTRY!$G$3:$BI$133,SUMIFS(ENTRY!$A$2:$A$133,ENTRY!$B$2:$B$133,$B9,ENTRY!$C$2:$C$133,$C9)-2,FALSE),0))) -> 0 | AAS9: =IF(LEFT($C9,5)="Total",0,IF(COUNTIF(ENTRY!$G$3:$BM$3,AAS$1)=0,"CopyPasteValue",IFERROR(HLOOKUP(AAS$1,ENTRY!$G$3:$BI$133,SUMIFS(ENTRY!$A$2:$A$133,ENTRY!$B$2:$B$133,$B9,ENTRY!$C$2:$C$133,$C9)-2,FALSE),0))) -> 0 | AAT9: =IF(LEFT($C9,5)="Total",0,IF(COUNTIF(ENTRY!$G$3:$BM$3,AAT$1)=0,"CopyPasteValue",IFERROR(HLOOKUP(AAT$1,ENTRY!$G$3:$BI$133,SUMIFS(ENTRY!$A$2:$A$133,ENTRY!$B$2:$B$133,$B9,ENTRY!$C$2:$C$133,$C9)-2,FALSE),0))) -> 0 | AAU9: =IF(LEFT($C9,5)="Total",0,IF(COUNTIF(ENTRY!$G$3:$BM$3,AAU$1)=0,"CopyPasteValue",IFERROR(HLOOKUP(AAU$1,ENTRY!$G$3:$BI$133,SUMIFS(ENTRY!$A$2:$A$133,ENTRY!$B$2:$B$133,$B9,ENTRY!$C$2:$C$133,$C9)-2,FALSE),0))) -> 0 | AAV9: =IF(LEFT($C9,5)="Total",0,IF(COUNTIF(ENTRY!$G$3:$BM$3,AAV$1)=0,"CopyPasteValue",IFERROR(HLOOKUP(AAV$1,ENTRY!$G$3:$BI$133,SUMIFS(ENTRY!$A$2:$A$133,ENTRY!$B$2:$B$133,$B9,ENTRY!$C$2:$C$133,$C9)-2,FALSE),0))) -> 0 | AAW9: =IF(LEFT($C9,5)="Total",0,IF(COUNTIF(ENTRY!$G$3:$BM$3,AAW$1)=0,"CopyPasteValue",IFERROR(HLOOKUP(AAW$1,ENTRY!$G$3:$BI$133,SUMIFS(ENTRY!$A$2:$A$133,ENTRY!$B$2:$B$133,$B9,ENTRY!$C$2:$C$133,$C9)-2,FALSE),0))) -> 0 | AAX9: =IF(LEFT($C9,5)="Total",0,IF(COUNTIF(ENTRY!$G$3:$BM$3,AAX$1)=0,"CopyPasteValue",IFERROR(HLOOKUP(AAX$1,ENTRY!$G$3:$BI$133,SUMIFS(ENTRY!$A$2:$A$133,ENTRY!$B$2:$B$133,$B9,ENTRY!$C$2:$C$133,$C9)-2,FALSE),0))) -> 0 | ... ABH9: =IF(LEFT($C9,5)="Total",0,IF(COUNTIF(ENTRY!$G$3:$BM$3,ABH$1)=0,"CopyPasteValue",IFERROR(HLOOKUP(ABH$1,ENTRY!$G$3:$BI$133,SUMIFS(ENTRY!$A$2:$A$133,ENTRY!$B$2:$B$133,$B9,ENTRY!$C$2:$C$133,$C9)-2,FALSE),0))) -> 0
B10: GC-Hand Bags | C10: BELT#1 | D10: =CELL("row",D10) -> 10 | E10: =COUNTIF(ENTRY!C$4:C$294,C10) -> 0 | F10: 0 | G10: 0 | H10: 0 | I10: 0 | J10: 0 | K10: 0 | L10: 0 | M10: 0 | N10: 0 | O10: 0 | P10: 0 | Q10: 0 | R10: 0 | S10: 0 | T10: 0 | U10: 0 | V10: 0 | W10: 0 | X10: 0 | Y10: 0 | Z10: 0 | AA10: 0 | AB10: 0 | AC10: 0 | AD10: 0 | AE10: 0 | AF10: 0 | AG10: 0 | AH10: 0 | AI10: 0 | AJ10: 0 | AK10: 0 | AL10: 0 | AM10: 0 | AN10: 0 | AO10: 0 | AP10: 0 | AQ10: 0 | AR10: 0 | AS10: 0 | AT10: 0 | AU10: 0 | AV10: 0 | AW10: 0 | AX10: 0 | AY10: 0 | AZ10: 0 | BA10: 0 | BB10: 0 | BC10: 0 | BD10: 0 | BE10: 0 | BF10: 0 | BG10: 0 | BH10: 0 | BI10: 0 | BJ10: 0 | BK10: 0 | BL10: 0 | BM10: 0 | BN10: 0 | BO10: 0 | BP10: 0 | BQ10: 0 | BR10: 0 | BS10: 0 | BT10: 0 | BU10: 0 | BV10: 0 | BW10: 0 | BX10: 0 | BY10: 0 | BZ10: 0 | CA10: 0 | CB10: 0 | CC10: 0 | CD10: 0 | CE10: 0 | CF10: 0 | CG10: 0 | CH10: 0 | CI10: 0 | CJ10: 0 | CK10: 0 | CL10: 0 | CM10: 0 | CN10: 0 | CO10: 0 | CP10: 0 | CQ10: 0 | CR10: 0 | CS10: 0 | CT10: 0 | CU10: 0 | CV10: 0 | CW10: 0 | CX10: 0 | CY10: 0 | CZ10: 0 | DA10: 0 | DB10: 0 | DC10: 0 | DD10: 0 | DE10: 0 | DF10: 0 | DG10: 0 | DH10: 0 | DI10: 0 | DJ10: 0 | DK10: 0 | DL10: 0 | DM10: 0 | DN10: 0 | DO10: 0 | DP10: 0 | DQ10: 0 | DR10: 0 | DS10: 0 | DT10: 0 | DU10: 0 | DV10: 0 | DW10: 0 | DX10: 0 | DY10: 0 | DZ10: 0 | EA10: 0 | EB10: 0 | EC10: 0 | ED10: 0 | EE10: 0 | EF10: 0 | EG10: 0 | EH10: 0 | EI10: 0 | EJ10: 0 | EK10: 0 | EL10: 0 | EM10: 0 | EN10: 0 | EO10: 0 | EP10: 0 | EQ10: 0 | ER10: 0 | ES10: 0 | ET10: 0 | EU10: 0 | EV10: 0 | EW10: 0 | EX10: 0 | EY10: 0 | EZ10: 0 | FA10: 0 | FB10: 0 | FC10: 0 | FD10: 0 | FE10: 0 | FF10: 0 | FG10: 0 | FH10: 0 | FI10: 0 | FJ10: 0 | FK10: 0 | FL10: 0 | FM10: 0 | FN10: 0 | FO10: 0 | FP10: 0 | FQ10: 0 | FR10: 0 | FS10: 0 | FT10: 0 | FU10: 0 | FV10: 0 | FW10: 0 | FX10: 0 | FY10: 0 | FZ10: 0 | GA10: 0 | GB10: 0 | GC10: 0 | GD10: 0 | GE10: 0 | GF10: 0 | GG10: 0 | GH10: 0 | GI10: 0 | GJ10: 0 | GK10: 0 | GL10: 0 | GM10: 0 | GN10: 0 | GO10: 0 | GP10: 0 | GQ10: 0 | GR10: 0 | GS10: 0 | GT10: 0 | GU10: 0 | GV10: 0 | GW10: 0 | GX10: 0 | GY10: 0 | GZ10: 0 | HA10: 0 | HB10: 0 | HC10: 0 | HD10: 0 | HE10: 0 | HF10: 0 | HG10: 0 | HH10: 0 | HI10: 0 | HJ10: 0 | HK10: 0 | HL10: 0 | HM10: 0 | HN10: 0 | HO10: 0 | HP10: 0 | HQ10: 0 | HR10: 0 | HS10: 0 | HT10: 0 | HU10: 0 | HV10: 0 | HW10: 0 | HX10: 0 | HY10: 0 | HZ10: 0 | IA10: 0 | IB10: 0 | IC10: 0 | ID10: 0 | IE10: 0 | IF10: 0 | IG10: 0 | IH10: 0 | II10: 0 | IJ10: 0 | IK10: 0 | IL10: 0 | IM10: 0 | IN10: 0 | IO10: 0 | IP10: 0 | IQ10: 0 | IR10: 0 | IS10: 0 | IT10: 0 | IU10: 0 | IV10: 0 | IW10: 0 | IX10: 0 | IY10: 0 | IZ10: 0 | JA10: 0 | JB10: 0 | JC10: 0 | JD10: 0 | JE10: 0 | JF10: 0 | JG10: 0 | JH10: 0 | JI10: 0 | JJ10: 0 | JK10: 0 | JL10: 0 | JM10: 0 | JN10: 0 | JO10: 0 | JP10: 0 | JQ10: 0 | JR10: 0 | JS10: 0 | JT10: 0 | JU10: 0 | JV10: 0 | JW10: 0 | JX10: 0 | JY10: 0 | JZ10: 0 | KA10: 0 | KB10: 0 | KC10: 0 | KD10: 0 | KE10: 0 | KF10: 0 | KG10: 0 | KH10: 0 | KI10: 0 | KJ10: 0 | KK10: 0 | KL10: 0 | KM10: 0 | KN10: 0 | KO10: 0 | KP10: 0 | KQ10: 0 | KR10: 0 | KS10: 0 | KT10: 0 | KU10: 0 | KV10: 0 | KW10: 0 | KX10: 0 | KY10: 0 | KZ10: 0 | LA10: 0 | LB10: 0 | LC10: 0 | LD10: 0 | LE10: 0 | LF10: 0 | LG10: 0 | LH10: 0 | LI10: 0 | LJ10: 0 | LK10: 0 | LL10: 0 | LM10: 0 | LN10: 0 | LO10: 0 | LP10: 0 | LQ10: 0 | LR10: 0 | LS10: 0 | LT10: 0 | LU10: 0 | LV10: 0 | LW10: 0 | LX10: 0 | LY10: 0 | LZ10: 0 | MA10: 0 | MB10: 0 | MC10: 0 | MD10: 0 | ME10: 0 | MF10: 0 | MG10: 0 | MH10: 0 | MI10: 0 | MJ10: 0 | MK10: 0 | ML10: 0 | MM10: 0 | MN10: 0 | MO10: 0 | MP10: 0 | MQ10: 0 | MR10: 0 | MS10: 0 | MT10: 0 | MU10: 0 | MV10: 0 | MW10: 0 | MX10: 0 | MY10: 0 | MZ10: 0 | NA10: 0 | NB10: 0 | NC10: 0 | ND10: 0 | NE10: 0 | NF10: 0 | NG10: 0 | NH10: 0 | NI10: 0 | NJ10: 0 | NK10: 0 | NL10: 0 | NM10: 0 | NN10: 0 | NO10: 0 | NP10: 0 | NQ10: 0 | NR10: 0 | NS10: 0 | NT10: 0 | NU10: 0 | NV10: 0 | NW10: 0 | NX10: 0 | NY10: 0 | NZ10: 0 | OA10: 0 | OB10: 0 | OC10: 0 | OD10: 0 | OE10: 0 | OF10: 0 | OG10: 0 | OH10: 0 | OI10: 0 | OJ10: 0 | OK10: 0 | OL10: 0 | OM10: 0 | ON10: 0 | OO10: 0 | OP10: 0 | OQ10: 0 | OR10: 0 | OS10: 0 | OT10: 0 | OU10: 0 | OV10: 0 | OW10: 0 | OX10: 0 | OY10: 0 | OZ10: 0 | PA10: 0 | PB10: 0 | PC10: 0 | PD10: 0 | PE10: 0 | PF10: 0 | PG10: 0 | PH10: 0 | PI10: 0 | PJ10: 0 | PK10: 0 | PL10: 0 | PM10: 0 | PN10: 0 | PO10: 0 | PP10: 0 | PQ10: 0 | PR10: 0 | PS10: 0 | PT10: 0 | PU10: 0 | PV10: 0 | PW10: 0 | PX10: 0 | PY10: 0 | PZ10: 0 | QA10: 0 | QB10: 0 | QC10: 0 | QD10: 0 | QE10: 0 | QF10: 0 | QG10: 0 | QH10: 0 | QI10: 0 | QJ10: 0 | QK10: 0 | QL10: 0 | QM10: 0 | QN10: 0 | QO10: 0 | QP10: 0 | QQ10: 0 | QR10: 0 | QS10: 0 | QT10: 0 | QU10: 0 | QV10: 0 | QW10: 0 | QX10: 0 | QY10: 0 | QZ10: 0 | RA10: 0 | RB10: 0 | RC10: 0 | RD10: 0 | RE10: 0 | RF10: 0 | RG10: 0 | RH10: 0 | RI10: 0 | RJ10: 0 | RK10: 0 | RL10: 0 | RM10: 0 | RN10: 0 | RO10: 0 | RP10: 0 | RQ10: 0 | RR10: 0 | RS10: 0 | RT10: 0 | RU10: 0 | RV10: 0 | RW10: 0 | RX10: 0 | RY10: 0 | RZ10: 0 | SA10: 0 | SB10: 0 | SC10: 0 | SD10: 0 | SE10: 0 | SF10: 0 | SG10: 0 | SH10: 0 | SI10: 0 | SJ10: 0 | SK10: 0 | SL10: 0 | SM10: 0 | SN10: 0 | SO10: 0 | SP10: 0 | SQ10: 0 | SR10: 0 | SS10: 0 | ST10: 0 | SU10: 0 | SV10: 0 | SW10: 0 | SX10: 0 | SY10: 0 | SZ10: 0 | TA10: 0 | TB10: 0 | TC10: 0 | TD10: 0 | TE10: 0 | TF10: 0 | TG10: 0 | TH10: 0 | TI10: 0 | TJ10: 0 | TK10: 0 | TL10: 0 | TM10: 0 | TN10: 0 | TO10: 0 | TP10: 0 | TQ10: 0 | TR10: 0 | TS10: 0 | TT10: 0 | TU10: 0 | TV10: 0 | TW10: 0 | TX10: 0 | TY10: 0 | TZ10: 0 | UA10: 0 | UB10: 0 | UC10: 0 | UD10: 0 | UE10: 0 | UF10: 0 | UG10: 0 | UH10: 0 | UI10: 0 | UJ10: 0 | UK10: 0 | UL10: 0 | UM10: 0 | UN10: 0 | UO10: 0 | UP10: 0 | UQ10: 0 | UR10: 0 | US10: 0 | UT10: 0 | UU10: 0 | UV10: 0 | UW10: 0 | UX10: 0 | UY10: 0 | UZ10: 0 | VA10: 0 | VB10: 0 | VC10: 0 | VD10: 0 | VE10: 0 | VF10: 0 | VG10: 0 | VH10: 0 | VI10: 0 | VJ10: 0 | VK10: 0 | VL10: 0 | VM10: 0 | VN10: 0 | VO10: 0 | VP10: 0 | VQ10: 0 | VR10: 0 | VS10: 0 | VT10: 0 | VU10: 0 | VV10: 0 | VW10: 0 | VX10: 0 | VY10: 0 | VZ10: 0 | WA10: 0 | WB10: 0 | WC10: 0 | WD10: 0 | WE10: 0 | WF10: 0 | WG10: 0 | WH10: 0 | WI10: 0 | WJ10: 0 | WK10: 0 | WL10: 0 | WM10: 0 | WN10: 0 | WO10: 0 | WP10: 0 | WQ10: 0 | WR10: 0 | WS10: 0 | WT10: 0 | WU10: 0 | WV10: 0 | WW10: 0 | WX10: 0 | WY10: 0 | WZ10: 0 | XA10: 0 | XB10: 0 | XC10: 0 | XD10: 0 | XE10: 0 | XF10: 0 | XG10: 0 | XH10: 0 | XI10: 0 | XJ10: 0 | XK10: 0 | XL10: 0 | XM10: 0 | XN10: 0 | XO10: 0 | XP10: 0 | XQ10: 0 | XR10: 0 | XS10: 0 | XT10: 0 | XU10: 0 | XV10: 0 | XW10: 0 | XX10: 0 | XY10: 0 | XZ10: 0 | YA10: 0 | YB10: 0 | YC10: 0 | YD10: 0 | YE10: 0 | YF10: 0 | YG10: 0 | YH10: 0 | YI10: 0 | YJ10: 0 | YK10: 0 | YL10: 0 | YM10: 0 | YN10: 0 | YO10: 0 | YP10: 0 | YQ10: 0 | YR10: 0 | YS10: 0 | YT10: 0 | YU10: 0 | YV10: 0 | YW10: 0 | YX10: 0 | YY10: 0 | YZ10: 0 | ZA10: 0 | ZB10: 0 | ZC10: 0 | ZD10: 0 | ZE10: 0 | ZF10: 0 | ZG10: 0 | ZH10: 0 | ZI10: 0 | ZJ10: 0 | ZK10: 0 | ZL10: 0 | ZM10: 0 | ZN10: 0 | ZO10: 0 | ZP10: 0 | ZQ10: 0 | ZR10: 0 | ZS10: 0 | ZT10: 0 | ZU10: 0 | ZV10: 0 | ZW10: 0 | ZX10: 0 | ZY10: 0 | ZZ10: 0 | AAA10: 0 | AAB10: 0 | AAC10: 0 | AAD10: 0 | AAE10: 0 | AAF10: 0 | AAG10: 0 | AAH10: 0 | AAI10: 0 | AAJ10: 0 | AAK10: 0 | AAL10: 0 | AAM10: 0 | AAN10: 0 | AAO10: 0 | AAP10: 0 | AAQ10: =IF(LEFT($C10,5)="Total",0,IF(COUNTIF(ENTRY!$G$3:$BM$3,AAQ$1)=0,"CopyPasteValue",IFERROR(HLOOKUP(AAQ$1,ENTRY!$G$3:$BI$133,SUMIFS(ENTRY!$A$2:$A$133,ENTRY!$B$2:$B$133,$B10,ENTRY!$C$2:$C$133,$C10)-2,FALSE),0))) -> 0 | AAR10: =IF(LEFT($C10,5)="Total",0,IF(COUNTIF(ENTRY!$G$3:$BM$3,AAR$1)=0,"CopyPasteValue",IFERROR(HLOOKUP(AAR$1,ENTRY!$G$3:$BI$133,SUMIFS(ENTRY!$A$2:$A$133,ENTRY!$B$2:$B$133,$B10,ENTRY!$C$2:$C$133,$C10)-2,FALSE),0))) -> 0 | AAS10: =IF(LEFT($C10,5)="Total",0,IF(COUNTIF(ENTRY!$G$3:$BM$3,AAS$1)=0,"CopyPasteValue",IFERROR(HLOOKUP(AAS$1,ENTRY!$G$3:$BI$133,SUMIFS(ENTRY!$A$2:$A$133,ENTRY!$B$2:$B$133,$B10,ENTRY!$C$2:$C$133,$C10)-2,FALSE),0))) -> 0 | AAT10: =IF(LEFT($C10,5)="Total",0,IF(COUNTIF(ENTRY!$G$3:$BM$3,AAT$1)=0,"CopyPasteValue",IFERROR(HLOOKUP(AAT$1,ENTRY!$G$3:$BI$133,SUMIFS(ENTRY!$A$2:$A$133,ENTRY!$B$2:$B$133,$B10,ENTRY!$C$2:$C$133,$C10)-2,FALSE),0))) -> 0 | AAU10: =IF(LEFT($C10,5)="Total",0,IF(COUNTIF(ENTRY!$G$3:$BM$3,AAU$1)=0,"CopyPasteValue",IFERROR(HLOOKUP(AAU$1,ENTRY!$G$3:$BI$133,SUMIFS(ENTRY!$A$2:$A$133,ENTRY!$B$2:$B$133,$B10,ENTRY!$C$2:$C$133,$C10)-2,FALSE),0))) -> 0 | AAV10: =IF(LEFT($C10,5)="Total",0,IF(COUNTIF(ENTRY!$G$3:$BM$3,AAV$1)=0,"CopyPasteValue",IFERROR(HLOOKUP(AAV$1,ENTRY!$G$3:$BI$133,SUMIFS(ENTRY!$A$2:$A$133,ENTRY!$B$2:$B$133,$B10,ENTRY!$C$2:$C$133,$C10)-2,FALSE),0))) -> 0 | AAW10: =IF(LEFT($C10,5)="Total",0,IF(COUNTIF(ENTRY!$G$3:$BM$3,AAW$1)=0,"CopyPasteValue",IFERROR(HLOOKUP(AAW$1,ENTRY!$G$3:$BI$133,SUMIFS(ENTRY!$A$2:$A$133,ENTRY!$B$2:$B$133,$B10,ENTRY!$C$2:$C$133,$C10)-2,FALSE),0))) -> 0 | AAX10: =IF(LEFT($C10,5)="Total",0,IF(COUNTIF(ENTRY!$G$3:$BM$3,AAX$1)=0,"CopyPasteValue",IFERROR(HLOOKUP(AAX$1,ENTRY!$G$3:$BI$133,SUMIFS(ENTRY!$A$2:$A$133,ENTRY!$B$2:$B$133,$B10,ENTRY!$C$2:$C$133,$C10)-2,FALSE),0))) -> 0 | ... ABH10: =IF(LEFT($C10,5)="Total",0,IF(COUNTIF(ENTRY!$G$3:$BM$3,ABH$1)=0,"CopyPasteValue",IFERROR(HLOOKUP(ABH$1,ENTRY!$G$3:$BI$133,SUMIFS(ENTRY!$A$2:$A$133,ENTRY!$B$2:$B$133,$B10,ENTRY!$C$2:$C$133,$C10)-2,FALSE),0))) -> 0
B11: GC-Hand Bags | C11: TRAVELBAG No.2 | D11: =CELL("row",D11) -> 11 | E11: =COUNTIF(ENTRY!C$4:C$294,C11) -> 1 | KJ11: 0 | KK11: 0 | KL11: 0 | KM11: 0 | KN11: 0 | KO11: 0 | KP11: 0 | KQ11: 0 | KR11: 0 | KS11: 0 | KT11: 0 | KU11: 0 | KV11: 0 | KW11: 0 | KX11: 0 | KY11: 0 | KZ11: 0 | LA11: 0 | LB11: 0 | LC11: 0 | LD11: 0 | LE11: 0 | LF11: 0 | LG11: 0 | LH11: 0 | LI11: 0 | LJ11: 0 | LK11: 0 | LL11: 0 | LM11: 0 | LN11: 0 | LO11: 0 | LP11: 0 | LQ11: 0 | LR11: 0 | LS11: 0 | LT11: 1 | LU11: 0 | LV11: 0 | LW11: 0 | LX11: 0 | LY11: 0 | LZ11: 0 | MA11: 0 | MB11: 0 | MC11: 0 | MD11: 0 | ME11: 0 | MF11: 0 | MG11: 0 | MH11: 0 | MI11: 0 | MJ11: 0 | MK11: 0 | ML11: 0 | MM11: 0 | MN11: 0 | MO11: 0 | MP11: 0 | MQ11: 0 | MR11: 0 | MS11: 0 | MT11: 0 | MU11: 0 | MV11: 0 | MW11: 0 | MX11: 0 | MY11: 0 | MZ11: 0 | NA11: 0 | NB11: 0 | NC11: 0 | ND11: 0 | NE11: 0 | NF11: 0 | NG11: 0 | NH11: 0 | NI11: 0 | NJ11: 0 | NK11: 0 | NL11: 0 | NM11: 0 | NN11: 0 | NO11: 0 | NP11: 0 | NQ11: 0 | NR11: 0 | NS11: 0 | NT11: 0 | NU11: 0 | NV11: 0 | NW11: 0 | NX11: 0 | NY11: 0 | NZ11: 0 | OA11: 0 | OB11: 0 | OC11: 0 | OD11: 0 | OE11: 0 | OF11: 0 | OG11: 0 | OH11: 0 | OI11: 0 | OJ11: 0 | OK11: 0 | OL11: 0 | OM11: 0 | ON11: 0 | OO11: 0 | OP11: 0 | OQ11: 0 | OR11: 0 | OS11: 0 | OT11: 0 | OU11: 0 | OV11: 0 | OW11: 0 | OX11: 0 | OY11: 0 | OZ11: 0 | PA11: 2 | PB11: 0 | PC11: 0 | PD11: 0 | PE11: 0 | PF11: 0 | PG11: 0 | PH11: 0 | PI11: 0 | PJ11: 1 | PK11: 0 | PL11: 0 | PM11: 1 | PN11: 0 | PO11: 0 | PP11: 0 | PQ11: 0 | PR11: 0 | PS11: 0 | PT11: 0 | PU11: 0 | PV11: 0 | PW11: 0 | PX11: 0 | PY11: 0 | PZ11: 0 | QA11: 0 | QB11: 0 | QC11: 0 | QD11: 0 | QE11: 0 | QF11: 0 | QG11: 0 | QH11: 0 | QI11: 0 | QJ11: 0 | QK11: 0 | QL11: 0 | QM11: 0 | QN11: 0 | QO11: 0 | QP11: 0 | QQ11: 0 | QR11: 0 | QS11: 0 | QT11: 0 | QU11: 0 | QV11: 4 | QW11: 0 | QX11: 0 | QY11: 0 | QZ11: 0 | RA11: 0 | RB11: 0 | RC11: 0 | RD11: 0 | RE11: 0 | RF11: 0 | RG11: 0 | RH11: 0 | RI11: 0 | RJ11: 0 | RK11: 0 | RL11: 0 | RM11: 0 | RN11: 0 | RO11: 0 | RP11: 0 | RQ11: 0 | RR11: 0 | RS11: 0 | RT11: 0 | RU11: 4 | RV11: 0 | RW11: 0 | RX11: 0 | RY11: 0 | RZ11: 0 | SA11: 0 | SB11: 0 | SC11: 0 | SD11: 0 | SE11: 0 | SF11: 0 | SG11: 0 | SH11: 0 | SI11: 0 | SJ11: 0 | SK11: 0 | SL11: 0 | SM11: 0 | SN11: 0 | SO11: 0 | SP11: 0 | SQ11: 0 | SR11: 0 | SS11: 0 | ST11: 0 | SU11: 0 | SV11: 0 | SW11: 0 | SX11: 0 | SY11: 0 | SZ11: 0 | TA11: 0 | TB11: 0 | TC11: 0 | TD11: 0 | TE11: 0 | TF11: 0 | TG11: 0 | TH11: 0 | TI11: 0 | TJ11: 0 | TK11: 0 | TL11: 0 | TM11: 0 | TN11: 0 | TO11: 0 | TP11: 0 | TQ11: 0 | TR11: 0 | TS11: 0 | TT11: 0 | TU11: 0 | TV11: 0 | TW11: 0 | TX11: 0 | TY11: 0 | TZ11: 0 | UA11: 0 | UB11: 0 | UC11: 0 | UD11: 0 | UE11: 0 | UF11: 0 | UG11: 0 | UH11: 0 | UI11: 0 | UJ11: 0 | UK11: 0 | UL11: 0 | UM11: 0 | UN11: 0 | UO11: 0 | UP11: 0 | UQ11: 0 | UR11: 0 | US11: 0 | UT11: 0 | UU11: 0 | UV11: 0 | UW11: 0 | UX11: 0 | UY11: 0 | UZ11: 0 | VA11: 0 | VB11: 0 | VC11: 0 | VD11: 0 | VE11: 0 | VF11: 0 | VG11: 0 | VH11: 0 | VI11: 0 | VJ11: 0 | VK11: 0 | VL11: 0 | VM11: 0 | VN11: 0 | VO11: 0 | VP11: 0 | VQ11: 0 | VR11: 0 | VS11: 0 | VT11: 0 | VU11: 0 | VV11: 0 | VW11: 0 | VX11: 0 | VY11: 0 | VZ11: 0 | WA11: 0 | WB11: 0 | WC11: 0 | WD11: 0 | WE11: 0 | WF11: 0 | WG11: 0 | WH11: 0 | WI11: 0 | WJ11: 0 | WK11: 0 | WL11: 0 | WM11: 0 | WN11: 0 | WO11: 0 | WP11: 0 | WQ11: 0 | WR11: 0 | WS11: 0 | WT11: 0 | WU11: 0 | WV11: 0 | WW11: 0 | WX11: 0 | WY11: 0 | WZ11: 0 | XA11: 0 | XB11: 0 | XC11: 0 | XD11: 0 | XE11: 0 | XF11: 0 | XG11: 0 | XH11: 0 | XI11: 0 | XJ11: 0 | XK11: 0 | XL11: 0 | XM11: 0 | XN11: 0 | XO11: 0 | XP11: 0 | XQ11: 0 | XR11: 0 | XS11: 0 | XT11: 0 | XU11: 0 | XV11: 0 | XW11: 0 | XX11: 0 | XY11: 0 | XZ11: 0 | YA11: 0 | YB11: 0 | YC11: 0 | YD11: 0 | YE11: 0 | YF11: 0 | YG11: 0 | YH11: 0 | YI11: 0 | YJ11: 0 | YK11: 0 | YL11: 0 | YM11: 0 | YN11: 0 | YO11: 0 | YP11: 0 | YQ11: 0 | YR11: 0 | YS11: 0 | YT11: 0 | YU11: 0 | YV11: 0 | YW11: 0 | YX11: 0 | YY11: 0 | YZ11: 0 | ZA11: 0 | ZB11: 0 | ZC11: 0 | ZD11: 0 | ZE11: 0 | ZF11: 0 | ZG11: 0 | ZH11: 0 | ZI11: 0 | ZJ11: 0 | ZK11: 0 | ZL11: 0 | ZM11: 0 | ZN11: 0 | ZO11: 0 | ZP11: 0 | ZQ11: 0 | ZR11: 0 | ZS11: 0 | ZT11: 0 | ZU11: 0 | ZV11: 0 | ZW11: 0 | ZX11: 0 | ZY11: 0 | ZZ11: 0 | AAA11: 0 | AAB11: 0 | AAC11: 0 | AAD11: 0 | AAE11: 0 | AAF11: 0 | AAG11: 0 | AAH11: 0 | AAI11: 0 | AAJ11: 0 | AAK11: 0 | AAL11: 0 | AAM11: 0 | AAN11: 0 | AAO11: 0 | AAP11: 0 | AAQ11: =IF(LEFT($C11,5)="Total",0,IF(COUNTIF(ENTRY!$G$3:$BM$3,AAQ$1)=0,"CopyPasteValue",IFERROR(HLOOKUP(AAQ$1,ENTRY!$G$3:$BI$133,SUMIFS(ENTRY!$A$2:$A$133,ENTRY!$B$2:$B$133,$B11,ENTRY!$C$2:$C$133,$C11)-2,FALSE),0))) -> 0 | AAR11: =IF(LEFT($C11,5)="Total",0,IF(COUNTIF(ENTRY!$G$3:$BM$3,AAR$1)=0,"CopyPasteValue",IFERROR(HLOOKUP(AAR$1,ENTRY!$G$3:$BI$133,SUMIFS(ENTRY!$A$2:$A$133,ENTRY!$B$2:$B$133,$B11,ENTRY!$C$2:$C$133,$C11)-2,FALSE),0))) -> 0 | AAS11: =IF(LEFT($C11,5)="Total",0,IF(COUNTIF(ENTRY!$G$3:$BM$3,AAS$1)=0,"CopyPasteValue",IFERROR(HLOOKUP(AAS$1,ENTRY!$G$3:$BI$133,SUMIFS(ENTRY!$A$2:$A$133,ENTRY!$B$2:$B$133,$B11,ENTRY!$C$2:$C$133,$C11)-2,FALSE),0))) -> 0 | AAT11: =IF(LEFT($C11,5)="Total",0,IF(COUNTIF(ENTRY!$G$3:$BM$3,AAT$1)=0,"CopyPasteValue",IFERROR(HLOOKUP(AAT$1,ENTRY!$G$3:$BI$133,SUMIFS(ENTRY!$A$2:$A$133,ENTRY!$B$2:$B$133,$B11,ENTRY!$C$2:$C$133,$C11)-2,FALSE),0))) -> 0 | AAU11: =IF(LEFT($C11,5)="Total",0,IF(COUNTIF(ENTRY!$G$3:$BM$3,AAU$1)=0,"CopyPasteValue",IFERROR(HLOOKUP(AAU$1,ENTRY!$G$3:$BI$133,SUMIFS(ENTRY!$A$2:$A$133,ENTRY!$B$2:$B$133,$B11,ENTRY!$C$2:$C$133,$C11)-2,FALSE),0))) -> 0 | AAV11: =IF(LEFT($C11,5)="Total",0,IF(COUNTIF(ENTRY!$G$3:$BM$3,AAV$1)=0,"CopyPasteValue",IFERROR(HLOOKUP(AAV$1,ENTRY!$G$3:$BI$133,SUMIFS(ENTRY!$A$2:$A$133,ENTRY!$B$2:$B$133,$B11,ENTRY!$C$2:$C$133,$C11)-2,FALSE),0))) -> 0 | AAW11: =IF(LEFT($C11,5)="Total",0,IF(COUNTIF(ENTRY!$G$3:$BM$3,AAW$1)=0,"CopyPasteValue",IFERROR(HLOOKUP(AAW$1,ENTRY!$G$3:$BI$133,SUMIFS(ENTRY!$A$2:$A$133,ENTRY!$B$2:$B$133,$B11,ENTRY!$C$2:$C$133,$C11)-2,FALSE),0))) -> 0 | AAX11: =IF(LEFT($C11,5)="Total",0,IF(COUNTIF(ENTRY!$G$3:$BM$3,AAX$1)=0,"CopyPasteValue",IFERROR(HLOOKUP(AAX$1,ENTRY!$G$3:$BI$133,SUMIFS(ENTRY!$A$2:$A$133,ENTRY!$B$2:$B$133,$B11,ENTRY!$C$2:$C$133,$C11)-2,FALSE),0))) -> 0 | ... ABH11: =IF(LEFT($C11,5)="Total",0,IF(COUNTIF(ENTRY!$G$3:$BM$3,ABH$1)=0,"CopyPasteValue",IFERROR(HLOOKUP(ABH$1,ENTRY!$G$3:$BI$133,SUMIFS(ENTRY!$A$2:$A$133,ENTRY!$B$2:$B$133,$B11,ENTRY!$C$2:$C$133,$C11)-2,FALSE),0))) -> 0
B12: GC-Hand Bags | C12: Travel Bag - Big Sack-90kg | D12: =CELL("row",D12) -> 12 | E12: =COUNTIF(ENTRY!C$4:C$294,C12) -> 1 | F12: 0 | G12: 0 | H12: 1 | I12: 0 | J12: 1 | K12: 0 | L12: 0 | M12: 0 | N12: 0 | O12: 0 | P12: 0 | Q12: 0 | R12: 0 | S12: 0 | T12: 0 | U12: 0 | V12: 0 | W12: 0 | X12: 0 | Y12: 0 | Z12: 0 | AA12: 0 | AB12: 0 | AC12: 0 | AD12: 0 | AE12: 0 | AF12: 0 | AG12: 0 | AH12: 0 | AI12: 0 | AJ12: 1 | AK12: 0 | AL12: 0 | AM12: 1 | AN12: 0 | AO12: 0 | AP12: 0 | AQ12: 0 | AR12: 0 | AS12: 0 | AT12: 0 | AU12: 0 | AV12: 0 | AW12: 0 | AX12: 0 | AY12: 0 | AZ12: 0 | BA12: 1 | BB12: 0 | BC12: 0 | BD12: 0 | BE12: 0 | BF12: 1 | BG12: 2 | BH12: 0 | BI12: 0 | BJ12: 1 | BK12: 0 | BL12: 0 | BM12: 0 | BN12: 0 | BO12: 0 | BP12: 0 | BQ12: 0 | BR12: 0 | BS12: 0 | BT12: 0 | BU12: 0 | BV12: 0 | BW12: 0 | BX12: 0 | BY12: 1 | BZ12: 0 | CA12: 0 | CB12: 0 | CC12: 0 | CD12: 0 | CE12: 0 | CF12: 0 | CG12: 0 | CH12: 0 | CI12: 1 | CJ12: 1 | CK12: 0 | CL12: 1 | CM12: 0 | CN12: 0 | CO12: 0 | CP12: 0 | CQ12: 0 | CR12: 0 | CS12: 2 | CT12: 0 | CU12: 0 | CV12: 0 | CW12: 0 | CX12: 0 | CY12: 0 | CZ12: 0 | DA12: 0 | DB12: 2 | DC12: 1 | DD12: 0 | DE12: 0 | DF12: 0 | DG12: 0 | DH12: 0 | DI12: 0 | DJ12: 0 | DK12: 0 | DL12: 0 | DM12: 0 | DN12: 0 | DO12: 0 | DP12: 0 | DQ12: 0 | DR12: 0 | DS12: 0 | DT12: 0 | DU12: 1 | DV12: 0 | DW12: 0 | DX12: 0 | DY12: 0 | DZ12: 0 | EA12: 0 | EB12: 0 | EC12: 0 | ED12: 0 | EE12: 0 | EF12: 0 | EG12: 0 | EH12: 0 | EI12: 0 | EJ12: 0 | EK12: 0 | EL12: 0 | EM12: 0 | EN12: 0 | EO12: 0 | EP12: 0 | EQ12: 0 | ER12: 0 | ES12: 0 | ET12: 0 | EU12: 0 | EV12: 0 | EW12: 0 | EX12: 0 | EY12: 0 | EZ12: 0 | FA12: 0 | FB12: 0 | FC12: 0 | FD12: 0 | FE12: 0 | FF12: 0 | FG12: 0 | FH12: 0 | FI12: 0 | FJ12: 0 | FK12: 0 | FL12: 0 | FM12: 0 | FN12: 0 | FO12: 0 | FP12: 0 | FQ12: 0 | FR12: 0 | FS12: 0 | FT12: 0 | FU12: 0 | FV12: 0 | FW12: 0 | FX12: 0 | FY12: 1 | FZ12: 0 | GA12: 0 | GB12: 0 | GC12: 0 | GD12: 0 | GE12: 0 | GF12: 1 | GG12: 0 | GH12: 0 | GI12: 0 | GJ12: 0 | GK12: 0 | GL12: 0 | GM12: 0 | GN12: 0 | GO12: 1 | GP12: 0 | GQ12: 0 | GR12: 0 | GS12: 0 | GT12: 0 | GU12: 0 | GV12: 0 | GW12: 0 | GX12: 0 | GY12: 0 | GZ12: 0 | HA12: 0 | HB12: 1 | HC12: 0 | HD12: 0 | HE12: 0 | HF12: 0 | HG12: 0 | HH12: 0 | HI12: 0 | HJ12: 0 | HK12: 0 | HL12: 1 | HM12: 0 | HN12: 0 | HO12: 0 | HP12: 0 | HQ12: 1 | HR12: 0 | HS12: 0 | HT12: 0 | HU12: 0 | HV12: 0 | HW12: 1 | HX12: 0 | HY12: 0 | HZ12: 0 | IA12: 0 | IB12: 0 | IC12: 1 | ID12: 0 | IE12: 1 | IF12: 0 | IG12: 0 | IH12: 0 | II12: 0 | IJ12: 1 | IK12: 0 | IL12: 0 | IM12: 0 | IN12: 0 | IO12: 0 | IP12: 0 | IQ12: 0 | IR12: 0 | IS12: 0 | IT12: 0 | IU12: 0 | IV12: 0 | IW12: 0 | IX12: 0 | IY12: 0 | IZ12: 0 | JA12: 0 | JB12: 0 | JC12: 0 | JD12: 0 | JE12: 0 | JF12: 0 | JG12: 0 | JH12: 0 | JI12: 0 | JJ12: 0 | JK12: 0 | JL12: 0 | JM12: 0 | JN12: 0 | JO12: 0 | JP12: 0 | JQ12: 0 | JR12: 0 | JS12: 0 | JT12: 0 | JU12: 0 | JV12: 0 | JW12: 0 | JX12: 0 | JY12: 0 | JZ12: 0 | KA12: 0 | KB12: 0 | KC12: 0 | KD12: 0 | KE12: 0 | KF12: 0 | KG12: 0 | KH12: 0 | KI12: 0 | KJ12: 1 | KK12: 0 | KL12: 0 | KM12: 0 | KN12: 0 | KO12: 0 | KP12: 0 | KQ12: 0 | KR12: 0 | KS12: 0 | KT12: 0 | KU12: 0 | KV12: 0 | KW12: 0 | KX12: 0 | KY12: 0 | KZ12: 0 | LA12: 0 | LB12: 0 | LC12: 0 | LD12: 1 | LE12: 0 | LF12: 0 | LG12: 0 | LH12: 0 | LI12: 0 | LJ12: 0 | LK12: 1 | LL12: 0 | LM12: 0 | LN12: 0 | LO12: 0 | LP12: 0 | LQ12: 0 | LR12: 0 | LS12: 0 | LT12: 0 | LU12: 0 | LV12: 0 | LW12: 0 | LX12: 0 | LY12: 0 | LZ12: 0 | MA12: 0 | MB12: 0 | MC12: 0 | MD12: 0 | ME12: 0 | MF12: 0 | MG12: 0 | MH12: 0 | MI12: 0 | MJ12: 0 | MK12: 0 | ML12: 0 | MM12: 0 | MN12: 1 | MO12: 0 | MP12: 0 | MQ12: 0 | MR12: 0 | MS12: 0 | MT12: 1 | MU12: 0 | MV12: 0 | MW12: 0 | MX12: 0 | MY12: 0 | MZ12: 0 | NA12: 0 | NB12: 0 | NC12: 0 | ND12: 0 | NE12: 0 | NF12: 0 | NG12: 0 | NH12: 0 | NI12: 0 | NJ12: 0 | NK12: 0 | NL12: 0 | NM12: 0 | NN12: 0 | NO12: 0 | NP12: 0 | NQ12: 0 | NR12: 0 | NS12: 0 | NT12: 0 | NU12: 0 | NV12: 0 | NW12: 0 | NX12: 0 | NY12: 0 | NZ12: 0 | OA12: 2 | OB12: 0 | OC12: 0 | OD12: 0 | OE12: 0 | OF12: 0 | OG12: 0 | OH12: 0 | OI12: 0 | OJ12: 0 | OK12: 0 | OL12: 0 | OM12: 0 | ON12: 0 | OO12: 0 | OP12: 0 | OQ12: 0 | OR12: 1 | OS12: 0 | OT12: 0 | OU12: 0 | OV12: 0 | OW12: 0 | OX12: 0 | OY12: 0 | OZ12: 0 | PA12: 0 | PB12: 0 | PC12: 0 | PD12: 0 | PE12: 0 | PF12: 0 | PG12: 0 | PH12: 0 | PI12: 0 | PJ12: 0 | PK12: 1 | PL12: 0 | PM12: 0 | PN12: 0 | PO12: 0 | PP12: 0 | PQ12: 0 | PR12: 0 | PS12: 0 | PT12: 0 | PU12: 0 | PV12: 0 | PW12: 0 | PX12: 0 | PY12: 0 | PZ12: 0 | QA12: 0 | QB12: 0 | QC12: 0 | QD12: 0 | QE12: 1 | QF12: 0 | QG12: 0 | QH12: 0 | QI12: 0 | QJ12: 0 | QK12: 0 | QL12: 0 | QM12: 0 | QN12: 0 | QO12: 0 | QP12: 0 | QQ12: 0 | QR12: 0 | QS12: 0 | QT12: 0 | QU12: 0 | QV12: 0 | QW12: 0 | QX12: 0 | QY12: 0 | QZ12: 1 | RA12: 0 | RB12: 0 | RC12: 0 | RD12: 0 | RE12: 0 | RF12: 0 | RG12: 0 | RH12: 0 | RI12: 0 | RJ12: 0 | RK12: 0 | RL12: 0 | RM12: 0 | RN12: 1 | RO12: 0 | RP12: 0 | RQ12: 0 | RR12: 0 | RS12: 0 | RT12: 0 | RU12: 0 | RV12: 0 | RW12: 0 | RX12: 0 | RY12: 0 | RZ12: 0 | SA12: 0 | SB12: 0 | SC12: 0 | SD12: 0 | SE12: 0 | SF12: 0 | SG12: 0 | SH12: 0 | SI12: 0 | SJ12: 0 | SK12: 0 | SL12: 0 | SM12: 0 | SN12: 0 | SO12: 0 | SP12: 0 | SQ12: 0 | SR12: 0 | SS12: 0 | ST12: 0 | SU12: 0 | SV12: 0 | SW12: 0 | SX12: 0 | SY12: 0 | SZ12: 0 | TA12: 0 | TB12: 0 | TC12: 0 | TD12: 0 | TE12: 0 | TF12: 0 | TG12: 0 | TH12: 0 | TI12: 0 | TJ12: 0 | TK12: 0 | TL12: 0 | TM12: 0 | TN12: 0 | TO12: 0 | TP12: 0 | TQ12: 0 | TR12: 0 | TS12: 1 | TT12: 0 | TU12: 0 | TV12: 0 | TW12: 0 | TX12: 0 | TY12: 0 | TZ12: 0 | UA12: 0 | UB12: 0 | UC12: 0 | UD12: 0 | UE12: 0 | UF12: 0 | UG12: 0 | UH12: 0 | UI12: 0 | UJ12: 0 | UK12: 0 | UL12: 0 | UM12: 0 | UN12: 0 | UO12: 0 | UP12: 0 | UQ12: 0 | UR12: 0 | US12: 0 | UT12: 0 | UU12: 0 | UV12: 0 | UW12: 0 | UX12: 0 | UY12: 0 | UZ12: 0 | VA12: 0 | VB12: 0 | VC12: 0 | VD12: 0 | VE12: 0 | VF12: 0 | VG12: 0 | VH12: 0 | VI12: 0 | VJ12: 0 | VK12: 0 | VL12: 0 | VM12: 1 | VN12: 0 | VO12: 0 | VP12: 0 | VQ12: 0 | VR12: 0 | VS12: 0 | VT12: 0 | VU12: 1 | VV12: 0 | VW12: 0 | VX12: 0 | VY12: 0 | VZ12: 0 | WA12: 0 | WB12: 0 | WC12: 0 | WD12: 0 | WE12: 0 | WF12: 0 | WG12: 0 | WH12: 0 | WI12: 0 | WJ12: 0 | WK12: 0 | WL12: 0 | WM12: 0 | WN12: 0 | WO12: 0 | WP12: 0 | WQ12: 0 | WR12: 0 | WS12: 0 | WT12: 0 | WU12: 0 | WV12: 0 | WW12: 0 | WX12: 0 | WY12: 0 | WZ12: 0 | XA12: 0 | XB12: 0 | XC12: 0 | XD12: 0 | XE12: 1 | XF12: 0 | XG12: 0 | XH12: 0 | XI12: 0 | XJ12: 0 | XK12: 0 | XL12: 0 | XM12: 0 | XN12: 0 | XO12: 0 | XP12: 0 | XQ12: 0 | XR12: 0 | XS12: 0 | XT12: 0 | XU12: 0 | XV12: 0 | XW12: 0 | XX12: 0 | XY12: 0 | XZ12: 0 | YA12: 0 | YB12: 0 | YC12: 0 | YD12: 0 | YE12: 0 | YF12: 0 | YG12: 0 | YH12: 0 | YI12: 0 | YJ12: 0 | YK12: 0 | YL12: 0 | YM12: 0 | YN12: 0 | YO12: 0 | YP12: 0 | YQ12: 0 | YR12: 0 | YS12: 0 | YT12: 0 | YU12: 0 | YV12: 0 | YW12: 0 | YX12: 0 | YY12: 0 | YZ12: 0 | ZA12: 0 | ZB12: 0 | ZC12: 0 | ZD12: 0 | ZE12: 0 | ZF12: 0 | ZG12: 0 | ZH12: 0 | ZI12: 0 | ZJ12: 0 | ZK12: 0 | ZL12: 0 | ZM12: 0 | ZN12: 0 | ZO12: 0 | ZP12: 0 | ZQ12: 0 | ZR12: 0 | ZS12: 0 | ZT12: 0 | ZU12: 0 | ZV12: 2 | ZW12: 0 | ZX12: 0 | ZY12: 0 | ZZ12: 2 | AAA12: 0 | AAB12: 0 | AAC12: 0 | AAD12: 0 | AAE12: 0 | AAF12: 0 | AAG12: 0 | AAH12: 0 | AAI12: 0 | AAJ12: 0 | AAK12: 0 | AAL12: 0 | AAM12: 1 | AAN12: 0 | AAO12: 0 | AAP12: 0 | AAQ12: =IF(LEFT($C12,5)="Total",0,IF(COUNTIF(ENTRY!$G$3:$BM$3,AAQ$1)=0,"CopyPasteValue",IFERROR(HLOOKUP(AAQ$1,ENTRY!$G$3:$BI$133,SUMIFS(ENTRY!$A$2:$A$133,ENTRY!$B$2:$B$133,$B12,ENTRY!$C$2:$C$133,$C12)-2,FALSE),0))) -> 0 | AAR12: =IF(LEFT($C12,5)="Total",0,IF(COUNTIF(ENTRY!$G$3:$BM$3,AAR$1)=0,"CopyPasteValue",IFERROR(HLOOKUP(AAR$1,ENTRY!$G$3:$BI$133,SUMIFS(ENTRY!$A$2:$A$133,ENTRY!$B$2:$B$133,$B12,ENTRY!$C$2:$C$133,$C12)-2,FALSE),0))) -> 0 | AAS12: =IF(LEFT($C12,5)="Total",0,IF(COUNTIF(ENTRY!$G$3:$BM$3,AAS$1)=0,"CopyPasteValue",IFERROR(HLOOKUP(AAS$1,ENTRY!$G$3:$BI$133,SUMIFS(ENTRY!$A$2:$A$133,ENTRY!$B$2:$B$133,$B12,ENTRY!$C$2:$C$133,$C12)-2,FALSE),0))) -> 0 | AAT12: =IF(LEFT($C12,5)="Total",0,IF(COUNTIF(ENTRY!$G$3:$BM$3,AAT$1)=0,"CopyPasteValue",IFERROR(HLOOKUP(AAT$1,ENTRY!$G$3:$BI$133,SUMIFS(ENTRY!$A$2:$A$133,ENTRY!$B$2:$B$133,$B12,ENTRY!$C$2:$C$133,$C12)-2,FALSE),0))) -> 1 | AAU12: =IF(LEFT($C12,5)="Total",0,IF(COUNTIF(ENTRY!$G$3:$BM$3,AAU$1)=0,"CopyPasteValue",IFERROR(HLOOKUP(AAU$1,ENTRY!$G$3:$BI$133,SUMIFS(ENTRY!$A$2:$A$133,ENTRY!$B$2:$B$133,$B12,ENTRY!$C$2:$C$133,$C12)-2,FALSE),0))) -> 0 | AAV12: =IF(LEFT($C12,5)="Total",0,IF(COUNTIF(ENTRY!$G$3:$BM$3,AAV$1)=0,"CopyPasteValue",IFERROR(HLOOKUP(AAV$1,ENTRY!$G$3:$BI$133,SUMIFS(ENTRY!$A$2:$A$133,ENTRY!$B$2:$B$133,$B12,ENTRY!$C$2:$C$133,$C12)-2,FALSE),0))) -> 0 | AAW12: =IF(LEFT($C12,5)="Total",0,IF(COUNTIF(ENTRY!$G$3:$BM$3,AAW$1)=0,"CopyPasteValue",IFERROR(HLOOKUP(AAW$1,ENTRY!$G$3:$BI$133,SUMIFS(ENTRY!$A$2:$A$133,ENTRY!$B$2:$B$133,$B12,ENTRY!$C$2:$C$133,$C12)-2,FALSE),0))) -> 0 | AAX12: =IF(LEFT($C12,5)="Total",0,IF(COUNTIF(ENTRY!$G$3:$BM$3,AAX$1)=0,"CopyPasteValue",IFERROR(HLOOKUP(AAX$1,ENTRY!$G$3:$BI$133,SUMIFS(ENTRY!$A$2:$A$133,ENTRY!$B$2:$B$133,$B12,ENTRY!$C$2:$C$133,$C12)-2,FALSE),0))) -> 0 | ... ABH12: =IF(LEFT($C12,5)="Total",0,IF(COUNTIF(ENTRY!$G$3:$BM$3,ABH$1)=0,"CopyPasteValue",IFERROR(HLOOKUP(ABH$1,ENTRY!$G$3:$BI$133,SUMIFS(ENTRY!$A$2:$A$133,ENTRY!$B$2:$B$133,$B12,ENTRY!$C$2:$C$133,$C12)-2,FALSE),0))) -> 0
B13: GC-Hand Bags | C13: HB1-New Grade | D13: =CELL("row",D13) -> 13 | E13: =COUNTIF(ENTRY!C$4:C$294,C13) -> 0 | F13: 0 | G13: 0 | H13: 0 | I13: 0 | J13: 0 | K13: 0 | L13: 0 | M13: 0 | N13: 0 | O13: 0 | P13: 0 | Q13: 0 | R13: 0 | S13: 0 | T13: 0 | U13: 0 | V13: 0 | W13: 0 | X13: 0 | Y13: 0 | Z13: 0 | AA13: 0 | AB13: 0 | AC13: 0 | AD13: 0 | AE13: 0 | AF13: 0 | AG13: 0 | AH13: 0 | AI13: 0 | AJ13: 0 | AK13: 0 | AL13: 0 | AM13: 0 | AN13: 0 | AO13: 0 | AP13: 0 | AQ13: 0 | AR13: 0 | AS13: 0 | AT13: 0 | AU13: 0 | AV13: 0 | AW13: 0 | AX13: 0 | AY13: 0 | AZ13: 0 | BA13: 0 | BB13: 0 | BC13: 0 | BD13: 0 | BE13: 0 | BF13: 0 | BG13: 0 | BH13: 0 | BI13: 0 | BJ13: 0 | BK13: 0 | BL13: 0 | BM13: 0 | BN13: 0 | BO13: 0 | BP13: 0 | BQ13: 0 | BR13: 0 | BS13: 0 | BT13: 0 | BU13: 0 | BV13: 0 | BW13: 0 | BX13: 0 | BY13: 0 | BZ13: 0 | CA13: 0 | CB13: 0 | CC13: 0 | CD13: 0 | CE13: 0 | CF13: 0 | CG13: 0 | CH13: 0 | CI13: 0 | CJ13: 0 | CK13: 0 | CL13: 0 | CM13: 0 | CN13: 0 | CO13: 0 | CP13: 0 | CQ13: 0 | CR13: 0 | CS13: 0 | CT13: 0 | CU13: 0 | CV13: 0 | CW13: 0 | CX13: 0 | CY13: 0 | CZ13: 0 | DA13: 0 | DB13: 0 | DC13: 0 | DD13: 0 | DE13: 0 | DF13: 0 | DG13: 0 | DH13: 0 | DI13: 0 | DJ13: 0 | DK13: 0 | DL13: 0 | DM13: 0 | DN13: 0 | DO13: 0 | DP13: 0 | DQ13: 0 | DR13: 0 | DS13: 0 | DT13: 0 | DU13: 0 | DV13: 0 | DW13: 0 | DX13: 0 | DY13: 0 | DZ13: 0 | EA13: 0 | EB13: 0 | EC13: 0 | ED13: 0 | EE13: 0 | EF13: 0 | EG13: 0 | EH13: 0 | EI13: 0 | EJ13: 0 | EK13: 0 | EL13: 0 | EM13: 0 | EN13: 0 | EO13: 0 | EP13: 0 | EQ13: 0 | ER13: 0 | ES13: 0 | ET13: 0 | EU13: 0 | EV13: 0 | EW13: 0 | EX13: 0 | EY13: 0 | EZ13: 0 | FA13: 0 | FB13: 0 | FC13: 0 | FD13: 0 | FE13: 0 | FF13: 0 | FG13: 0 | FH13: 0 | FI13: 0 | FJ13: 0 | FK13: 0 | FL13: 0 | FM13: 0 | FN13: 0 | FO13: 0 | FP13: 0 | FQ13: 0 | FR13: 0 | FS13: 0 | FT13: 0 | FU13: 0 | FV13: 0 | FW13: 0 | FX13: 0 | FY13: 0 | FZ13: 0 | GA13: 0 | GB13: 0 | GC13: 0 | GD13: 0 | GE13: 0 | GF13: 0 | GG13: 0 | GH13: 0 | GI13: 0 | GJ13: 0 | GK13: 0 | GL13: 0 | GM13: 0 | GN13: 0 | GO13: 0 | GP13: 0 | GQ13: 0 | GR13: 0 | GS13: 0 | GT13: 0 | GU13: 0 | GV13: 0 | GW13: 0 | GX13: 0 | GY13: 0 | GZ13: 0 | HA13: 0 | HB13: 0 | HC13: 0 | HD13: 0 | HE13: 0 | HF13: 0 | HG13: 0 | HH13: 0 | HI13: 0 | HJ13: 0 | HK13: 0 | HL13: 0 | HM13: 0 | HN13: 0 | HO13: 0 | HP13: 0 | HQ13: 0 | HR13: 0 | HS13: 0 | HT13: 0 | HU13: 0 | HV13: 0 | HW13: 0 | HX13: 0 | HY13: 0 | HZ13: 0 | IA13: 0 | IB13: 0 | IC13: 0 | ID13: 0 | IE13: 0 | IF13: 0 | IG13: 0 | IH13: 0 | II13: 0 | IJ13: 0 | IK13: 0 | IL13: 0 | IM13: 0 | IN13: 0 | IO13: 0 | IP13: 0 | IQ13: 0 | IR13: 0 | IS13: 0 | IT13: 0 | IU13: 0 | IV13: 0 | IW13: 0 | IX13: 0 | IY13: 0 | IZ13: 0 | JA13: 0 | JB13: 0 | JC13: 0 | JD13: 0 | JE13: 0 | JF13: 0 | JG13: 0 | JH13: 0 | JI13: 0 | JJ13: 0 | JK13: 0 | JL13: 0 | JM13: 0 | JN13: 0 | JO13: 0 | JP13: 0 | JQ13: 0 | JR13: 0 | JS13: 0 | JT13: 0 | JU13: 0 | JV13: 0 | JW13: 0 | JX13: 0 | JY13: 0 | JZ13: 0 | KA13: 0 | KB13: 0 | KC13: 0 | KD13: 0 | KE13: 0 | KF13: 0 | KG13: 0 | KH13: 0 | KI13: 0 | KJ13: 0 | KK13: 0 | KL13: 0 | KM13: 0 | KN13: 0 | KO13: 0 | KP13: 0 | KQ13: 0 | KR13: 0 | KS13: 0 | KT13: 0 | KU13: 0 | KV13: 0 | KW13: 0 | KX13: 0 | KY13: 0 | KZ13: 0 | LA13: 0 | LB13: 0 | LC13: 0 | LD13: 0 | LE13: 0 | LF13: 0 | LG13: 0 | LH13: 0 | LI13: 0 | LJ13: 0 | LK13: 0 | LL13: 0 | LM13: 0 | LN13: 0 | LO13: 0 | LP13: 0 | LQ13: 0 | LR13: 0 | LS13: 0 | LT13: 0 | LU13: 0 | LV13: 0 | LW13: 0 | LX13: 0 | LY13: 0 | LZ13: 0 | MA13: 0 | MB13: 0 | MC13: 0 | MD13: 0 | ME13: 0 | MF13: 0 | MG13: 0 | MH13: 0 | MI13: 0 | MJ13: 0 | MK13: 0 | ML13: 0 | MM13: 0 | MN13: 0 | MO13: 0 | MP13: 0 | MQ13: 0 | MR13: 0 | MS13: 0 | MT13: 0 | MU13: 0 | MV13: 0 | MW13: 0 | MX13: 0 | MY13: 0 | MZ13: 0 | NA13: 0 | NB13: 0 | NC13: 0 | ND13: 0 | NE13: 0 | NF13: 0 | NG13: 0 | NH13: 0 | NI13: 0 | NJ13: 0 | NK13: 0 | NL13: 0 | NM13: 0 | NN13: 0 | NO13: 0 | NP13: 0 | NQ13: 0 | NR13: 0 | NS13: 0 | NT13: 0 | NU13: 0 | NV13: 0 | NW13: 0 | NX13: 0 | NY13: 0 | NZ13: 0 | OA13: 0 | OB13: 0 | OC13: 0 | OD13: 0 | OE13: 0 | OF13: 0 | OG13: 0 | OH13: 0 | OI13: 0 | OJ13: 0 | OK13: 0 | OL13: 0 | OM13: 0 | ON13: 0 | OO13: 0 | OP13: 0 | OQ13: 0 | OR13: 0 | OS13: 0 | OT13: 0 | OU13: 0 | OV13: 0 | OW13: 0 | OX13: 0 | OY13: 0 | OZ13: 0 | PA13: 0 | PB13: 0 | PC13: 0 | PD13: 0 | PE13: 0 | PF13: 0 | PG13: 0 | PH13: 0 | PI13: 0 | PJ13: 0 | PK13: 0 | PL13: 0 | PM13: 0 | PN13: 0 | PO13: 0 | PP13: 0 | PQ13: 0 | PR13: 0 | PS13: 0 | PT13: 0 | PU13: 0 | PV13: 0 | PW13: 0 | PX13: 0 | PY13: 0 | PZ13: 0 | QA13: 0 | QB13: 0 | QC13: 0 | QD13: 0 | QE13: 0 | QF13: 0 | QG13: 0 | QH13: 0 | QI13: 0 | QJ13: 0 | QK13: 0 | QL13: 0 | QM13: 0 | QN13: 0 | QO13: 0 | QP13: 0 | QQ13: 0 | QR13: 0 | QS13: 0 | QT13: 0 | QU13: 0 | QV13: 0 | QW13: 0 | QX13: 0 | QY13: 0 | QZ13: 0 | RA13: 0 | RB13: 0 | RC13: 0 | RD13: 0 | RE13: 0 | RF13: 0 | RG13: 0 | RH13: 0 | RI13: 0 | RJ13: 0 | RK13: 0 | RL13: 0 | RM13: 0 | RN13: 0 | RO13: 0 | RP13: 0 | RQ13: 0 | RR13: 0 | RS13: 0 | RT13: 0 | RU13: 0 | RV13: 0 | RW13: 0 | RX13: 0 | RY13: 0 | RZ13: 0 | SA13: 0 | SB13: 0 | SC13: 0 | SD13: 0 | SE13: 0 | SF13: 0 | SG13: 0 | SH13: 0 | SI13: 0 | SJ13: 0 | SK13: 0 | SL13: 0 | SM13: 0 | SN13: 0 | SO13: 0 | SP13: 0 | SQ13: 0 | SR13: 0 | SS13: 0 | ST13: 0 | SU13: 0 | SV13: 0 | SW13: 0 | SX13: 0 | SY13: 0 | SZ13: 0 | TA13: 0 | TB13: 0 | TC13: 0 | TD13: 0 | TE13: 0 | TF13: 0 | TG13: 0 | TH13: 0 | TI13: 0 | TJ13: 0 | TK13: 0 | TL13: 0 | TM13: 0 | TN13: 0 | TO13: 0 | TP13: 0 | TQ13: 0 | TR13: 0 | TS13: 0 | TT13: 0 | TU13: 0 | TV13: 0 | TW13: 0 | TX13: 0 | TY13: 0 | TZ13: 0 | UA13: 0 | UB13: 0 | UC13: 0 | UD13: 0 | UE13: 0 | UF13: 0 | UG13: 0 | UH13: 0 | UI13: 0 | UJ13: 0 | UK13: 0 | UL13: 0 | UM13: 0 | UN13: 0 | UO13: 0 | UP13: 0 | UQ13: 0 | UR13: 0 | US13: 0 | UT13: 0 | UU13: 0 | UV13: 0 | UW13: 0 | UX13: 0 | UY13: 0 | UZ13: 0 | VA13: 0 | VB13: 0 | VC13: 0 | VD13: 0 | VE13: 0 | VF13: 0 | VG13: 0 | VH13: 0 | VI13: 0 | VJ13: 0 | VK13: 0 | VL13: 0 | VM13: 0 | VN13: 0 | VO13: 0 | VP13: 0 | VQ13: 0 | VR13: 0 | VS13: 0 | VT13: 0 | VU13: 0 | VV13: 0 | VW13: 0 | VX13: 0 | VY13: 0 | VZ13: 0 | WA13: 0 | WB13: 0 | WC13: 0 | WD13: 0 | WE13: 0 | WF13: 0 | WG13: 0 | WH13: 0 | WI13: 0 | WJ13: 0 | WK13: 0 | WL13: 0 | WM13: 0 | WN13: 0 | WO13: 0 | WP13: 0 | WQ13: 0 | WR13: 0 | WS13: 0 | WT13: 0 | WU13: 0 | WV13: 0 | WW13: 0 | WX13: 0 | WY13: 0 | WZ13: 0 | XA13: 0 | XB13: 0 | XC13: 0 | XD13: 0 | XE13: 0 | XF13: 0 | XG13: 0 | XH13: 0 | XI13: 0 | XJ13: 0 | XK13: 0 | XL13: 0 | XM13: 0 | XN13: 0 | XO13: 0 | XP13: 0 | XQ13: 0 | XR13: 0 | XS13: 0 | XT13: 0 | XU13: 0 | XV13: 0 | XW13: 0 | XX13: 0 | XY13: 0 | XZ13: 0 | YA13: 0 | YB13: 0 | YC13: 0 | YD13: 0 | YE13: 0 | YF13: 0 | YG13: 0 | YH13: 0 | YI13: 0 | YJ13: 0 | YK13: 0 | YL13: 0 | YM13: 0 | YN13: 0 | YO13: 0 | YP13: 0 | YQ13: 0 | YR13: 0 | YS13: 0 | YT13: 0 | YU13: 0 | YV13: 0 | YW13: 0 | YX13: 0 | YY13: 0 | YZ13: 0 | ZA13: 0 | ZB13: 0 | ZC13: 0 | ZD13: 0 | ZE13: 0 | ZF13: 0 | ZG13: 0 | ZH13: 0 | ZI13: 0 | ZJ13: 0 | ZK13: 0 | ZL13: 0 | ZM13: 0 | ZN13: 0 | ZO13: 0 | ZP13: 0 | ZQ13: 0 | ZR13: 0 | ZS13: 0 | ZT13: 0 | ZU13: 0 | ZV13: 0 | ZW13: 0 | ZX13: 0 | ZY13: 0 | ZZ13: 0 | AAA13: 0 | AAB13: 0 | AAC13: 0 | AAD13: 0 | AAE13: 0 | AAF13: 0 | AAG13: 0 | AAH13: 0 | AAI13: 0 | AAJ13: 0 | AAK13: 0 | AAL13: 0 | AAM13: 0 | AAN13: 0 | AAO13: 0 | AAP13: 0 | AAQ13: =IF(LEFT($C13,5)="Total",0,IF(COUNTIF(ENTRY!$G$3:$BM$3,AAQ$1)=0,"CopyPasteValue",IFERROR(HLOOKUP(AAQ$1,ENTRY!$G$3:$BI$133,SUMIFS(ENTRY!$A$2:$A$133,ENTRY!$B$2:$B$133,$B13,ENTRY!$C$2:$C$133,$C13)-2,FALSE),0))) -> 0 | AAR13: =IF(LEFT($C13,5)="Total",0,IF(COUNTIF(ENTRY!$G$3:$BM$3,AAR$1)=0,"CopyPasteValue",IFERROR(HLOOKUP(AAR$1,ENTRY!$G$3:$BI$133,SUMIFS(ENTRY!$A$2:$A$133,ENTRY!$B$2:$B$133,$B13,ENTRY!$C$2:$C$133,$C13)-2,FALSE),0))) -> 0 | AAS13: =IF(LEFT($C13,5)="Total",0,IF(COUNTIF(ENTRY!$G$3:$BM$3,AAS$1)=0,"CopyPasteValue",IFERROR(HLOOKUP(AAS$1,ENTRY!$G$3:$BI$133,SUMIFS(ENTRY!$A$2:$A$133,ENTRY!$B$2:$B$133,$B13,ENTRY!$C$2:$C$133,$C13)-2,FALSE),0))) -> 0 | AAT13: =IF(LEFT($C13,5)="Total",0,IF(COUNTIF(ENTRY!$G$3:$BM$3,AAT$1)=0,"CopyPasteValue",IFERROR(HLOOKUP(AAT$1,ENTRY!$G$3:$BI$133,SUMIFS(ENTRY!$A$2:$A$133,ENTRY!$B$2:$B$133,$B13,ENTRY!$C$2:$C$133,$C13)-2,FALSE),0))) -> 0 | AAU13: =IF(LEFT($C13,5)="Total",0,IF(COUNTIF(ENTRY!$G$3:$BM$3,AAU$1)=0,"CopyPasteValue",IFERROR(HLOOKUP(AAU$1,ENTRY!$G$3:$BI$133,SUMIFS(ENTRY!$A$2:$A$133,ENTRY!$B$2:$B$133,$B13,ENTRY!$C$2:$C$133,$C13)-2,FALSE),0))) -> 0 | AAV13: =IF(LEFT($C13,5)="Total",0,IF(COUNTIF(ENTRY!$G$3:$BM$3,AAV$1)=0,"CopyPasteValue",IFERROR(HLOOKUP(AAV$1,ENTRY!$G$3:$BI$133,SUMIFS(ENTRY!$A$2:$A$133,ENTRY!$B$2:$B$133,$B13,ENTRY!$C$2:$C$133,$C13)-2,FALSE),0))) -> 0 | AAW13: =IF(LEFT($C13,5)="Total",0,IF(COUNTIF(ENTRY!$G$3:$BM$3,AAW$1)=0,"CopyPasteValue",IFERROR(HLOOKUP(AAW$1,ENTRY!$G$3:$BI$133,SUMIFS(ENTRY!$A$2:$A$133,ENTRY!$B$2:$B$133,$B13,ENTRY!$C$2:$C$133,$C13)-2,FALSE),0))) -> 0 | AAX13: =IF(LEFT($C13,5)="Total",0,IF(COUNTIF(ENTRY!$G$3:$BM$3,AAX$1)=0,"CopyPasteValue",IFERROR(HLOOKUP(AAX$1,ENTRY!$G$3:$BI$133,SUMIFS(ENTRY!$A$2:$A$133,ENTRY!$B$2:$B$133,$B13,ENTRY!$C$2:$C$133,$C13)-2,FALSE),0))) -> 0 | ... ABH13: =IF(LEFT($C13,5)="Total",0,IF(COUNTIF(ENTRY!$G$3:$BM$3,ABH$1)=0,"CopyPasteValue",IFERROR(HLOOKUP(ABH$1,ENTRY!$G$3:$BI$133,SUMIFS(ENTRY!$A$2:$A$133,ENTRY!$B$2:$B$133,$B13,ENTRY!$C$2:$C$133,$C13)-2,FALSE),0))) -> 0
B14: GC-Hand Bags | C14: HB1 (Special) | D14: =CELL("row",D14) -> 14 | E14: =COUNTIF(ENTRY!C$4:C$294,C14) -> 1 | F14: 0 | G14: 0 | H14: 0 | I14: 0 | J14: 0 | K14: 0 | L14: 0 | M14: 0 | N14: 0 | O14: 0 | P14: 0 | Q14: 0 | R14: 0 | S14: 0 | T14: 0 | U14: 0 | V14: 0 | W14: 0 | X14: 0 | Y14: 0 | Z14: 0 | AA14: 0 | AB14: 0 | AC14: 0 | AD14: 0 | AE14: 0 | AF14: 0 | AG14: 0 | AH14: 0 | AI14: 0 | AJ14: 0 | AK14: 0 | AL14: 0 | AM14: 0 | AN14: 0 | AO14: 0 | AP14: 0 | AQ14: 0 | AR14: 0 | AS14: 0 | AT14: 0 | AU14: 0 | AV14: 0 | AW14: 0 | AX14: 0 | AY14: 0 | AZ14: 0 | BA14: 0 | BB14: 0 | BC14: 0 | BD14: 0 | BE14: 0 | BF14: 0 | BG14: 0 | BH14: 0 | BI14: 0 | BJ14: 0 | BK14: 0 | BL14: 0 | BM14: 0 | BN14: 0 | BO14: 0 | BP14: 0 | BQ14: 0 | BR14: 0 | BS14: 0 | BT14: 0 | BU14: 0 | BV14: 0 | BW14: 0 | BX14: 0 | BY14: 0 | BZ14: 0 | CA14: 0 | CB14: 0 | CC14: 0 | CD14: 0 | CE14: 0 | CF14: 0 | CG14: 0 | CH14: 0 | CI14: 0 | CJ14: 0 | CK14: 0 | CL14: 0 | CM14: 0 | CN14: 0 | CO14: 0 | CP14: 0 | CQ14: 0 | CR14: 0 | CS14: 0 | CT14: 0 | CU14: 0 | CV14: 0 | CW14: 0 | CX14: 0 | CY14: 0 | CZ14: 0 | DA14: 0 | DB14: 0 | DC14: 0 | DD14: 0 | DE14: 0 | DF14: 0 | DG14: 0 | DH14: 0 | DI14: 0 | DJ14: 0 | DK14: 0 | DL14: 0 | DM14: 0 | DN14: 0 | DO14: 0 | DP14: 0 | DQ14: 0 | DR14: 0 | DS14: 0 | DT14: 0 | DU14: 0 | DV14: 0 | DW14: 0 | DX14: 0 | DY14: 0 | DZ14: 0 | EA14: 0 | EB14: 0 | EC14: 0 | ED14: 0 | EE14: 0 | EF14: 0 | EG14: 0 | EH14: 0 | EI14: 0 | EJ14: 0 | EK14: 0 | EL14: 0 | EM14: 0 | EN14: 0 | EO14: 0 | EP14: 0 | EQ14: 0 | ER14: 0 | ES14: 0 | ET14: 0 | EU14: 0 | EV14: 0 | EW14: 0 | EX14: 0 | EY14: 0 | EZ14: 0 | FA14: 0 | FB14: 0 | FC14: 0 | FD14: 0 | FE14: 0 | FF14: 0 | FG14: 0 | FH14: 0 | FI14: 0 | FJ14: 0 | FK14: 0 | FL14: 0 | FM14: 0 | FN14: 0 | FO14: 0 | FP14: 0 | FQ14: 0 | FR14: 0 | FS14: 0 | FT14: 0 | FU14: 0 | FV14: 0 | FW14: 0 | FX14: 0 | FY14: 0 | FZ14: 0 | GA14: 0 | GB14: 0 | GC14: 0 | GD14: 0 | GE14: 0 | GF14: 0 | GG14: 0 | GH14: 0 | GI14: 0 | GJ14: 0 | GK14: 0 | GL14: 0 | GM14: 0 | GN14: 0 | GO14: 0 | GP14: 0 | GQ14: 0 | GR14: 0 | GS14: 0 | GT14: 0 | GU14: 0 | GV14: 0 | GW14: 0 | GX14: 0 | GY14: 0 | GZ14: 0 | HA14: 0 | HB14: 0 | HC14: 0 | HD14: 0 | HE14: 0 | HF14: 0 | HG14: 0 | HH14: 0 | HI14: 0 | HJ14: 0 | HK14: 0 | HL14: 0 | HM14: 0 | HN14: 0 | HO14: 0 | HP14: 0 | HQ14: 0 | HR14: 0 | HS14: 0 | HT14: 0 | HU14: 0 | HV14: 0 | HW14: 0 | HX14: 0 | HY14: 0 | HZ14: 0 | IA14: 0 | IB14: 0 | IC14: 0 | ID14: 0 | IE14: 0 | IF14: 0 | IG14: 0 | IH14: 0 | II14: 0 | IJ14: 0 | IK14: 0 | IL14: 0 | IM14: 0 | IN14: 0 | IO14: 0 | IP14: 0 | IQ14: 0 | IR14: 0 | IS14: 0 | IT14: 0 | IU14: 0 | IV14: 0 | IW14: 0 | IX14: 0 | IY14: 0 | IZ14: 0 | JA14: 0 | JB14: 0 | JC14: 0 | JD14: 0 | JE14: 0 | JF14: 0 | JG14: 0 | JH14: 0 | JI14: 0 | JJ14: 0 | JK14: 0 | JL14: 0 | JM14: 0 | JN14: 0 | JO14: 0 | JP14: 0 | JQ14: 0 | JR14: 0 | JS14: 0 | JT14: 0 | JU14: 0 | JV14: 0 | JW14: 0 | JX14: 0 | JY14: 0 | JZ14: 0 | KA14: 0 | KB14: 0 | KC14: 0 | KD14: 0 | KE14: 0 | KF14: 0 | KG14: 0 | KH14: 0 | KI14: 0 | KJ14: 0 | KK14: 0 | KL14: 0 | KM14: 0 | KN14: 0 | KO14: 0 | KP14: 0 | KQ14: 0 | KR14: 0 | KS14: 0 | KT14: 0 | KU14: 0 | KV14: 0 | KW14: 0 | KX14: 0 | KY14: 0 | KZ14: 0 | LA14: 0 | LB14: 0 | LC14: 0 | LD14: 0 | LE14: 0 | LF14: 0 | LG14: 0 | LH14: 0 | LI14: 0 | LJ14: 0 | LK14: 0 | LL14: 0 | LM14: 0 | LN14: 0 | LO14: 0 | LP14: 0 | LQ14: 0 | LR14: 0 | LS14: 0 | LT14: 0 | LU14: 0 | LV14: 0 | LW14: 0 | LX14: 0 | LY14: 0 | LZ14: 0 | MA14: 0 | MB14: 0 | MC14: 0 | MD14: 0 | ME14: 0 | MF14: 0 | MG14: 0 | MH14: 0 | MI14: 0 | MJ14: 0 | MK14: 0 | ML14: 0 | MM14: 0 | MN14: 0 | MO14: 0 | MP14: 0 | MQ14: 0 | MR14: 0 | MS14: 0 | MT14: 0 | MU14: 0 | MV14: 0 | MW14: 0 | MX14: 0 | MY14: 0 | MZ14: 0 | NA14: 0 | NB14: 0 | NC14: 0 | ND14: 0 | NE14: 0 | NF14: 0 | NG14: 0 | NH14: 0 | NI14: 0 | NJ14: 0 | NK14: 0 | NL14: 0 | NM14: 0 | NN14: 0 | NO14: 0 | NP14: 0 | NQ14: 0 | NR14: 0 | NS14: 0 | NT14: 0 | NU14: 0 | NV14: 0 | NW14: 0 | NX14: 0 | NY14: 0 | NZ14: 0 | OA14: 0 | OB14: 0 | OC14: 0 | OD14: 0 | OE14: 0 | OF14: 0 | OG14: 0 | OH14: 0 | OI14: 0 | OJ14: 0 | OK14: 0 | OL14: 0 | OM14: 0 | ON14: 0 | OO14: 0 | OP14: 0 | OQ14: 0 | OR14: 0 | OS14: 0 | OT14: 0 | OU14: 0 | OV14: 0 | OW14: 0 | OX14: 0 | OY14: 0 | OZ14: 0 | PA14: 0 | PB14: 0 | PC14: 0 | PD14: 0 | PE14: 0 | PF14: 0 | PG14: 0 | PH14: 0 | PI14: 0 | PJ14: 0 | PK14: 0 | PL14: 0 | PM14: 0 | PN14: 0 | PO14: 0 | PP14: 0 | PQ14: 0 | PR14: 0 | PS14: 0 | PT14: 0 | PU14: 0 | PV14: 0 | PW14: 0 | PX14: 0 | PY14: 0 | PZ14: 0 | QA14: 0 | QB14: 0 | QC14: 0 | QD14: 0 | QE14: 0 | QF14: 0 | QG14: 0 | QH14: 0 | QI14: 0 | QJ14: 0 | QK14: 0 | QL14: 0 | QM14: 0 | QN14: 0 | QO14: 0 | QP14: 0 | QQ14: 0 | QR14: 0 | QS14: 0 | QT14: 0 | QU14: 0 | QV14: 0 | QW14: 0 | QX14: 0 | QY14: 0 | QZ14: 0 | RA14: 0 | RB14: 0 | RC14: 0 | RD14: 0 | RE14: 0 | RF14: 0 | RG14: 0 | RH14: 0 | RI14: 0 | RJ14: 0 | RK14: 0 | RL14: 0 | RM14: 0 | RN14: 0 | RO14: 0 | RP14: 0 | RQ14: 0 | RR14: 0 | RS14: 0 | RT14: 0 | RU14: 0 | RV14: 0 | RW14: 0 | RX14: 0 | RY14: 0 | RZ14: 0 | SA14: 0 | SB14: 0 | SC14: 0 | SD14: 0 | SE14: 0 | SF14: 0 | SG14: 0 | SH14: 0 | SI14: 0 | SJ14: 0 | SK14: 0 | SL14: 0 | SM14: 0 | SN14: 0 | SO14: 0 | SP14: 0 | SQ14: 0 | SR14: 0 | SS14: 0 | ST14: 0 | SU14: 0 | SV14: 0 | SW14: 0 | SX14: 0 | SY14: 0 | SZ14: 0 | TA14: 0 | TB14: 0 | TC14: 0 | TD14: 0 | TE14: 0 | TF14: 0 | TG14: 0 | TH14: 0 | TI14: 0 | TJ14: 0 | TK14: 0 | TL14: 0 | TM14: 0 | TN14: 0 | TO14: 0 | TP14: 0 | TQ14: 0 | TR14: 0 | TS14: 0 | TT14: 0 | TU14: 0 | TV14: 0 | TW14: 0 | TX14: 0 | TY14: 0 | TZ14: 0 | UA14: 0 | UB14: 0 | UC14: 0 | UD14: 0 | UE14: 0 | UF14: 0 | UG14: 0 | UH14: 0 | UI14: 0 | UJ14: 0 | UK14: 0 | UL14: 0 | UM14: 0 | UN14: 0 | UO14: 0 | UP14: 0 | UQ14: 0 | UR14: 0 | US14: 0 | UT14: 0 | UU14: 0 | UV14: 0 | UW14: 0 | UX14: 0 | UY14: 0 | UZ14: 0 | VA14: 0 | VB14: 0 | VC14: 0 | VD14: 0 | VE14: 0 | VF14: 0 | VG14: 0 | VH14: 0 | VI14: 0 | VJ14: 0 | VK14: 0 | VL14: 0 | VM14: 0 | VN14: 0 | VO14: 0 | VP14: 0 | VQ14: 0 | VR14: 0 | VS14: 0 | VT14: 0 | VU14: 0 | VV14: 0 | VW14: 0 | VX14: 0 | VY14: 0 | VZ14: 0 | WA14: 0 | WB14: 0 | WC14: 0 | WD14: 0 | WE14: 0 | WF14: 0 | WG14: 0 | WH14: 0 | WI14: 0 | WJ14: 0 | WK14: 0 | WL14: 0 | WM14: 0 | WN14: 0 | WO14: 0 | WP14: 0 | WQ14: 0 | WR14: 0 | WS14: 0 | WT14: 0 | WU14: 0 | WV14: 0 | WW14: 0 | WX14: 0 | WY14: 0 | WZ14: 0 | XA14: 0 | XB14: 0 | XC14: 0 | XD14: 0 | XE14: 0 | XF14: 0 | XG14: 0 | XH14: 0 | XI14: 0 | XJ14: 0 | XK14: 0 | XL14: 0 | XM14: 0 | XN14: 0 | XO14: 0 | XP14: 0 | XQ14: 0 | XR14: 0 | XS14: 0 | XT14: 0 | XU14: 0 | XV14: 0 | XW14: 0 | XX14: 0 | XY14: 0 | XZ14: 0 | YA14: 0 | YB14: 0 | YC14: 0 | YD14: 0 | YE14: 0 | YF14: 0 | YG14: 0 | YH14: 0 | YI14: 0 | YJ14: 0 | YK14: 0 | YL14: 0 | YM14: 0 | YN14: 0 | YO14: 0 | YP14: 0 | YQ14: 0 | YR14: 0 | YS14: 0 | YT14: 0 | YU14: 0 | YV14: 0 | YW14: 0 | YX14: 0 | YY14: 0 | YZ14: 0 | ZA14: 0 | ZB14: 0 | ZC14: 0 | ZD14: 0 | ZE14: 0 | ZF14: 0 | ZG14: 0 | ZH14: 0 | ZI14: 0 | ZJ14: 0 | ZK14: 0 | ZL14: 0 | ZM14: 0 | ZN14: 0 | ZO14: 0 | ZP14: 0 | ZQ14: 0 | ZR14: 0 | ZS14: 0 | ZT14: 0 | ZU14: 0 | ZV14: 0 | ZW14: 0 | ZX14: 0 | ZY14: 0 | ZZ14: 0 | AAA14: 0 | AAB14: 0 | AAC14: 0 | AAD14: 0 | AAE14: 0 | AAF14: 0 | AAG14: 0 | AAH14: 0 | AAI14: 0 | AAJ14: 0 | AAK14: 0 | AAL14: 0 | AAM14: 0 | AAN14: 0 | AAO14: 0 | AAP14: 0 | AAQ14: =IF(LEFT($C14,5)="Total",0,IF(COUNTIF(ENTRY!$G$3:$BM$3,AAQ$1)=0,"CopyPasteValue",IFERROR(HLOOKUP(AAQ$1,ENTRY!$G$3:$BI$133,SUMIFS(ENTRY!$A$2:$A$133,ENTRY!$B$2:$B$133,$B14,ENTRY!$C$2:$C$133,$C14)-2,FALSE),0))) -> 0 | AAR14: =IF(LEFT($C14,5)="Total",0,IF(COUNTIF(ENTRY!$G$3:$BM$3,AAR$1)=0,"CopyPasteValue",IFERROR(HLOOKUP(AAR$1,ENTRY!$G$3:$BI$133,SUMIFS(ENTRY!$A$2:$A$133,ENTRY!$B$2:$B$133,$B14,ENTRY!$C$2:$C$133,$C14)-2,FALSE),0))) -> 0 | AAS14: =IF(LEFT($C14,5)="Total",0,IF(COUNTIF(ENTRY!$G$3:$BM$3,AAS$1)=0,"CopyPasteValue",IFERROR(HLOOKUP(AAS$1,ENTRY!$G$3:$BI$133,SUMIFS(ENTRY!$A$2:$A$133,ENTRY!$B$2:$B$133,$B14,ENTRY!$C$2:$C$133,$C14)-2,FALSE),0))) -> 0 | AAT14: =IF(LEFT($C14,5)="Total",0,IF(COUNTIF(ENTRY!$G$3:$BM$3,AAT$1)=0,"CopyPasteValue",IFERROR(HLOOKUP(AAT$1,ENTRY!$G$3:$BI$133,SUMIFS(ENTRY!$A$2:$A$133,ENTRY!$B$2:$B$133,$B14,ENTRY!$C$2:$C$133,$C14)-2,FALSE),0))) -> 0 | AAU14: =IF(LEFT($C14,5)="Total",0,IF(COUNTIF(ENTRY!$G$3:$BM$3,AAU$1)=0,"CopyPasteValue",IFERROR(HLOOKUP(AAU$1,ENTRY!$G$3:$BI$133,SUMIFS(ENTRY!$A$2:$A$133,ENTRY!$B$2:$B$133,$B14,ENTRY!$C$2:$C$133,$C14)-2,FALSE),0))) -> 0 | AAV14: =IF(LEFT($C14,5)="Total",0,IF(COUNTIF(ENTRY!$G$3:$BM$3,AAV$1)=0,"CopyPasteValue",IFERROR(HLOOKUP(AAV$1,ENTRY!$G$3:$BI$133,SUMIFS(ENTRY!$A$2:$A$133,ENTRY!$B$2:$B$133,$B14,ENTRY!$C$2:$C$133,$C14)-2,FALSE),0))) -> 0 | AAW14: =IF(LEFT($C14,5)="Total",0,IF(COUNTIF(ENTRY!$G$3:$BM$3,AAW$1)=0,"CopyPasteValue",IFERROR(HLOOKUP(AAW$1,ENTRY!$G$3:$BI$133,SUMIFS(ENTRY!$A$2:$A$133,ENTRY!$B$2:$B$133,$B14,ENTRY!$C$2:$C$133,$C14)-2,FALSE),0))) -> 0 | AAX14: =IF(LEFT($C14,5)="Total",0,IF(COUNTIF(ENTRY!$G$3:$BM$3,AAX$1)=0,"CopyPasteValue",IFERROR(HLOOKUP(AAX$1,ENTRY!$G$3:$BI$133,SUMIFS(ENTRY!$A$2:$A$133,ENTRY!$B$2:$B$133,$B14,ENTRY!$C$2:$C$133,$C14)-2,FALSE),0))) -> 0 | ... ABH14: =IF(LEFT($C14,5)="Total",0,IF(COUNTIF(ENTRY!$G$3:$BM$3,ABH$1)=0,"CopyPasteValue",IFERROR(HLOOKUP(ABH$1,ENTRY!$G$3:$BI$133,SUMIFS(ENTRY!$A$2:$A$133,ENTRY!$B$2:$B$133,$B14,ENTRY!$C$2:$C$133,$C14)-2,FALSE),0))) -> 0
B15: GC-Hand Bags | C15: Handbag A | D15: =CELL("row",D15) -> 15 | E15: =COUNTIF(ENTRY!C$4:C$294,C15) -> 1 | F15: 0 | G15: 1 | H15: 0 | I15: 0 | J15: 0 | K15: 0 | L15: 0 | M15: 0 | N15: 0 | O15: 0 | P15: 1 | Q15: 0 | R15: 0 | S15: 0 | T15: 0 | U15: 0 | V15: 0 | W15: 1 | X15: 0 | Y15: 0 | Z15: 0 | AA15: 0 | AB15: 0 | AC15: 0 | AD15: 1 | AE15: 1 | AF15: 0 | AG15: 0 | AH15: 1 | AI15: 1 | AJ15: 1 | AK15: 2 | AL15: 3 | AM15: 0 | AN15: 0 | AO15: 2 | AP15: 2 | AQ15: 0 | AR15: 0 | AS15: 0 | AT15: 0 | AU15: 0 | AV15: 1 | AW15: 0 | AX15: 0 | AY15: 0 | AZ15: 0 | BA15: 1 | BB15: 0 | BC15: 1 | BD15: 0 | BE15: 0 | BF15: 0 | BG15: 4 | BH15: 0 | BI15: 0 | BJ15: 0 | BK15: 0 | BL15: 0 | BM15: 0 | BN15: 1 | BO15: 0 | BP15: 0 | BQ15: 2 | BR15: 1 | BS15: 0 | BT15: 1 | BU15: 0 | BV15: 0 | BW15: 0 | BX15: 2 | BY15: 2 | BZ15: 0 | CA15: 1 | CB15: 0 | CC15: 0 | CD15: 0 | CE15: 7 | CF15: 1 | CG15: 1 | CH15: 2 | CI15: 1 | CJ15: 1 | CK15: 0 | CL15: 1 | CM15: 1 | CN15: 1 | CO15: 0 | CP15: 0 | CQ15: 0 | CR15: 0 | CS15: 2 | CT15: 2 | CU15: 0 | CV15: 1 | CW15: 0 | CX15: 0 | CY15: 0 | CZ15: 0 | DA15: 0 | DB15: 0 | DC15: 0 | DD15: 0 | DE15: 0 | DF15: 0 | DG15: 0 | DH15: 0 | DI15: 0 | DJ15: 0 | DK15: 0 | DL15: 0 | DM15: 0 | DN15: 0 | DO15: 0 | DP15: 0 | DQ15: 0 | DR15: 0 | DS15: 0 | DT15: 0 | DU15: 0 | DV15: 0 | DW15: 0 | DX15: 0 | DY15: 0 | DZ15: 0 | EA15: 0 | EB15: 0 | EC15: 0 | ED15: 0 | EE15: 0 | EF15: 0 | EG15: 0 | EH15: 0 | EI15: 0 | EJ15: 0 | EK15: 0 | EL15: 0 | EM15: 0 | EN15: 0 | EO15: 0 | EP15: 0 | EQ15: 0 | ER15: 0 | ES15: 0 | ET15: 0 | EU15: 0 | EV15: 0 | EW15: 0 | EX15: 0 | EY15: 0 | EZ15: 0 | FA15: 0 | FB15: 0 | FC15: 0 | FD15: 0 | FE15: 0 | FF15: 0 | FG15: 0 | FH15: 0 | FI15: 0 | FJ15: 0 | FK15: 0 | FL15: 0 | FM15: 0 | FN15: 0 | FO15: 0 | FP15: 0 | FQ15: 0 | FR15: 0 | FS15: 0 | FT15: 0 | FU15: 0 | FV15: 0 | FW15: 0 | FX15: 0 | FY15: 1 | FZ15: 1 | GA15: 0 | GB15: 0 | GC15: 0 | GD15: 0 | GE15: 0 | GF15: 0 | GG15: 4 | GH15: 0 | GI15: 0 | GJ15: 0 | GK15: 0 | GL15: 0 | GM15: 0 | GN15: 0 | GO15: 0 | GP15: 0 | GQ15: 0 | GR15: 0 | GS15: 0 | GT15: 0 | GU15: 0 | GV15: 0 | GW15: 0 | GX15: 2 | GY15: 0 | GZ15: 0 | HA15: 0 | HB15: 0 | HC15: 0 | HD15: 0 | HE15: 0 | HF15: 0 | HG15: 0 | HH15: 0 | HI15: 0 | HJ15: 0 | HK15: 0 | HL15: 0 | HM15: 0 | HN15: 0 | HO15: 0 | HP15: 0 | HQ15: 0 | HR15: 0 | HS15: 0 | HT15: 0 | HU15: 0 | HV15: 1 | HW15: 0 | HX15: 0 | HY15: 0 | HZ15: 0 | IA15: 1 | IB15: 0 | IC15: 0 | ID15: 0 | IE15: 0 | IF15: 0 | IG15: 0 | IH15: 0 | II15: 0 | IJ15: 0 | IK15: 0 | IL15: 0 | IM15: 0 | IN15: 0 | IO15: 0 | IP15: 0 | IQ15: 0 | IR15: 0 | IS15: 0 | IT15: 0 | IU15: 0 | IV15: 0 | IW15: 0 | IX15: 0 | IY15: 0 | IZ15: 0 | JA15: 0 | JB15: 0 | JC15: 0 | JD15: 0 | JE15: 0 | JF15: 0 | JG15: 0 | JH15: 0 | JI15: 0 | JJ15: 0 | JK15: 0 | JL15: 0 | JM15: 0 | JN15: 0 | JO15: 0 | JP15: 0 | JQ15: 0 | JR15: 0 | JS15: 0 | JT15: 0 | JU15: 0 | JV15: 0 | JW15: 0 | JX15: 0 | JY15: 0 | JZ15: 0 | KA15: 0 | KB15: 0 | KC15: 0 | KD15: 0 | KE15: 0 | KF15: 0 | KG15: 0 | KH15: 0 | KI15: 0 | KJ15: 2 | KK15: 0 | KL15: 0 | KM15: 0 | KN15: 1 | KO15: 0 | KP15: 0 | KQ15: 0 | KR15: 0 | KS15: 0 | KT15: 0 | KU15: 0 | KV15: 2 | KW15: 0 | KX15: 0 | KY15: 0 | KZ15: 0 | LA15: 0 | LB15: 0 | LC15: 0 | LD15: 1 | LE15: 0 | LF15: 0 | LG15: 0 | LH15: 0 | LI15: 0 | LJ15: 0 | LK15: 0 | LL15: 0 | LM15: 0 | LN15: 0 | LO15: 0 | LP15: 3 | LQ15: 4 | LR15: 0 | LS15: 1 | LT15: 0 | LU15: 0 | LV15: 0 | LW15: 1 | LX15: 0 | LY15: 0 | LZ15: 1 | MA15: 0 | MB15: 0 | MC15: 0 | MD15: 0 | ME15: 0 | MF15: 0 | MG15: 0 | MH15: 0 | MI15: 0 | MJ15: 0 | MK15: 0 | ML15: 0 | MM15: 0 | MN15: 1 | MO15: 0 | MP15: 0 | MQ15: 0 | MR15: 0 | MS15: 0 | MT15: 0 | MU15: 0 | MV15: 0 | MW15: 0 | MX15: 0 | MY15: 1 | MZ15: 0 | NA15: 0 | NB15: 0 | NC15: 0 | ND15: 0 | NE15: 0 | NF15: 0 | NG15: 0 | NH15: 0 | NI15: 1 | NJ15: 0 | NK15: 0 | NL15: 0 | NM15: 0 | NN15: 0 | NO15: 1 | NP15: 0 | NQ15: 0 | NR15: 1 | NS15: 0 | NT15: 2 | NU15: 0 | NV15: 0 | NW15: 0 | NX15: 0 | NY15: 0 | NZ15: 0 | OA15: 0 | OB15: 0 | OC15: 1 | OD15: 0 | OE15: 0 | OF15: 0 | OG15: 0 | OH15: 0 | OI15: 0 | OJ15: 0 | OK15: 0 | OL15: 0 | OM15: 0 | ON15: 0 | OO15: 1 | OP15: 0 | OQ15: 1 | OR15: 0 | OS15: 0 | OT15: 1 | OU15: 0 | OV15: 0 | OW15: 0 | OX15: 8 | OY15: 0 | OZ15: 0 | PA15: 0 | PB15: 0 | PC15: 0 | PD15: 0 | PE15: 0 | PF15: 0 | PG15: 0 | PH15: 0 | PI15: 0 | PJ15: 0 | PK15: 0 | PL15: 0 | PM15: 0 | PN15: 0 | PO15: 0 | PP15: 0 | PQ15: 1 | PR15: 1 | PS15: 0 | PT15: 0 | PU15: 0 | PV15: 0 | PW15: 0 | PX15: 0 | PY15: 0 | PZ15: 0 | QA15: 1 | QB15: 0 | QC15: 0 | QD15: 0 | QE15: 0 | QF15: 0 | QG15: 6 | QH15: 6 | QI15: 0 | QJ15: 0 | QK15: 0 | QL15: 1 | QM15: 0 | QN15: 0 | QO15: 5 | QP15: 0 | QQ15: 0 | QR15: 0 | QS15: 0 | QT15: 0 | QU15: 0 | QV15: 0 | QW15: 3 | QX15: 0 | QY15: 0 | QZ15: 2 | RA15: 3 | RB15: 1 | RC15: 0 | RD15: 0 | RE15: 0 | RF15: 0 | RG15: 0 | RH15: 0 | RI15: 0 | RJ15: 0 | RK15: 0 | RL15: 0 | RM15: 0 | RN15: 0 | RO15: 0 | RP15: 1 | RQ15: 0 | RR15: 0 | RS15: 1 | RT15: 0 | RU15: 0 | RV15: 2 | RW15: 0 | RX15: 0 | RY15: 2 | RZ15: 2 | SA15: 0 | SB15: 2 | SC15: 0 | SD15: 3 | SE15: 5 | SF15: 0 | SG15: 17 | SH15: 0 | SI15: 4 | SJ15: 2 | SK15: 0 | SL15: 0 | SM15: 0 | SN15: 0 | SO15: 0 | SP15: 3 | SQ15: 0 | SR15: 1 | SS15: 0 | ST15: 0 | SU15: 0 | SV15: 0 | SW15: 3 | SX15: 0 | SY15: 0 | SZ15: 0 | TA15: 3 | TB15: 2 | TC15: 0 | TD15: 1 | TE15: 0 | TF15: 0 | TG15: 0 | TH15: 0 | TI15: 0 | TJ15: 0 | TK15: 0 | TL15: 1 | TM15: 0 | TN15: 1 | TO15: 0 | TP15: 0 | TQ15: 0 | TR15: 1 | TS15: 1 | TT15: 0 | TU15: 1 | TV15: 0 | TW15: 1 | TX15: 0 | TY15: 0 | TZ15: 0 | UA15: 0 | UB15: 0 | UC15: 0 | UD15: 0 | UE15: 0 | UF15: 0 | UG15: 0 | UH15: 0 | UI15: 0 | UJ15: 0 | UK15: 0 | UL15: 0 | UM15: 0 | UN15: 0 | UO15: 0 | UP15: 0 | UQ15: 0 | UR15: 0 | US15: 0 | UT15: 0 | UU15: 0 | UV15: 0 | UW15: 1 | UX15: 0 | UY15: 1 | UZ15: 1 | VA15: 0 | VB15: 0 | VC15: 1 | VD15: 0 | VE15: 3 | VF15: 0 | VG15: 0 | VH15: 0 | VI15: 0 | VJ15: 0 | VK15: 0 | VL15: 0 | VM15: 4 | VN15: 0 | VO15: 0 | VP15: 0 | VQ15: 0 | VR15: 0 | VS15: 0 | VT15: 0 | VU15: 4 | VV15: 0 | VW15: 0 | VX15: 0 | VY15: 0 | VZ15: 0 | WA15: 1 | WB15: 0 | WC15: 1 | WD15: 0 | WE15: 0 | WF15: 0 | WG15: 0 | WH15: 0 | WI15: 0 | WJ15: 0 | WK15: 0 | WL15: 0 | WM15: 0 | WN15: 0 | WO15: 0 | WP15: 0 | WQ15: 0 | WR15: 0 | WS15: 0 | WT15: 0 | WU15: 0 | WV15: 0 | WW15: 0 | WX15: 0 | WY15: 0 | WZ15: 0 | XA15: 0 | XB15: 0 | XC15: 1 | XD15: 0 | XE15: 3 | XF15: 0 | XG15: 0 | XH15: 0 | XI15: 0 | XJ15: 0 | XK15: 0 | XL15: 0 | XM15: 0 | XN15: 0 | XO15: 1 | XP15: 0 | XQ15: 0 | XR15: 0 | XS15: 0 | XT15: 0 | XU15: 0 | XV15: 0 | XW15: 1 | XX15: 0 | XY15: 0 | XZ15: 0 | YA15: 0 | YB15: 0 | YC15: 0 | YD15: 0 | YE15: 1 | YF15: 0 | YG15: 0 | YH15: 0 | YI15: 0 | YJ15: 0 | YK15: 1 | YL15: 0 | YM15: 0 | YN15: 4 | YO15: 0 | YP15: 0 | YQ15: 0 | YR15: 0 | YS15: 1 | YT15: 0 | YU15: 0 | YV15: 0 | YW15: 1 | YX15: 1 | YY15: 10 | YZ15: 0 | ZA15: 0 | ZB15: 1 | ZC15: 0 | ZD15: 0 | ZE15: 1 | ZF15: 0 | ZG15: 0 | ZH15: 0 | ZI15: 0 | ZJ15: 0 | ZK15: 0 | ZL15: 0 | ZM15: 1 | ZN15: 0 | ZO15: 0 | ZP15: 0 | ZQ15: 0 | ZR15: 0 | ZS15: 0 | ZT15: 0 | ZU15: 0 | ZV15: 0 | ZW15: 0 | ZX15: 0 | ZY15: 0 | ZZ15: 0 | AAA15: 1 | AAB15: 0 | AAC15: 0 | AAD15: 0 | AAE15: 0 | AAF15: 0 | AAG15: 0 | AAH15: 0 | AAI15: 0 | AAJ15: 0 | AAK15: 0 | AAL15: 0 | AAM15: 0 | AAN15: 0 | AAO15: 0 | AAP15: 0 | AAQ15: =IF(LEFT($C15,5)="Total",0,IF(COUNTIF(ENTRY!$G$3:$BM$3,AAQ$1)=0,"CopyPasteValue",IFERROR(HLOOKUP(AAQ$1,ENTRY!$G$3:$BI$133,SUMIFS(ENTRY!$A$2:$A$133,ENTRY!$B$2:$B$133,$B15,ENTRY!$C$2:$C$133,$C15)-2,FALSE),0))) -> 0 | AAR15: =IF(LEFT($C15,5)="Total",0,IF(COUNTIF(ENTRY!$G$3:$BM$3,AAR$1)=0,"CopyPasteValue",IFERROR(HLOOKUP(AAR$1,ENTRY!$G$3:$BI$133,SUMIFS(ENTRY!$A$2:$A$133,ENTRY!$B$2:$B$133,$B15,ENTRY!$C$2:$C$133,$C15)-2,FALSE),0))) -> 0 | AAS15: =IF(LEFT($C15,5)="Total",0,IF(COUNTIF(ENTRY!$G$3:$BM$3,AAS$1)=0,"CopyPasteValue",IFERROR(HLOOKUP(AAS$1,ENTRY!$G$3:$BI$133,SUMIFS(ENTRY!$A$2:$A$133,ENTRY!$B$2:$B$133,$B15,ENTRY!$C$2:$C$133,$C15)-2,FALSE),0))) -> 0 | AAT15: =IF(LEFT($C15,5)="Total",0,IF(COUNTIF(ENTRY!$G$3:$BM$3,AAT$1)=0,"CopyPasteValue",IFERROR(HLOOKUP(AAT$1,ENTRY!$G$3:$BI$133,SUMIFS(ENTRY!$A$2:$A$133,ENTRY!$B$2:$B$133,$B15,ENTRY!$C$2:$C$133,$C15)-2,FALSE),0))) -> 0 | AAU15: =IF(LEFT($C15,5)="Total",0,IF(COUNTIF(ENTRY!$G$3:$BM$3,AAU$1)=0,"CopyPasteValue",IFERROR(HLOOKUP(AAU$1,ENTRY!$G$3:$BI$133,SUMIFS(ENTRY!$A$2:$A$133,ENTRY!$B$2:$B$133,$B15,ENTRY!$C$2:$C$133,$C15)-2,FALSE),0))) -> 0 | AAV15: =IF(LEFT($C15,5)="Total",0,IF(COUNTIF(ENTRY!$G$3:$BM$3,AAV$1)=0,"CopyPasteValue",IFERROR(HLOOKUP(AAV$1,ENTRY!$G$3:$BI$133,SUMIFS(ENTRY!$A$2:$A$133,ENTRY!$B$2:$B$133,$B15,ENTRY!$C$2:$C$133,$C15)-2,FALSE),0))) -> 0 | AAW15: =IF(LEFT($C15,5)="Total",0,IF(COUNTIF(ENTRY!$G$3:$BM$3,AAW$1)=0,"CopyPasteValue",IFERROR(HLOOKUP(AAW$1,ENTRY!$G$3:$BI$133,SUMIFS(ENTRY!$A$2:$A$133,ENTRY!$B$2:$B$133,$B15,ENTRY!$C$2:$C$133,$C15)-2,FALSE),0))) -> 0 | AAX15: =IF(LEFT($C15,5)="Total",0,IF(COUNTIF(ENTRY!$G$3:$BM$3,AAX$1)=0,"CopyPasteValue",IFERROR(HLOOKUP(AAX$1,ENTRY!$G$3:$BI$133,SUMIFS(ENTRY!$A$2:$A$133,ENTRY!$B$2:$B$133,$B15,ENTRY!$C$2:$C$133,$C15)-2,FALSE),0))) -> 0 | ... ABH15: =IF(LEFT($C15,5)="Total",0,IF(COUNTIF(ENTRY!$G$3:$BM$3,ABH$1)=0,"CopyPasteValue",IFERROR(HLOOKUP(ABH$1,ENTRY!$G$3:$BI$133,SUMIFS(ENTRY!$A$2:$A$133,ENTRY!$B$2:$B$133,$B15,ENTRY!$C$2:$C$133,$C15)-2,FALSE),0))) -> 0
B16: GC-Hand Bags | C16: Laptop Bags#1 | D16: =CELL("row",D16) -> 16 | E16: =COUNTIF(ENTRY!C$4:C$294,C16) -> 1 | F16: 0 | G16: 0 | H16: 0 | I16: 0 | J16: 3 | K16: 0 | L16: 0 | M16: 1 | N16: 0 | O16: 0 | P16: 0 | Q16: 0 | R16: 0 | S16: 0 | T16: 4 | U16: 0 | V16: 0 | W16: 0 | X16: 1 | Y16: 0 | Z16: 0 | AA16: 0 | AB16: 0 | AC16: 0 | AD16: 0 | AE16: 0 | AF16: 2 | AG16: 0 | AH16: 0 | AI16: 0 | AJ16: 1 | AK16: 0 | AL16: 0 | AM16: 0 | AN16: 0 | AO16: 0 | AP16: 0 | AQ16: 0 | AR16: 0 | AS16: 2 | AT16: 0 | AU16: 0 | AV16: 1 | AW16: 0 | AX16: 0 | AY16: 0 | AZ16: 0 | BA16: 1 | BB16: 0 | BC16: 2 | BD16: 0 | BE16: 0 | BF16: 0 | BG16: 2 | BH16: 0 | BI16: 0 | BJ16: 0 | BK16: 0 | BL16: 0 | BM16: 1 | BN16: 2 | BO16: 0 | BP16: 0 | BQ16: 0 | BR16: 0 | BS16: 0 | BT16: 0 | BU16: 0 | BV16: 0 | BW16: 0 | BX16: 0 | BY16: 0 | BZ16: 0 | CA16: 0 | CB16: 0 | CC16: 0 | CD16: 0 | CE16: 0 | CF16: 0 | CG16: 0 | CH16: 0 | CI16: 0 | CJ16: 0 | CK16: 0 | CL16: 0 | CM16: 0 | CN16: 0 | CO16: 0 | CP16: 0 | CQ16: 0 | CR16: 0 | CS16: 0 | CT16: 0 | CU16: 0 | CV16: 0 | CW16: 0 | CX16: 0 | CY16: 0 | CZ16: 0 | DA16: 0 | DB16: 0 | DC16: 0 | DD16: 0 | DE16: 0 | DF16: 0 | DG16: 0 | DH16: 0 | DI16: 0 | DJ16: 0 | DK16: 0 | DL16: 0 | DM16: 0 | DN16: 0 | DO16: 0 | DP16: 0 | DQ16: 0 | DR16: 0 | DS16: 0 | DT16: 0 | DU16: 0 | DV16: 0 | DW16: 0 | DX16: 0 | DY16: 0 | DZ16: 0 | EA16: 0 | EB16: 0 | EC16: 0 | ED16: 0 | EE16: 0 | EF16: 0 | EG16: 0 | EH16: 0 | EI16: 0 | EJ16: 0 | EK16: 0 | EL16: 0 | EM16: 0 | EN16: 0 | EO16: 0 | EP16: 0 | EQ16: 0 | ER16: 0 | ES16: 0 | ET16: 0 | EU16: 0 | EV16: 0 | EW16: 0 | EX16: 0 | EY16: 0 | EZ16: 0 | FA16: 0 | FB16: 0 | FC16: 0 | FD16: 0 | FE16: 0 | FF16: 0 | FG16: 0 | FH16: 0 | FI16: 0 | FJ16: 0 | FK16: 0 | FL16: 0 | FM16: 0 | FN16: 0 | FO16: 0 | FP16: 0 | FQ16: 0 | FR16: 0 | FS16: 0 | FT16: 0 | FU16: 0 | FV16: 0 | FW16: 0 | FX16: 0 | FY16: 2 | FZ16: 1 | GA16: 0 | GB16: 0 | GC16: 0 | GD16: 0 | GE16: 0 | GF16: 4 | GG16: 0 | GH16: 0 | GI16: 0 | GJ16: 0 | GK16: 0 | GL16: 0 | GM16: 0 | GN16: 0 | GO16: 0 | GP16: 0 | GQ16: 0 | GR16: 0 | GS16: 0 | GT16: 0 | GU16: 0 | GV16: 0 | GW16: 0 | GX16: 0 | GY16: 0 | GZ16: 0 | HA16: 0 | HB16: 2 | HC16: 0 | HD16: 0 | HE16: 0 | HF16: 0 | HG16: 0 | HH16: 0 | HI16: 0 | HJ16: 0 | HK16: 0 | HL16: 0 | HM16: 4 | HN16: 0 | HO16: 2 | HP16: 0 | HQ16: 0 | HR16: 0 | HS16: 0 | HT16: 0 | HU16: 0 | HV16: 0 | HW16: 0 | HX16: 0 | HY16: 0 | HZ16: 0 | IA16: 0 | IB16: 0 | IC16: 0 | ID16: 0 | IE16: 0 | IF16: 0 | IG16: 0 | IH16: 0 | II16: 0 | IJ16: 0 | IK16: 0 | IL16: 0 | IM16: 0 | IN16: 0 | IO16: 0 | IP16: 0 | IQ16: 0 | IR16: 0 | IS16: 0 | IT16: 0 | IU16: 0 | IV16: 0 | IW16: 0 | IX16: 0 | IY16: 0 | IZ16: 0 | JA16: 0 | JB16: 0 | JC16: 0 | JD16: 0 | JE16: 0 | JF16: 0 | JG16: 0 | JH16: 0 | JI16: 0 | JJ16: 0 | JK16: 0 | JL16: 0 | JM16: 0 | JN16: 0 | JO16: 0 | JP16: 0 | JQ16: 0 | JR16: 0 | JS16: 0 | JT16: 0 | JU16: 0 | JV16: 0 | JW16: 0 | JX16: 0 | JY16: 0 | JZ16: 0 | KA16: 0 | KB16: 0 | KC16: 0 | KD16: 0 | KE16: 0 | KF16: 0 | KG16: 0 | KH16: 0 | KI16: 0 | KJ16: 1 | KK16: 0 | KL16: 0 | KM16: 0 | KN16: 0 | KO16: 0 | KP16: 0 | KQ16: 0 | KR16: 0 | KS16: 0 | KT16: 0 | KU16: 0 | KV16: 0 | KW16: 0 | KX16: 0 | KY16: 0 | KZ16: 0 | LA16: 0 | LB16: 0 | LC16: 0 | LD16: 2 | LE16: 0 | LF16: 0 | LG16: 0 | LH16: 0 | LI16: 1 | LJ16: 0 | LK16: 0 | LL16: 0 | LM16: 0 | LN16: 0 | LO16: 0 | LP16: 0 | LQ16: 0 | LR16: 0 | LS16: 0 | LT16: 0 | LU16: 0 | LV16: 0 | LW16: 0 | LX16: 0 | LY16: 0 | LZ16: 0 | MA16: 0 | MB16: 0 | MC16: 0 | MD16: 0 | ME16: 0 | MF16: 0 | MG16: 0 | MH16: 0 | MI16: 0 | MJ16: 0 | MK16: 0 | ML16: 0 | MM16: 0 | MN16: 2 | MO16: 0 | MP16: 0 | MQ16: 0 | MR16: 0 | MS16: 0 | MT16: 0 | MU16: 0 | MV16: 0 | MW16: 0 | MX16: 0 | MY16: 2 | MZ16: 0 | NA16: 0 | NB16: 0 | NC16: 2 | ND16: 0 | NE16: 0 | NF16: 0 | NG16: 0 | NH16: 0 | NI16: 0 | NJ16: 0 | NK16: 0 | NL16: 0 | NM16: 2 | NN16: 0 | NO16: 0 | NP16: 0 | NQ16: 0 | NR16: 0 | NS16: 0 | NT16: 2 | NU16: 0 | NV16: 0 | NW16: 0 | NX16: 0 | NY16: 0 | NZ16: 0 | OA16: 1 | OB16: 0 | OC16: 0 | OD16: 0 | OE16: 0 | OF16: 0 | OG16: 0 | OH16: 0 | OI16: 0 | OJ16: 0 | OK16: 0 | OL16: 1 | OM16: 0 | ON16: 0 | OO16: 0 | OP16: 0 | OQ16: 0 | OR16: 0 | OS16: 0 | OT16: 0 | OU16: 0 | OV16: 1 | OW16: 0 | OX16: 0 | OY16: 0 | OZ16: 0 | PA16: 0 | PB16: 0 | PC16: 0 | PD16: 0 | PE16: 0 | PF16: 0 | PG16: 0 | PH16: 0 | PI16: 0 | PJ16: 0 | PK16: 0 | PL16: 0 | PM16: 0 | PN16: 0 | PO16: 0 | PP16: 0 | PQ16: 0 | PR16: 0 | PS16: 0 | PT16: 0 | PU16: 0 | PV16: 0 | PW16: 0 | PX16: 0 | PY16: 0 | PZ16: 0 | QA16: 1 | QB16: 0 | QC16: 0 | QD16: 0 | QE16: 3 | QF16: 0 | QG16: 0 | QH16: 0 | QI16: 0 | QJ16: 0 | QK16: 0 | QL16: 0 | QM16: 0 | QN16: 0 | QO16: 0 | QP16: 0 | QQ16: 0 | QR16: 0 | QS16: 0 | QT16: 0 | QU16: 0 | QV16: 0 | QW16: 3 | QX16: 0 | QY16: 0 | QZ16: 0 | RA16: 0 | RB16: 0 | RC16: 0 | RD16: 0 | RE16: 0 | RF16: 0 | RG16: 0 | RH16: 0 | RI16: 0 | RJ16: 0 | RK16: 0 | RL16: 0 | RM16: 0 | RN16: 0 | RO16: 0 | RP16: 0 | RQ16: 1 | RR16: 0 | RS16: 0 | RT16: 0 | RU16: 1 | RV16: 0 | RW16: 0 | RX16: 0 | RY16: 0 | RZ16: 0 | SA16: 0 | SB16: 0 | SC16: 0 | SD16: 0 | SE16: 0 | SF16: 0 | SG16: 1 | SH16: 0 | SI16: 5 | SJ16: 0 | SK16: 0 | SL16: 0 | SM16: 0 | SN16: 0 | SO16: 0 | SP16: 0 | SQ16: 0 | SR16: 0 | SS16: 0 | ST16: 0 | SU16: 0 | SV16: 0 | SW16: 1 | SX16: 0 | SY16: 0 | SZ16: 0 | TA16: 0 | TB16: 0 | TC16: 0 | TD16: 0 | TE16: 0 | TF16: 0 | TG16: 0 | TH16: 0 | TI16: 0 | TJ16: 0 | TK16: 0 | TL16: 0 | TM16: 0 | TN16: 0 | TO16: 0 | TP16: 0 | TQ16: 0 | TR16: 0 | TS16: 0 | TT16: 0 | TU16: 0 | TV16: 0 | TW16: 0 | TX16: 0 | TY16: 0 | TZ16: 0 | UA16: 0 | UB16: 0 | UC16: 0 | UD16: 0 | UE16: 0 | UF16: 0 | UG16: 0 | UH16: 0 | UI16: 0 | UJ16: 0 | UK16: 0 | UL16: 0 | UM16: 0 | UN16: 0 | UO16: 0 | UP16: 0 | UQ16: 0 | UR16: 0 | US16: 0 | UT16: 0 | UU16: 0 | UV16: 1 | UW16: 0 | UX16: 0 | UY16: 0 | UZ16: 0 | VA16: 4 | VB16: 0 | VC16: 0 | VD16: 0 | VE16: 0 | VF16: 0 | VG16: 0 | VH16: 0 | VI16: 0 | VJ16: 0 | VK16: 0 | VL16: 0 | VM16: 4 | VN16: 0 | VO16: 0 | VP16: 0 | VQ16: 0 | VR16: 0 | VS16: 0 | VT16: 0 | VU16: 4 | VV16: 0 | VW16: 0 | VX16: 0 | VY16: 0 | VZ16: 0 | WA16: 0 | WB16: 0 | WC16: 0 | WD16: 0 | WE16: 0 | WF16: 0 | WG16: 0 | WH16: 0 | WI16: 0 | WJ16: 0 | WK16: 0 | WL16: 0 | WM16: 0 | WN16: 0 | WO16: 0 | WP16: 0 | WQ16: 0 | WR16: 0 | WS16: 0 | WT16: 0 | WU16: 1 | WV16: 0 | WW16: 0 | WX16: 0 | WY16: 0 | WZ16: 0 | XA16: 0 | XB16: 0 | XC16: 0 | XD16: 0 | XE16: 0 | XF16: 0 | XG16: 0 | XH16: 0 | XI16: 0 | XJ16: 0 | XK16: 1 | XL16: 0 | XM16: 0 | XN16: 0 | XO16: 1 | XP16: 0 | XQ16: 0 | XR16: 0 | XS16: 0 | XT16: 0 | XU16: 0 | XV16: 0 | XW16: 0 | XX16: 0 | XY16: 0 | XZ16: 0 | YA16: 0 | YB16: 0 | YC16: 0 | YD16: 0 | YE16: 0 | YF16: 0 | YG16: 0 | YH16: 0 | YI16: 0 | YJ16: 0 | YK16: 0 | YL16: 0 | YM16: 0 | YN16: 0 | YO16: 0 | YP16: 0 | YQ16: 0 | YR16: 0 | YS16: 0 | YT16: 0 | YU16: 0 | YV16: 0 | YW16: 0 | YX16: 0 | YY16: 0 | YZ16: 0 | ZA16: 0 | ZB16: 0 | ZC16: 0 | ZD16: 0 | ZE16: 0 | ZF16: 0 | ZG16: 0 | ZH16: 0 | ZI16: 0 | ZJ16: 0 | ZK16: 0 | ZL16: 0 | ZM16: 0 | ZN16: 0 | ZO16: 0 | ZP16: 0 | ZQ16: 0 | ZR16: 0 | ZS16: 0 | ZT16: 0 | ZU16: 0 | ZV16: 0 | ZW16: 0 | ZX16: 0 | ZY16: 0 | ZZ16: 0 | AAA16: 0 | AAB16: 0 | AAC16: 0 | AAD16: 0 | AAE16: 0 | AAF16: 0 | AAG16: 0 | AAH16: 0 | AAI16: 0 | AAJ16: 0 | AAK16: 0 | AAL16: 0 | AAM16: 0 | AAN16: 0 | AAO16: 0 | AAP16: 0 | AAQ16: =IF(LEFT($C16,5)="Total",0,IF(COUNTIF(ENTRY!$G$3:$BM$3,AAQ$1)=0,"CopyPasteValue",IFERROR(HLOOKUP(AAQ$1,ENTRY!$G$3:$BI$133,SUMIFS(ENTRY!$A$2:$A$133,ENTRY!$B$2:$B$133,$B16,ENTRY!$C$2:$C$133,$C16)-2,FALSE),0))) -> 0 | AAR16: =IF(LEFT($C16,5)="Total",0,IF(COUNTIF(ENTRY!$G$3:$BM$3,AAR$1)=0,"CopyPasteValue",IFERROR(HLOOKUP(AAR$1,ENTRY!$G$3:$BI$133,SUMIFS(ENTRY!$A$2:$A$133,ENTRY!$B$2:$B$133,$B16,ENTRY!$C$2:$C$133,$C16)-2,FALSE),0))) -> 0 | AAS16: =IF(LEFT($C16,5)="Total",0,IF(COUNTIF(ENTRY!$G$3:$BM$3,AAS$1)=0,"CopyPasteValue",IFERROR(HLOOKUP(AAS$1,ENTRY!$G$3:$BI$133,SUMIFS(ENTRY!$A$2:$A$133,ENTRY!$B$2:$B$133,$B16,ENTRY!$C$2:$C$133,$C16)-2,FALSE),0))) -> 0 | AAT16: =IF(LEFT($C16,5)="Total",0,IF(COUNTIF(ENTRY!$G$3:$BM$3,AAT$1)=0,"CopyPasteValue",IFERROR(HLOOKUP(AAT$1,ENTRY!$G$3:$BI$133,SUMIFS(ENTRY!$A$2:$A$133,ENTRY!$B$2:$B$133,$B16,ENTRY!$C$2:$C$133,$C16)-2,FALSE),0))) -> 0 | AAU16: =IF(LEFT($C16,5)="Total",0,IF(COUNTIF(ENTRY!$G$3:$BM$3,AAU$1)=0,"CopyPasteValue",IFERROR(HLOOKUP(AAU$1,ENTRY!$G$3:$BI$133,SUMIFS(ENTRY!$A$2:$A$133,ENTRY!$B$2:$B$133,$B16,ENTRY!$C$2:$C$133,$C16)-2,FALSE),0))) -> 0 | AAV16: =IF(LEFT($C16,5)="Total",0,IF(COUNTIF(ENTRY!$G$3:$BM$3,AAV$1)=0,"CopyPasteValue",IFERROR(HLOOKUP(AAV$1,ENTRY!$G$3:$BI$133,SUMIFS(ENTRY!$A$2:$A$133,ENTRY!$B$2:$B$133,$B16,ENTRY!$C$2:$C$133,$C16)-2,FALSE),0))) -> 0 | AAW16: =IF(LEFT($C16,5)="Total",0,IF(COUNTIF(ENTRY!$G$3:$BM$3,AAW$1)=0,"CopyPasteValue",IFERROR(HLOOKUP(AAW$1,ENTRY!$G$3:$BI$133,SUMIFS(ENTRY!$A$2:$A$133,ENTRY!$B$2:$B$133,$B16,ENTRY!$C$2:$C$133,$C16)-2,FALSE),0))) -> 0 | AAX16: =IF(LEFT($C16,5)="Total",0,IF(COUNTIF(ENTRY!$G$3:$BM$3,AAX$1)=0,"CopyPasteValue",IFERROR(HLOOKUP(AAX$1,ENTRY!$G$3:$BI$133,SUMIFS(ENTRY!$A$2:$A$133,ENTRY!$B$2:$B$133,$B16,ENTRY!$C$2:$C$133,$C16)-2,FALSE),0))) -> 0 | ... ABH16: =IF(LEFT($C16,5)="Total",0,IF(COUNTIF(ENTRY!$G$3:$BM$3,ABH$1)=0,"CopyPasteValue",IFERROR(HLOOKUP(ABH$1,ENTRY!$G$3:$BI$133,SUMIFS(ENTRY!$A$2:$A$133,ENTRY!$B$2:$B$133,$B16,ENTRY!$C$2:$C$133,$C16)-2,FALSE),0))) -> 0
B17: GC-Hand Bags | C17: HB2-New Grade | D17: =CELL("row",D17) -> 17 | E17: =COUNTIF(ENTRY!C$4:C$294,C17) -> 0 | F17: 0 | G17: 0 | H17: 0 | I17: 0 | J17: 0 | K17: 0 | L17: 0 | M17: 0 | N17: 0 | O17: 0 | P17: 0 | Q17: 0 | R17: 0 | S17: 0 | T17: 0 | U17: 0 | V17: 0 | W17: 0 | X17: 0 | Y17: 0 | Z17: 0 | AA17: 0 | AB17: 0 | AC17: 0 | AD17: 0 | AE17: 0 | AF17: 0 | AG17: 0 | AH17: 0 | AI17: 0 | AJ17: 0 | AK17: 0 | AL17: 0 | AM17: 0 | AN17: 0 | AO17: 0 | AP17: 0 | AQ17: 0 | AR17: 0 | AS17: 0 | AT17: 0 | AU17: 0 | AV17: 0 | AW17: 0 | AX17: 0 | AY17: 0 | AZ17: 0 | BA17: 0 | BB17: 0 | BC17: 0 | BD17: 0 | BE17: 0 | BF17: 0 | BG17: 0 | BH17: 0 | BI17: 0 | BJ17: 0 | BK17: 0 | BL17: 0 | BM17: 0 | BN17: 0 | BO17: 0 | BP17: 0 | BQ17: 0 | BR17: 0 | BS17: 0 | BT17: 0 | BU17: 0 | BV17: 0 | BW17: 0 | BX17: 0 | BY17: 0 | BZ17: 0 | CA17: 0 | CB17: 0 | CC17: 0 | CD17: 0 | CE17: 0 | CF17: 0 | CG17: 0 | CH17: 0 | CI17: 0 | CJ17: 0 | CK17: 0 | CL17: 0 | CM17: 0 | CN17: 0 | CO17: 0 | CP17: 0 | CQ17: 0 | CR17: 0 | CS17: 0 | CT17: 0 | CU17: 0 | CV17: 0 | CW17: 0 | CX17: 0 | CY17: 0 | CZ17: 0 | DA17: 0 | DB17: 0 | DC17: 0 | DD17: 0 | DE17: 0 | DF17: 0 | DG17: 0 | DH17: 0 | DI17: 0 | DJ17: 0 | DK17: 0 | DL17: 0 | DM17: 0 | DN17: 0 | DO17: 0 | DP17: 0 | DQ17: 0 | DR17: 0 | DS17: 0 | DT17: 0 | DU17: 0 | DV17: 0 | DW17: 0 | DX17: 0 | DY17: 0 | DZ17: 0 | EA17: 0 | EB17: 0 | EC17: 0 | ED17: 0 | EE17: 0 | EF17: 0 | EG17: 0 | EH17: 0 | EI17: 0 | EJ17: 0 | EK17: 0 | EL17: 0 | EM17: 0 | EN17: 0 | EO17: 0 | EP17: 0 | EQ17: 0 | ER17: 0 | ES17: 0 | ET17: 0 | EU17: 0 | EV17: 0 | EW17: 0 | EX17: 0 | EY17: 0 | EZ17: 0 | FA17: 0 | FB17: 0 | FC17: 0 | FD17: 0 | FE17: 0 | FF17: 0 | FG17: 0 | FH17: 0 | FI17: 0 | FJ17: 0 | FK17: 0 | FL17: 0 | FM17: 0 | FN17: 0 | FO17: 0 | FP17: 0 | FQ17: 0 | FR17: 0 | FS17: 0 | FT17: 0 | FU17: 0 | FV17: 0 | FW17: 0 | FX17: 0 | FY17: 0 | FZ17: 0 | GA17: 0 | GB17: 0 | GC17: 0 | GD17: 0 | GE17: 0 | GF17: 0 | GG17: 0 | GH17: 0 | GI17: 0 | GJ17: 0 | GK17: 0 | GL17: 0 | GM17: 0 | GN17: 0 | GO17: 0 | GP17: 0 | GQ17: 0 | GR17: 0 | GS17: 0 | GT17: 0 | GU17: 0 | GV17: 0 | GW17: 0 | GX17: 0 | GY17: 0 | GZ17: 0 | HA17: 0 | HB17: 0 | HC17: 0 | HD17: 0 | HE17: 0 | HF17: 0 | HG17: 0 | HH17: 0 | HI17: 0 | HJ17: 0 | HK17: 0 | HL17: 0 | HM17: 0 | HN17: 0 | HO17: 0 | HP17: 0 | HQ17: 0 | HR17: 0 | HS17: 0 | HT17: 0 | HU17: 0 | HV17: 0 | HW17: 0 | HX17: 0 | HY17: 0 | HZ17: 0 | IA17: 0 | IB17: 0 | IC17: 0 | ID17: 0 | IE17: 0 | IF17: 0 | IG17: 0 | IH17: 0 | II17: 0 | IJ17: 0 | IK17: 0 | IL17: 0 | IM17: 0 | IN17: 0 | IO17: 0 | IP17: 0 | IQ17: 0 | IR17: 0 | IS17: 0 | IT17: 0 | IU17: 0 | IV17: 0 | IW17: 0 | IX17: 0 | IY17: 0 | IZ17: 0 | JA17: 0 | JB17: 0 | JC17: 0 | JD17: 0 | JE17: 0 | JF17: 0 | JG17: 0 | JH17: 0 | JI17: 0 | JJ17: 0 | JK17: 0 | JL17: 0 | JM17: 0 | JN17: 0 | JO17: 0 | JP17: 0 | JQ17: 0 | JR17: 0 | JS17: 0 | JT17: 0 | JU17: 0 | JV17: 0 | JW17: 0 | JX17: 0 | JY17: 0 | JZ17: 0 | KA17: 0 | KB17: 0 | KC17: 0 | KD17: 0 | KE17: 0 | KF17: 0 | KG17: 0 | KH17: 0 | KI17: 0 | KJ17: 0 | KK17: 0 | KL17: 0 | KM17: 0 | KN17: 0 | KO17: 0 | KP17: 0 | KQ17: 0 | KR17: 0 | KS17: 0 | KT17: 0 | KU17: 0 | KV17: 0 | KW17: 0 | KX17: 0 | KY17: 0 | KZ17: 0 | LA17: 0 | LB17: 0 | LC17: 0 | LD17: 0 | LE17: 0 | LF17: 0 | LG17: 0 | LH17: 0 | LI17: 0 | LJ17: 0 | LK17: 0 | LL17: 0 | LM17: 0 | LN17: 0 | LO17: 0 | LP17: 0 | LQ17: 0 | LR17: 0 | LS17: 0 | LT17: 0 | LU17: 0 | LV17: 0 | LW17: 0 | LX17: 0 | LY17: 0 | LZ17: 0 | MA17: 0 | MB17: 0 | MC17: 0 | MD17: 0 | ME17: 0 | MF17: 0 | MG17: 0 | MH17: 0 | MI17: 0 | MJ17: 0 | MK17: 0 | ML17: 0 | MM17: 0 | MN17: 0 | MO17: 0 | MP17: 0 | MQ17: 0 | MR17: 0 | MS17: 0 | MT17: 0 | MU17: 0 | MV17: 0 | MW17: 0 | MX17: 0 | MY17: 0 | MZ17: 0 | NA17: 0 | NB17: 0 | NC17: 0 | ND17: 0 | NE17: 0 | NF17: 0 | NG17: 0 | NH17: 0 | NI17: 0 | NJ17: 0 | NK17: 0 | NL17: 0 | NM17: 0 | NN17: 0 | NO17: 0 | NP17: 0 | NQ17: 0 | NR17: 0 | NS17: 0 | NT17: 0 | NU17: 0 | NV17: 0 | NW17: 0 | NX17: 0 | NY17: 0 | NZ17: 0 | OA17: 0 | OB17: 0 | OC17: 0 | OD17: 0 | OE17: 0 | OF17: 0 | OG17: 0 | OH17: 0 | OI17: 0 | OJ17: 0 | OK17: 0 | OL17: 0 | OM17: 0 | ON17: 0 | OO17: 0 | OP17: 0 | OQ17: 0 | OR17: 0 | OS17: 0 | OT17: 0 | OU17: 0 | OV17: 0 | OW17: 0 | OX17: 0 | OY17: 0 | OZ17: 0 | PA17: 0 | PB17: 0 | PC17: 0 | PD17: 0 | PE17: 0 | PF17: 0 | PG17: 0 | PH17: 0 | PI17: 0 | PJ17: 0 | PK17: 0 | PL17: 0 | PM17: 0 | PN17: 0 | PO17: 0 | PP17: 0 | PQ17: 0 | PR17: 0 | PS17: 0 | PT17: 0 | PU17: 0 | PV17: 0 | PW17: 0 | PX17: 0 | PY17: 0 | PZ17: 0 | QA17: 0 | QB17: 0 | QC17: 0 | QD17: 0 | QE17: 0 | QF17: 0 | QG17: 0 | QH17: 0 | QI17: 0 | QJ17: 0 | QK17: 0 | QL17: 0 | QM17: 0 | QN17: 0 | QO17: 0 | QP17: 0 | QQ17: 0 | QR17: 0 | QS17: 0 | QT17: 0 | QU17: 0 | QV17: 0 | QW17: 0 | QX17: 0 | QY17: 0 | QZ17: 0 | RA17: 0 | RB17: 0 | RC17: 0 | RD17: 0 | RE17: 0 | RF17: 0 | RG17: 0 | RH17: 0 | RI17: 0 | RJ17: 0 | RK17: 0 | RL17: 0 | RM17: 0 | RN17: 0 | RO17: 0 | RP17: 0 | RQ17: 0 | RR17: 0 | RS17: 0 | RT17: 0 | RU17: 0 | RV17: 0 | RW17: 0 | RX17: 0 | RY17: 0 | RZ17: 0 | SA17: 0 | SB17: 0 | SC17: 0 | SD17: 0 | SE17: 0 | SF17: 0 | SG17: 0 | SH17: 0 | SI17: 0 | SJ17: 0 | SK17: 0 | SL17: 0 | SM17: 0 | SN17: 0 | SO17: 0 | SP17: 0 | SQ17: 0 | SR17: 0 | SS17: 0 | ST17: 0 | SU17: 0 | SV17: 0 | SW17: 0 | SX17: 0 | SY17: 0 | SZ17: 0 | TA17: 0 | TB17: 0 | TC17: 0 | TD17: 0 | TE17: 0 | TF17: 0 | TG17: 0 | TH17: 0 | TI17: 0 | TJ17: 0 | TK17: 0 | TL17: 0 | TM17: 0 | TN17: 0 | TO17: 0 | TP17: 0 | TQ17: 0 | TR17: 0 | TS17: 0 | TT17: 0 | TU17: 0 | TV17: 0 | TW17: 0 | TX17: 0 | TY17: 0 | TZ17: 0 | UA17: 0 | UB17: 0 | UC17: 0 | UD17: 0 | UE17: 0 | UF17: 0 | UG17: 0 | UH17: 0 | UI17: 0 | UJ17: 0 | UK17: 0 | UL17: 0 | UM17: 0 | UN17: 0 | UO17: 0 | UP17: 0 | UQ17: 0 | UR17: 0 | US17: 0 | UT17: 0 | UU17: 0 | UV17: 0 | UW17: 0 | UX17: 0 | UY17: 0 | UZ17: 0 | VA17: 0 | VB17: 0 | VC17: 0 | VD17: 0 | VE17: 0 | VF17: 0 | VG17: 0 | VH17: 0 | VI17: 0 | VJ17: 0 | VK17: 0 | VL17: 0 | VM17: 0 | VN17: 0 | VO17: 0 | VP17: 0 | VQ17: 0 | VR17: 0 | VS17: 0 | VT17: 0 | VU17: 0 | VV17: 0 | VW17: 0 | VX17: 0 | VY17: 0 | VZ17: 0 | WA17: 0 | WB17: 0 | WC17: 0 | WD17: 0 | WE17: 0 | WF17: 0 | WG17: 0 | WH17: 0 | WI17: 0 | WJ17: 0 | WK17: 0 | WL17: 0 | WM17: 0 | WN17: 0 | WO17: 0 | WP17: 0 | WQ17: 0 | WR17: 0 | WS17: 0 | WT17: 0 | WU17: 0 | WV17: 0 | WW17: 0 | WX17: 0 | WY17: 0 | WZ17: 0 | XA17: 0 | XB17: 0 | XC17: 0 | XD17: 0 | XE17: 0 | XF17: 0 | XG17: 0 | XH17: 0 | XI17: 0 | XJ17: 0 | XK17: 0 | XL17: 0 | XM17: 0 | XN17: 0 | XO17: 0 | XP17: 0 | XQ17: 0 | XR17: 0 | XS17: 0 | XT17: 0 | XU17: 0 | XV17: 0 | XW17: 0 | XX17: 0 | XY17: 0 | XZ17: 0 | YA17: 0 | YB17: 0 | YC17: 0 | YD17: 0 | YE17: 0 | YF17: 0 | YG17: 0 | YH17: 0 | YI17: 0 | YJ17: 0 | YK17: 0 | YL17: 0 | YM17: 0 | YN17: 0 | YO17: 0 | YP17: 0 | YQ17: 0 | YR17: 0 | YS17: 0 | YT17: 0 | YU17: 0 | YV17: 0 | YW17: 0 | YX17: 0 | YY17: 0 | YZ17: 0 | ZA17: 0 | ZB17: 0 | ZC17: 0 | ZD17: 0 | ZE17: 0 | ZF17: 0 | ZG17: 0 | ZH17: 0 | ZI17: 0 | ZJ17: 0 | ZK17: 0 | ZL17: 0 | ZM17: 0 | ZN17: 0 | ZO17: 0 | ZP17: 0 | ZQ17: 0 | ZR17: 0 | ZS17: 0 | ZT17: 0 | ZU17: 0 | ZV17: 0 | ZW17: 0 | ZX17: 0 | ZY17: 0 | ZZ17: 0 | AAA17: 0 | AAB17: 0 | AAC17: 0 | AAD17: 0 | AAE17: 0 | AAF17: 0 | AAG17: 0 | AAH17: 0 | AAI17: 0 | AAJ17: 0 | AAK17: 0 | AAL17: 0 | AAM17: 0 | AAN17: 0 | AAO17: 0 | AAP17: 0 | AAQ17: =IF(LEFT($C17,5)="Total",0,IF(COUNTIF(ENTRY!$G$3:$BM$3,AAQ$1)=0,"CopyPasteValue",IFERROR(HLOOKUP(AAQ$1,ENTRY!$G$3:$BI$133,SUMIFS(ENTRY!$A$2:$A$133,ENTRY!$B$2:$B$133,$B17,ENTRY!$C$2:$C$133,$C17)-2,FALSE),0))) -> 0 | AAR17: =IF(LEFT($C17,5)="Total",0,IF(COUNTIF(ENTRY!$G$3:$BM$3,AAR$1)=0,"CopyPasteValue",IFERROR(HLOOKUP(AAR$1,ENTRY!$G$3:$BI$133,SUMIFS(ENTRY!$A$2:$A$133,ENTRY!$B$2:$B$133,$B17,ENTRY!$C$2:$C$133,$C17)-2,FALSE),0))) -> 0 | AAS17: =IF(LEFT($C17,5)="Total",0,IF(COUNTIF(ENTRY!$G$3:$BM$3,AAS$1)=0,"CopyPasteValue",IFERROR(HLOOKUP(AAS$1,ENTRY!$G$3:$BI$133,SUMIFS(ENTRY!$A$2:$A$133,ENTRY!$B$2:$B$133,$B17,ENTRY!$C$2:$C$133,$C17)-2,FALSE),0))) -> 0 | AAT17: =IF(LEFT($C17,5)="Total",0,IF(COUNTIF(ENTRY!$G$3:$BM$3,AAT$1)=0,"CopyPasteValue",IFERROR(HLOOKUP(AAT$1,ENTRY!$G$3:$BI$133,SUMIFS(ENTRY!$A$2:$A$133,ENTRY!$B$2:$B$133,$B17,ENTRY!$C$2:$C$133,$C17)-2,FALSE),0))) -> 0 | AAU17: =IF(LEFT($C17,5)="Total",0,IF(COUNTIF(ENTRY!$G$3:$BM$3,AAU$1)=0,"CopyPasteValue",IFERROR(HLOOKUP(AAU$1,ENTRY!$G$3:$BI$133,SUMIFS(ENTRY!$A$2:$A$133,ENTRY!$B$2:$B$133,$B17,ENTRY!$C$2:$C$133,$C17)-2,FALSE),0))) -> 0 | AAV17: =IF(LEFT($C17,5)="Total",0,IF(COUNTIF(ENTRY!$G$3:$BM$3,AAV$1)=0,"CopyPasteValue",IFERROR(HLOOKUP(AAV$1,ENTRY!$G$3:$BI$133,SUMIFS(ENTRY!$A$2:$A$133,ENTRY!$B$2:$B$133,$B17,ENTRY!$C$2:$C$133,$C17)-2,FALSE),0))) -> 0 | AAW17: =IF(LEFT($C17,5)="Total",0,IF(COUNTIF(ENTRY!$G$3:$BM$3,AAW$1)=0,"CopyPasteValue",IFERROR(HLOOKUP(AAW$1,ENTRY!$G$3:$BI$133,SUMIFS(ENTRY!$A$2:$A$133,ENTRY!$B$2:$B$133,$B17,ENTRY!$C$2:$C$133,$C17)-2,FALSE),0))) -> 0 | AAX17: =IF(LEFT($C17,5)="Total",0,IF(COUNTIF(ENTRY!$G$3:$BM$3,AAX$1)=0,"CopyPasteValue",IFERROR(HLOOKUP(AAX$1,ENTRY!$G$3:$BI$133,SUMIFS(ENTRY!$A$2:$A$133,ENTRY!$B$2:$B$133,$B17,ENTRY!$C$2:$C$133,$C17)-2,FALSE),0))) -> 0 | ... ABH17: =IF(LEFT($C17,5)="Total",0,IF(COUNTIF(ENTRY!$G$3:$BM$3,ABH$1)=0,"CopyPasteValue",IFERROR(HLOOKUP(ABH$1,ENTRY!$G$3:$BI$133,SUMIFS(ENTRY!$A$2:$A$133,ENTRY!$B$2:$B$133,$B17,ENTRY!$C$2:$C$133,$C17)-2,FALSE),0))) -> 0
B18: GC-Hand Bags | C18: HB3 | D18: =CELL("row",D18) -> 18 | E18: =COUNTIF(ENTRY!C$4:C$294,C18) -> 1 | F18: 0 | G18: 0 | H18: 0 | I18: 0 | J18: 1 | K18: 1 | L18: 0 | M18: 0 | N18: 0 | O18: 0 | P18: 0 | Q18: 0 | R18: 0 | S18: 0 | T18: 0 | U18: 0 | V18: 0 | W18: 0 | X18: 0 | Y18: 0 | Z18: 0 | AA18: 0 | AB18: 0 | AC18: 0 | AD18: 0 | AE18: 1 | AF18: 0 | AG18: 0 | AH18: 0 | AI18: 0 | AJ18: 0 | AK18: 0 | AL18: 0 | AM18: 0 | AN18: 0 | AO18: 0 | AP18: 0 | AQ18: 0 | AR18: 0 | AS18: 0 | AT18: 0 | AU18: 0 | AV18: 0 | AW18: 1 | AX18: 0 | AY18: 0 | AZ18: 0 | BA18: 1 | BB18: 0 | BC18: 0 | BD18: 0 | BE18: 0 | BF18: 0 | BG18: 0 | BH18: 1 | BI18: 0 | BJ18: 1 | BK18: 0 | BL18: 0 | BM18: 0 | BN18: 0 | BO18: 0 | BP18: 0 | BQ18: 0 | BR18: 0 | BS18: 0 | BT18: 3 | BU18: 0 | BV18: 0 | BW18: 0 | BX18: 0 | BY18: 0 | BZ18: 2 | CA18: 0 | CB18: 0 | CC18: 0 | CD18: 0 | CE18: 0 | CF18: 4 | CG18: 0 | CH18: 1 | CI18: 0 | CJ18: 0 | CK18: 0 | CL18: 0 | CM18: 3 | CN18: 0 | CO18: 0 | CP18: 0 | CQ18: 0 | CR18: 0 | CS18: 2 | CT18: 5 | CU18: 0 | CV18: 0 | CW18: 1 | CX18: 0 | CY18: 0 | CZ18: 0 | DA18: 1 | DB18: 0 | DC18: 0 | DD18: 0 | DE18: 0 | DF18: 0 | DG18: 0 | DH18: 2 | DI18: 0 | DJ18: 0 | DK18: 1 | DL18: 0 | DM18: 0 | DN18: 1 | DO18: 0 | DP18: 4 | DQ18: 0 | DR18: 1 | DS18: 0 | DT18: 0 | DU18: 0 | DV18: 2 | DW18: 0 | DX18: 5 | DY18: 1 | DZ18: 2 | EA18: 0 | EB18: 0 | EC18: 1 | ED18: 0 | EE18: 5 | EF18: 1 | EG18: 0 | EH18: 0 | EI18: 0 | EJ18: 0 | EK18: 0 | EL18: 0 | EM18: 0 | EN18: 0 | EO18: 0 | EP18: 0 | EQ18: 0 | ER18: 0 | ES18: 0 | ET18: 0 | EU18: 0 | EV18: 0 | EW18: 0 | EX18: 0 | EY18: 0 | EZ18: 0 | FA18: 0 | FB18: 0 | FC18: 0 | FD18: 0 | FE18: 0 | FF18: 0 | FG18: 0 | FH18: 0 | FI18: 0 | FJ18: 0 | FK18: 0 | FL18: 0 | FM18: 0 | FN18: 0 | FO18: 0 | FP18: 0 | FQ18: 0 | FR18: 0 | FS18: 0 | FT18: 0 | FU18: 0 | FV18: 0 | FW18: 0 | FX18: 0 | FY18: 4 | FZ18: 0 | GA18: 0 | GB18: 0 | GC18: 0 | GD18: 0 | GE18: 0 | GF18: 0 | GG18: 0 | GH18: 0 | GI18: 0 | GJ18: 0 | GK18: 0 | GL18: 0 | GM18: 4 | GN18: 0 | GO18: 0 | GP18: 0 | GQ18: 0 | GR18: 0 | GS18: 0 | GT18: 0 | GU18: 0 | GV18: 0 | GW18: 0 | GX18: 2 | GY18: 0 | GZ18: 0 | HA18: 0 | HB18: 0 | HC18: 0 | HD18: 0 | HE18: 0 | HF18: 0 | HG18: 0 | HH18: 0 | HI18: 0 | HJ18: 0 | HK18: 0 | HL18: 0 | HM18: 0 | HN18: 0 | HO18: 0 | HP18: 0 | HQ18: 0 | HR18: 0 | HS18: 0 | HT18: 0 | HU18: 0 | HV18: 0 | HW18: 0 | HX18: 0 | HY18: 0 | HZ18: 2 | IA18: 0 | IB18: 0 | IC18: 0 | ID18: 1 | IE18: 2 | IF18: 0 | IG18: 0 | IH18: 0 | II18: 0 | IJ18: 1 | IK18: 0 | IL18: 0 | IM18: 0 | IN18: 0 | IO18: 0 | IP18: 0 | IQ18: 0 | IR18: 0 | IS18: 0 | IT18: 0 | IU18: 0 | IV18: 0 | IW18: 0 | IX18: 0 | IY18: 0 | IZ18: 0 | JA18: 0 | JB18: 0 | JC18: 0 | JD18: 0 | JE18: 0 | JF18: 0 | JG18: 0 | JH18: 0 | JI18: 0 | JJ18: 0 | JK18: 0 | JL18: 0 | JM18: 0 | JN18: 0 | JO18: 0 | JP18: 0 | JQ18: 0 | JR18: 0 | JS18: 0 | JT18: 0 | JU18: 0 | JV18: 0 | JW18: 0 | JX18: 0 | JY18: 0 | JZ18: 0 | KA18: 0 | KB18: 0 | KC18: 0 | KD18: 0 | KE18: 0 | KF18: 0 | KG18: 0 | KH18: 0 | KI18: 0 | KJ18: 0 | KK18: 0 | KL18: 0 | KM18: 0 | KN18: 0 | KO18: 0 | KP18: 0 | KQ18: 0 | KR18: 0 | KS18: 0 | KT18: 0 | KU18: 0 | KV18: 0 | KW18: 0 | KX18: 0 | KY18: 2 | KZ18: 0 | LA18: 0 | LB18: 0 | LC18: 0 | LD18: 0 | LE18: 0 | LF18: 0 | LG18: 0 | LH18: 0 | LI18: 0 | LJ18: 0 | LK18: 0 | LL18: 0 | LM18: 0 | LN18: 0 | LO18: 0 | LP18: 0 | LQ18: 0 | LR18: 0 | LS18: 0 | LT18: 0 | LU18: 0 | LV18: 0 | LW18: 0 | LX18: 0 | LY18: 0 | LZ18: 0 | MA18: 0 | MB18: 0 | MC18: 0 | MD18: 6 | ME18: 0 | MF18: 0 | MG18: 0 | MH18: 0 | MI18: 0 | MJ18: 0 | MK18: 6 | ML18: 0 | MM18: 0 | MN18: 0 | MO18: 0 | MP18: 0 | MQ18: 0 | MR18: 0 | MS18: 0 | MT18: 0 | MU18: 0 | MV18: 0 | MW18: 0 | MX18: 0 | MY18: 5 | MZ18: 0 | NA18: 0 | NB18: 0 | NC18: 0 | ND18: 0 | NE18: 0 | NF18: 0 | NG18: 0 | NH18: 0 | NI18: 0 | NJ18: 0 | NK18: 0 | NL18: 0 | NM18: 1 | NN18: 0 | NO18: 1 | NP18: 0 | NQ18: 0 | NR18: 0 | NS18: 0 | NT18: 4 | NU18: 0 | NV18: 0 | NW18: 0 | NX18: 0 | NY18: 0 | NZ18: 0 | OA18: 5 | OB18: 0 | OC18: 0 | OD18: 0 | OE18: 0 | OF18: 0 | OG18: 0 | OH18: 0 | OI18: 0 | OJ18: 0 | OK18: 0 | OL18: 0 | OM18: 0 | ON18: 0 | OO18: 3 | OP18: 0 | OQ18: 0 | OR18: 0 | OS18: 0 | OT18: 0 | OU18: 0 | OV18: 2 | OW18: 0 | OX18: 0 | OY18: 1 | OZ18: 0 | PA18: 0 | PB18: 0 | PC18: 6 | PD18: 0 | PE18: 0 | PF18: 0 | PG18: 1 | PH18: 0 | PI18: 0 | PJ18: 6 | PK18: 0 | PL18: 0 | PM18: 0 | PN18: 0 | PO18: 0 | PP18: 0 | PQ18: 4 | PR18: 0 | PS18: 0 | PT18: 0 | PU18: 0 | PV18: 0 | PW18: 0 | PX18: 1 | PY18: 0 | PZ18: 0 | QA18: 0 | QB18: 0 | QC18: 0 | QD18: 0 | QE18: 0 | QF18: 0 | QG18: 0 | QH18: 0 | QI18: 0 | QJ18: 0 | QK18: 0 | QL18: 0 | QM18: 0 | QN18: 0 | QO18: 0 | QP18: 0 | QQ18: 0 | QR18: 0 | QS18: 0 | QT18: 0 | QU18: 0 | QV18: 0 | QW18: 0 | QX18: 0 | QY18: 0 | QZ18: 0 | RA18: 1 | RB18: 0 | RC18: 0 | RD18: 0 | RE18: 0 | RF18: 0 | RG18: 6 | RH18: 0 | RI18: 0 | RJ18: 0 | RK18: 0 | RL18: 0 | RM18: 0 | RN18: 5 | RO18: 0 | RP18: 0 | RQ18: 0 | RR18: 0 | RS18: 0 | RT18: 0 | RU18: 1 | RV18: 0 | RW18: 0 | RX18: 0 | RY18: 0 | RZ18: 0 | SA18: 0 | SB18: 0 | SC18: 0 | SD18: 0 | SE18: 0 | SF18: 0 | SG18: 0 | SH18: 0 | SI18: 0 | SJ18: 0 | SK18: 0 | SL18: 0 | SM18: 0 | SN18: 0 | SO18: 0 | SP18: 0 | SQ18: 0 | SR18: 0 | SS18: 0 | ST18: 0 | SU18: 0 | SV18: 0 | SW18: 0 | SX18: 0 | SY18: 0 | SZ18: 0 | TA18: 0 | TB18: 0 | TC18: 0 | TD18: 0 | TE18: 0 | TF18: 0 | TG18: 0 | TH18: 0 | TI18: 1 | TJ18: 0 | TK18: 0 | TL18: 0 | TM18: 0 | TN18: 0 | TO18: 1 | TP18: 0 | TQ18: 0 | TR18: 0 | TS18: 0 | TT18: 0 | TU18: 0 | TV18: 0 | TW18: 0 | TX18: 0 | TY18: 0 | TZ18: 0 | UA18: 0 | UB18: 0 | UC18: 0 | UD18: 0 | UE18: 0 | UF18: 0 | UG18: 0 | UH18: 0 | UI18: 0 | UJ18: 0 | UK18: 0 | UL18: 0 | UM18: 0 | UN18: 0 | UO18: 0 | UP18: 0 | UQ18: 0 | UR18: 0 | US18: 0 | UT18: 0 | UU18: 0 | UV18: 2 | UW18: 0 | UX18: 1 | UY18: 0 | UZ18: 26 | VA18: 0 | VB18: 0 | VC18: 0 | VD18: 0 | VE18: 0 | VF18: 0 | VG18: 0 | VH18: 0 | VI18: 0 | VJ18: 0 | VK18: 0 | VL18: 0 | VM18: 2 | VN18: 1 | VO18: 0 | VP18: 0 | VQ18: 0 | VR18: 0 | VS18: 0 | VT18: 0 | VU18: 1 | VV18: 0 | VW18: 0 | VX18: 1 | VY18: 0 | VZ18: 0 | WA18: 5 | WB18: 6 | WC18: 1 | WD18: 0 | WE18: 11 | WF18: 0 | WG18: 0 | WH18: 0 | WI18: 0 | WJ18: 0 | WK18: 0 | WL18: 0 | WM18: 0 | WN18: 0 | WO18: 0 | WP18: 0 | WQ18: 0 | WR18: 0 | WS18: 0 | WT18: 0 | WU18: 0 | WV18: 0 | WW18: 0 | WX18: 0 | WY18: 0 | WZ18: 0 | XA18: 0 | XB18: 1 | XC18: 0 | XD18: 0 | XE18: 0 | XF18: 0 | XG18: 0 | XH18: 0 | XI18: 0 | XJ18: 1 | XK18: 0 | XL18: 0 | XM18: 0 | XN18: 0 | XO18: 3 | XP18: 0 | XQ18: 1 | XR18: 1 | XS18: 1 | XT18: 0 | XU18: 0 | XV18: 1 | XW18: 0 | XX18: 1 | XY18: 2 | XZ18: 0 | YA18: 0 | YB18: 0 | YC18: 0 | YD18: 0 | YE18: 1 | YF18: 1 | YG18: 0 | YH18: 0 | YI18: 1 | YJ18: 0 | YK18: 0 | YL18: 2 | YM18: 0 | YN18: 1 | YO18: 0 | YP18: 0 | YQ18: 0 | YR18: 0 | YS18: 15 | YT18: 1 | YU18: 0 | YV18: 0 | YW18: 0 | YX18: 2 | YY18: 0 | YZ18: 0 | ZA18: 1 | ZB18: 2 | ZC18: 0 | ZD18: 0 | ZE18: 0 | ZF18: 0 | ZG18: 2 | ZH18: 0 | ZI18: 0 | ZJ18: 0 | ZK18: 0 | ZL18: 1 | ZM18: 0 | ZN18: 1 | ZO18: 0 | ZP18: 1 | ZQ18: 0 | ZR18: 1 | ZS18: 0 | ZT18: 2 | ZU18: 0 | ZV18: 1 | ZW18: 0 | ZX18: 0 | ZY18: 4 | ZZ18: 0 | AAA18: 0 | AAB18: 1 | AAC18: 0 | AAD18: 1 | AAE18: 0 | AAF18: 4 | AAG18: 0 | AAH18: 0 | AAI18: 0 | AAJ18: 0 | AAK18: 0 | AAL18: 0 | AAM18: 0 | AAN18: 1 | AAO18: 0 | AAP18: 0 | AAQ18: =IF(LEFT($C18,5)="Total",0,IF(COUNTIF(ENTRY!$G$3:$BM$3,AAQ$1)=0,"CopyPasteValue",IFERROR(HLOOKUP(AAQ$1,ENTRY!$G$3:$BI$133,SUMIFS(ENTRY!$A$2:$A$133,ENTRY!$B$2:$B$133,$B18,ENTRY!$C$2:$C$133,$C18)-2,FALSE),0))) -> 1 | AAR18: =IF(LEFT($C18,5)="Total",0,IF(COUNTIF(ENTRY!$G$3:$BM$3,AAR$1)=0,"CopyPasteValue",IFERROR(HLOOKUP(AAR$1,ENTRY!$G$3:$BI$133,SUMIFS(ENTRY!$A$2:$A$133,ENTRY!$B$2:$B$133,$B18,ENTRY!$C$2:$C$133,$C18)-2,FALSE),0))) -> 0 | AAS18: =IF(LEFT($C18,5)="Total",0,IF(COUNTIF(ENTRY!$G$3:$BM$3,AAS$1)=0,"CopyPasteValue",IFERROR(HLOOKUP(AAS$1,ENTRY!$G$3:$BI$133,SUMIFS(ENTRY!$A$2:$A$133,ENTRY!$B$2:$B$133,$B18,ENTRY!$C$2:$C$133,$C18)-2,FALSE),0))) -> 0 | AAT18: =IF(LEFT($C18,5)="Total",0,IF(COUNTIF(ENTRY!$G$3:$BM$3,AAT$1)=0,"CopyPasteValue",IFERROR(HLOOKUP(AAT$1,ENTRY!$G$3:$BI$133,SUMIFS(ENTRY!$A$2:$A$133,ENTRY!$B$2:$B$133,$B18,ENTRY!$C$2:$C$133,$C18)-2,FALSE),0))) -> 1 | AAU18: =IF(LEFT($C18,5)="Total",0,IF(COUNTIF(ENTRY!$G$3:$BM$3,AAU$1)=0,"CopyPasteValue",IFERROR(HLOOKUP(AAU$1,ENTRY!$G$3:$BI$133,SUMIFS(ENTRY!$A$2:$A$133,ENTRY!$B$2:$B$133,$B18,ENTRY!$C$2:$C$133,$C18)-2,FALSE),0))) -> 0 | AAV18: =IF(LEFT($C18,5)="Total",0,IF(COUNTIF(ENTRY!$G$3:$BM$3,AAV$1)=0,"CopyPasteValue",IFERROR(HLOOKUP(AAV$1,ENTRY!$G$3:$BI$133,SUMIFS(ENTRY!$A$2:$A$133,ENTRY!$B$2:$B$133,$B18,ENTRY!$C$2:$C$133,$C18)-2,FALSE),0))) -> 0 | AAW18: =IF(LEFT($C18,5)="Total",0,IF(COUNTIF(ENTRY!$G$3:$BM$3,AAW$1)=0,"CopyPasteValue",IFERROR(HLOOKUP(AAW$1,ENTRY!$G$3:$BI$133,SUMIFS(ENTRY!$A$2:$A$133,ENTRY!$B$2:$B$133,$B18,ENTRY!$C$2:$C$133,$C18)-2,FALSE),0))) -> 0 | AAX18: =IF(LEFT($C18,5)="Total",0,IF(COUNTIF(ENTRY!$G$3:$BM$3,AAX$1)=0,"CopyPasteValue",IFERROR(HLOOKUP(AAX$1,ENTRY!$G$3:$BI$133,SUMIFS(ENTRY!$A$2:$A$133,ENTRY!$B$2:$B$133,$B18,ENTRY!$C$2:$C$133,$C18)-2,FALSE),0))) -> 1 | ... ABH18: =IF(LEFT($C18,5)="Total",0,IF(COUNTIF(ENTRY!$G$3:$BM$3,ABH$1)=0,"CopyPasteValue",IFERROR(HLOOKUP(ABH$1,ENTRY!$G$3:$BI$133,SUMIFS(ENTRY!$A$2:$A$133,ENTRY!$B$2:$B$133,$B18,ENTRY!$C$2:$C$133,$C18)-2,FALSE),0))) -> 0
B19: GC-Hand Bags | C19: SchoolBag No.1-Bale | D19: =CELL("row",D19) -> 19 | E19: =COUNTIF(ENTRY!C$4:C$294,C19) -> 0 | F19: 0 | G19: 0 | H19: 0 | I19: 0 | J19: 0 | K19: 0 | L19: 0 | M19: 0 | N19: 0 | O19: 0 | P19: 0 | Q19: 0 | R19: 0 | S19: 0 | T19: 0 | U19: 0 | V19: 0 | W19: 0 | X19: 0 | Y19: 0 | Z19: 0 | AA19: 0 | AB19: 0 | AC19: 0 | AD19: 0 | AE19: 0 | AF19: 0 | AG19: 0 | AH19: 0 | AI19: 0 | AJ19: 0 | AK19: 0 | AL19: 0 | AM19: 0 | AN19: 0 | AO19: 0 | AP19: 0 | AQ19: 0 | AR19: 0 | AS19: 0 | AT19: 0 | AU19: 0 | AV19: 0 | AW19: 0 | AX19: 0 | AY19: 0 | AZ19: 0 | BA19: 0 | BB19: 0 | BC19: 0 | BD19: 0 | BE19: 0 | BF19: 0 | BG19: 0 | BH19: 0 | BI19: 0 | BJ19: 0 | BK19: 0 | BL19: 0 | BM19: 0 | BN19: 0 | BO19: 0 | BP19: 0 | BQ19: 0 | BR19: 0 | BS19: 0 | BT19: 0 | BU19: 0 | BV19: 0 | BW19: 0 | BX19: 0 | BY19: 0 | BZ19: 0 | CA19: 0 | CB19: 0 | CC19: 0 | CD19: 0 | CE19: 0 | CF19: 0 | CG19: 0 | CH19: 0 | CI19: 0 | CJ19: 0 | CK19: 0 | CL19: 0 | CM19: 0 | CN19: 0 | CO19: 0 | CP19: 0 | CQ19: 0 | CR19: 0 | CS19: 0 | CT19: 0 | CU19: 0 | CV19: 0 | CW19: 0 | CX19: 0 | CY19: 0 | CZ19: 0 | DA19: 0 | DB19: 0 | DC19: 0 | DD19: 0 | DE19: 0 | DF19: 0 | DG19: 0 | DH19: 0 | DI19: 0 | DJ19: 0 | DK19: 0 | DL19: 0 | DM19: 0 | DN19: 0 | DO19: 0 | DP19: 0 | DQ19: 0 | DR19: 0 | DS19: 0 | DT19: 0 | DU19: 0 | DV19: 0 | DW19: 0 | DX19: 0 | DY19: 0 | DZ19: 0 | EA19: 0 | EB19: 0 | EC19: 0 | ED19: 0 | EE19: 0 | EF19: 0 | EG19: 0 | EH19: 0 | EI19: 0 | EJ19: 0 | EK19: 0 | EL19: 0 | EM19: 0 | EN19: 0 | EO19: 0 | EP19: 0 | EQ19: 0 | ER19: 0 | ES19: 0 | ET19: 0 | EU19: 0 | EV19: 0 | EW19: 0 | EX19: 0 | EY19: 0 | EZ19: 0 | FA19: 0 | FB19: 0 | FC19: 0 | FD19: 0 | FE19: 0 | FF19: 0 | FG19: 0 | FH19: 0 | FI19: 0 | FJ19: 0 | FK19: 0 | FL19: 0 | FM19: 0 | FN19: 0 | FO19: 0 | FP19: 0 | FQ19: 0 | FR19: 0 | FS19: 0 | FT19: 0 | FU19: 0 | FV19: 0 | FW19: 0 | FX19: 0 | FY19: 0 | FZ19: 0 | GA19: 0 | GB19: 0 | GC19: 0 | GD19: 0 | GE19: 0 | GF19: 0 | GG19: 0 | GH19: 0 | GI19: 0 | GJ19: 0 | GK19: 0 | GL19: 0 | GM19: 0 | GN19: 0 | GO19: 0 | GP19: 0 | GQ19: 0 | GR19: 0 | GS19: 0 | GT19: 0 | GU19: 0 | GV19: 0 | GW19: 0 | GX19: 0 | GY19: 0 | GZ19: 0 | HA19: 0 | HB19: 0 | HC19: 0 | HD19: 0 | HE19: 0 | HF19: 0 | HG19: 0 | HH19: 0 | HI19: 0 | HJ19: 0 | HK19: 0 | HL19: 0 | HM19: 0 | HN19: 0 | HO19: 0 | HP19: 0 | HQ19: 0 | HR19: 0 | HS19: 0 | HT19: 0 | HU19: 0 | HV19: 0 | HW19: 0 | HX19: 0 | HY19: 0 | HZ19: 0 | IA19: 0 | IB19: 0 | IC19: 0 | ID19: 0 | IE19: 0 | IF19: 0 | IG19: 0 | IH19: 0 | II19: 0 | IJ19: 0 | IK19: 0 | IL19: 0 | IM19: 0 | IN19: 0 | IO19: 0 | IP19: 0 | IQ19: 0 | IR19: 0 | IS19: 0 | IT19: 0 | IU19: 0 | IV19: 0 | IW19: 0 | IX19: 0 | IY19: 0 | IZ19: 0 | JA19: 0 | JB19: 0 | JC19: 0 | JD19: 0 | JE19: 0 | JF19: 0 | JG19: 0 | JH19: 0 | JI19: 0 | JJ19: 0 | JK19: 0 | JL19: 0 | JM19: 0 | JN19: 0 | JO19: 0 | JP19: 0 | JQ19: 0 | JR19: 0 | JS19: 0 | JT19: 0 | JU19: 0 | JV19: 0 | JW19: 0 | JX19: 0 | JY19: 0 | JZ19: 0 | KA19: 0 | KB19: 0 | KC19: 0 | KD19: 0 | KE19: 0 | KF19: 0 | KG19: 0 | KH19: 0 | KI19: 0 | KJ19: 0 | KK19: 0 | KL19: 0 | KM19: 0 | KN19: 0 | KO19: 0 | KP19: 0 | KQ19: 0 | KR19: 0 | KS19: 0 | KT19: 0 | KU19: 0 | KV19: 0 | KW19: 0 | KX19: 0 | KY19: 0 | KZ19: 0 | LA19: 0 | LB19: 0 | LC19: 0 | LD19: 0 | LE19: 0 | LF19: 0 | LG19: 0 | LH19: 0 | LI19: 0 | LJ19: 0 | LK19: 0 | LL19: 0 | LM19: 0 | LN19: 0 | LO19: 0 | LP19: 0 | LQ19: 0 | LR19: 0 | LS19: 0 | LT19: 0 | LU19: 0 | LV19: 0 | LW19: 0 | LX19: 0 | LY19: 0 | LZ19: 0 | MA19: 0 | MB19: 0 | MC19: 0 | MD19: 0 | ME19: 0 | MF19: 0 | MG19: 0 | MH19: 0 | MI19: 0 | MJ19: 0 | MK19: 0 | ML19: 0 | MM19: 0 | MN19: 0 | MO19: 0 | MP19: 0 | MQ19: 0 | MR19: 0 | MS19: 0 | MT19: 0 | MU19: 0 | MV19: 0 | MW19: 0 | MX19: 0 | MY19: 0 | MZ19: 0 | NA19: 0 | NB19: 0 | NC19: 0 | ND19: 0 | NE19: 0 | NF19: 0 | NG19: 0 | NH19: 0 | NI19: 0 | NJ19: 0 | NK19: 0 | NL19: 0 | NM19: 0 | NN19: 0 | NO19: 0 | NP19: 0 | NQ19: 0 | NR19: 0 | NS19: 0 | NT19: 0 | NU19: 0 | NV19: 0 | NW19: 0 | NX19: 0 | NY19: 0 | NZ19: 0 | OA19: 0 | OB19: 0 | OC19: 0 | OD19: 0 | OE19: 0 | OF19: 0 | OG19: 0 | OH19: 0 | OI19: 0 | OJ19: 0 | OK19: 0 | OL19: 0 | OM19: 0 | ON19: 0 | OO19: 0 | OP19: 0 | OQ19: 0 | OR19: 0 | OS19: 0 | OT19: 0 | OU19: 0 | OV19: 0 | OW19: 0 | OX19: 0 | OY19: 0 | OZ19: 0 | PA19: 0 | PB19: 0 | PC19: 0 | PD19: 0 | PE19: 0 | PF19: 0 | PG19: 0 | PH19: 0 | PI19: 0 | PJ19: 0 | PK19: 0 | PL19: 0 | PM19: 0 | PN19: 0 | PO19: 0 | PP19: 0 | PQ19: 0 | PR19: 0 | PS19: 0 | PT19: 0 | PU19: 0 | PV19: 0 | PW19: 0 | PX19: 0 | PY19: 0 | PZ19: 0 | QA19: 0 | QB19: 0 | QC19: 0 | QD19: 0 | QE19: 0 | QF19: 0 | QG19: 0 | QH19: 0 | QI19: 0 | QJ19: 0 | QK19: 0 | QL19: 0 | QM19: 0 | QN19: 0 | QO19: 0 | QP19: 0 | QQ19: 0 | QR19: 0 | QS19: 0 | QT19: 0 | QU19: 0 | QV19: 0 | QW19: 0 | QX19: 0 | QY19: 0 | QZ19: 0 | RA19: 0 | RB19: 0 | RC19: 0 | RD19: 0 | RE19: 0 | RF19: 0 | RG19: 0 | RH19: 0 | RI19: 0 | RJ19: 0 | RK19: 0 | RL19: 0 | RM19: 0 | RN19: 0 | RO19: 0 | RP19: 0 | RQ19: 0 | RR19: 0 | RS19: 0 | RT19: 0 | RU19: 0 | RV19: 0 | RW19: 0 | RX19: 0 | RY19: 0 | RZ19: 0 | SA19: 0 | SB19: 0 | SC19: 0 | SD19: 0 | SE19: 0 | SF19: 0 | SG19: 0 | SH19: 0 | SI19: 0 | SJ19: 0 | SK19: 0 | SL19: 0 | SM19: 0 | SN19: 0 | SO19: 0 | SP19: 0 | SQ19: 0 | SR19: 0 | SS19: 0 | ST19: 0 | SU19: 0 | SV19: 0 | SW19: 0 | SX19: 0 | SY19: 0 | SZ19: 0 | TA19: 0 | TB19: 0 | TC19: 0 | TD19: 0 | TE19: 0 | TF19: 0 | TG19: 0 | TH19: 0 | TI19: 0 | TJ19: 0 | TK19: 0 | TL19: 0 | TM19: 0 | TN19: 0 | TO19: 0 | TP19: 0 | TQ19: 0 | TR19: 0 | TS19: 0 | TT19: 0 | TU19: 0 | TV19: 0 | TW19: 0 | TX19: 0 | TY19: 0 | TZ19: 0 | UA19: 0 | UB19: 0 | UC19: 0 | UD19: 0 | UE19: 0 | UF19: 0 | UG19: 0 | UH19: 0 | UI19: 0 | UJ19: 0 | UK19: 0 | UL19: 0 | UM19: 0 | UN19: 0 | UO19: 0 | UP19: 0 | UQ19: 0 | UR19: 0 | US19: 0 | UT19: 0 | UU19: 0 | UV19: 0 | UW19: 0 | UX19: 0 | UY19: 0 | UZ19: 0 | VA19: 0 | VB19: 0 | VC19: 0 | VD19: 0 | VE19: 0 | VF19: 0 | VG19: 0 | VH19: 0 | VI19: 0 | VJ19: 0 | VK19: 0 | VL19: 0 | VM19: 0 | VN19: 0 | VO19: 0 | VP19: 0 | VQ19: 0 | VR19: 0 | VS19: 0 | VT19: 0 | VU19: 0 | VV19: 0 | VW19: 0 | VX19: 0 | VY19: 0 | VZ19: 0 | WA19: 0 | WB19: 0 | WC19: 0 | WD19: 0 | WE19: 0 | WF19: 0 | WG19: 0 | WH19: 0 | WI19: 0 | WJ19: 0 | WK19: 0 | WL19: 0 | WM19: 0 | WN19: 0 | WO19: 0 | WP19: 0 | WQ19: 0 | WR19: 0 | WS19: 0 | WT19: 0 | WU19: 0 | WV19: 0 | WW19: 0 | WX19: 0 | WY19: 0 | WZ19: 0 | XA19: 0 | XB19: 0 | XC19: 0 | XD19: 0 | XE19: 0 | XF19: 0 | XG19: 0 | XH19: 0 | XI19: 0 | XJ19: 0 | XK19: 0 | XL19: 0 | XM19: 0 | XN19: 0 | XO19: 0 | XP19: 0 | XQ19: 0 | XR19: 0 | XS19: 0 | XT19: 0 | XU19: 0 | XV19: 0 | XW19: 0 | XX19: 0 | XY19: 0 | XZ19: 0 | YA19: 0 | YB19: 0 | YC19: 0 | YD19: 0 | YE19: 0 | YF19: 0 | YG19: 0 | YH19: 0 | YI19: 0 | YJ19: 0 | YK19: 0 | YL19: 0 | YM19: 0 | YN19: 0 | YO19: 0 | YP19: 0 | YQ19: 0 | YR19: 0 | YS19: 0 | YT19: 0 | YU19: 0 | YV19: 0 | YW19: 0 | YX19: 0 | YY19: 0 | YZ19: 0 | ZA19: 0 | ZB19: 0 | ZC19: 0 | ZD19: 0 | ZE19: 0 | ZF19: 0 | ZG19: 0 | ZH19: 0 | ZI19: 0 | ZJ19: 0 | ZK19: 0 | ZL19: 0 | ZM19: 0 | ZN19: 0 | ZO19: 0 | ZP19: 0 | ZQ19: 0 | ZR19: 0 | ZS19: 0 | ZT19: 0 | ZU19: 0 | ZV19: 0 | ZW19: 0 | ZX19: 0 | ZY19: 0 | ZZ19: 0 | AAA19: 0 | AAB19: 0 | AAC19: 0 | AAD19: 0 | AAE19: 0 | AAF19: 0 | AAG19: 0 | AAH19: 0 | AAI19: 0 | AAJ19: 0 | AAK19: 0 | AAL19: 0 | AAM19: 0 | AAN19: 0 | AAO19: 0 | AAP19: 0 | AAQ19: =IF(LEFT($C19,5)="Total",0,IF(COUNTIF(ENTRY!$G$3:$BM$3,AAQ$1)=0,"CopyPasteValue",IFERROR(HLOOKUP(AAQ$1,ENTRY!$G$3:$BI$133,SUMIFS(ENTRY!$A$2:$A$133,ENTRY!$B$2:$B$133,$B19,ENTRY!$C$2:$C$133,$C19)-2,FALSE),0))) -> 0 | AAR19: =IF(LEFT($C19,5)="Total",0,IF(COUNTIF(ENTRY!$G$3:$BM$3,AAR$1)=0,"CopyPasteValue",IFERROR(HLOOKUP(AAR$1,ENTRY!$G$3:$BI$133,SUMIFS(ENTRY!$A$2:$A$133,ENTRY!$B$2:$B$133,$B19,ENTRY!$C$2:$C$133,$C19)-2,FALSE),0))) -> 0 | AAS19: =IF(LEFT($C19,5)="Total",0,IF(COUNTIF(ENTRY!$G$3:$BM$3,AAS$1)=0,"CopyPasteValue",IFERROR(HLOOKUP(AAS$1,ENTRY!$G$3:$BI$133,SUMIFS(ENTRY!$A$2:$A$133,ENTRY!$B$2:$B$133,$B19,ENTRY!$C$2:$C$133,$C19)-2,FALSE),0))) -> 0 | AAT19: =IF(LEFT($C19,5)="Total",0,IF(COUNTIF(ENTRY!$G$3:$BM$3,AAT$1)=0,"CopyPasteValue",IFERROR(HLOOKUP(AAT$1,ENTRY!$G$3:$BI$133,SUMIFS(ENTRY!$A$2:$A$133,ENTRY!$B$2:$B$133,$B19,ENTRY!$C$2:$C$133,$C19)-2,FALSE),0))) -> 0 | AAU19: =IF(LEFT($C19,5)="Total",0,IF(COUNTIF(ENTRY!$G$3:$BM$3,AAU$1)=0,"CopyPasteValue",IFERROR(HLOOKUP(AAU$1,ENTRY!$G$3:$BI$133,SUMIFS(ENTRY!$A$2:$A$133,ENTRY!$B$2:$B$133,$B19,ENTRY!$C$2:$C$133,$C19)-2,FALSE),0))) -> 0 | AAV19: =IF(LEFT($C19,5)="Total",0,IF(COUNTIF(ENTRY!$G$3:$BM$3,AAV$1)=0,"CopyPasteValue",IFERROR(HLOOKUP(AAV$1,ENTRY!$G$3:$BI$133,SUMIFS(ENTRY!$A$2:$A$133,ENTRY!$B$2:$B$133,$B19,ENTRY!$C$2:$C$133,$C19)-2,FALSE),0))) -> 0 | AAW19: =IF(LEFT($C19,5)="Total",0,IF(COUNTIF(ENTRY!$G$3:$BM$3,AAW$1)=0,"CopyPasteValue",IFERROR(HLOOKUP(AAW$1,ENTRY!$G$3:$BI$133,SUMIFS(ENTRY!$A$2:$A$133,ENTRY!$B$2:$B$133,$B19,ENTRY!$C$2:$C$133,$C19)-2,FALSE),0))) -> 0 | AAX19: =IF(LEFT($C19,5)="Total",0,IF(COUNTIF(ENTRY!$G$3:$BM$3,AAX$1)=0,"CopyPasteValue",IFERROR(HLOOKUP(AAX$1,ENTRY!$G$3:$BI$133,SUMIFS(ENTRY!$A$2:$A$133,ENTRY!$B$2:$B$133,$B19,ENTRY!$C$2:$C$133,$C19)-2,FALSE),0))) -> 0 | ... ABH19: =IF(LEFT($C19,5)="Total",0,IF(COUNTIF(ENTRY!$G$3:$BM$3,ABH$1)=0,"CopyPasteValue",IFERROR(HLOOKUP(ABH$1,ENTRY!$G$3:$BI$133,SUMIFS(ENTRY!$A$2:$A$133,ENTRY!$B$2:$B$133,$B19,ENTRY!$C$2:$C$133,$C19)-2,FALSE),0))) -> 0
